Workbook

Sheet Executive Summary
A1: SummitBridge Health Plan
A2: Bending the Medical Cost Curve: A Precision Strategy for High-Cost Utilization, Avoidable Care & Retention
A4: THE BOTTOM LINE
A5: SummitBridge doesn't have a cost problem across the board — it has a concentration problem. In the 2024 book analyzed ($11.3M allowed, 800 members), 76% of spend is inpatient and just 40 members (top 5%) drive 20% of every dollar. The winning move is precision, not broad cuts: wrap the few members who matter, divert the care that shouldn't be in the ED, and stop losing our most expensive members to cost confusion. We identify ~$653K of Year-1 addressable savings (~5.8% of allowed) with a credible path to far more in inpatient/readmission management — all without touching quality.
A7: # | B7: Strategic storyline | C7: What the data shows | D7: Our proposition (action) | E7: Year-1 impact | F7: Owner · horizon
A8: 1 | B8: Build a High-Cost Claimant Command Center | C8: 40 members (top 5%) drive 20.5% of allowed spend, running $5,280 PMPM vs $1,150 for the rest. Their cost is concentrated in inpatient (76% of the book) and oncology/specialty biologics. ▸ National benchmark: the top 5% of Americans drive ~50% of all U.S. health spending (AHRQ MEPS) — concentration is structural, so a focused pod is the highest-ROI lever. | D8: Stand up a concierge care-management pod that owns these 40 members: proactive outreach, site-of-care steering, prior-auth refinement, and readmission prevention. Precision beats population-wide programs. | E8: ="≈ $"&TEXT('Member Spend'!$U$5*0.1,"#,##0")&"/yr from a 10% cut on their $2.3M — more impact than any broad program, from 40 relationships" -> ≈ $231,730/yr from a 10% cut on their $2.3M — more impact than any broad program, from 40 relationships | F8: Care Management · 0–6 mo
A9: 2 | B9: Divert the 3-in-4 ED Visits That Don't Belong There | C9: 914 of 1,209 ED visits (76%) are avoidable or potentially avoidable. The average ED visit costs $1,127 vs $135 in urgent care — an ~8x setting premium. 65+ members and Kentucky are the hotspots. ▸ National benchmark: 155M U.S. ED visits in 2022; ~10% are non-urgent and use skews to age 75+ (CDC NCHS) — our 65+ hotspot mirrors the national pattern. | D9: Launch an ED diversion program: 24/7 nurse triage line, telehealth-first routing, urgent-care steering, and embedded navigators for the 65+/KY hotspots. | E9: ="≈ $"&TEXT('Category Spend'!$B$42,"#,##0")&"/yr diverting just 20% to urgent care; scales with adoption" -> ≈ $181,354/yr diverting just 20% to urgent care; scales with adoption | F9: Population Health · 0–9 mo
A10: 3 | B10: Shift Specialty Pharmacy to Lower-Cost Sites | C10: Specialty Rx is $791K of allowed; oncology biologics alone are 43% of it. These are frequently infused in the highest-cost hospital outpatient setting. ▸ National benchmark: U.S. retail Rx hit $467B in 2024 (+7.9%), the fastest-growing spend category, led by GLP-1/diabetes-obesity drugs (CMS NHE) — the cost curve is steepening. | D10: Refine prior-auth and formulary; steer eligible infusions to home/office and biosimilars. The model quantifies 5/10/15% reductions at $40K/$79K/$119K. | E10: ="Up to $"&TEXT('Category Spend'!$D$31,"#,##0")&"/yr at a 15% specialty Rx reduction; low clinical risk" -> Up to $118,685/yr at a 15% specialty Rx reduction; low clinical risk | F10: Pharmacy · 3–12 mo
A11: 4 | B11: Treat Behavioral Health to Break the ED Cycle | C11: BH isn't cheap because of price ($175/visit, ~PCP level) — it's under-treated: 45% of members touch BH but average only 1.3 visits/yr. BH members average 48% more ED visits (1.83 vs 1.24) with identical inpatient use. ▸ National benchmark: national ED use concentrates in older, complex patients and BH is a recognized ED-diversion lever (CDC; see External Benchmarks tab). | D11: Embed collaborative-care / measurement-based BH with telehealth access and PCP integration to sustain treatment and cut downstream ED use. | E11: ="≈ $"&TEXT(('Behavioral Health'!$B$20*('Behavioral Health'!$B$21-'Behavioral Health'!$C$21))*0.5*'Category Spend'!$E$4,"#,##0")&"/yr in avoided ED if half the excess BH-member ED is prevented" -> ≈ $121,101/yr in avoided ED if half the excess BH-member ED is prevented | F11: Population Health · 6–12 mo
A12: 5 | B12: Retention = Margin: Stop Losing Our Costliest Members | C12: 11.6% disenrolled. Leavers ran 36% higher PMPM ($1,770 vs $1,302) at similar risk — cost exposure, not sickness, drives exits. Premium Affordability + Network/Access account for 71% of stated reasons. ▸ National benchmark: CMS projects ~4.7M Marketplace enrollees will exit when enhanced subsidies expire in 2026 — affordability pressure is systemic, not just ours. | D12: Deploy cost-transparency tools and an in-network care finder; proactively outreach high-PMPM members flagged for affordability; close rural network-adequacy gaps. | E12: Protects renewal revenue on 93 exits and curbs adverse-selection drift; each retained commercial group compounds | F12: Member Experience · 0–6 mo
A14: PRIORITIZED SAVINGS ROADMAP
B15: Initiative | C15: Horizon | D15: Type | E15: Year-1 $
B16: High-cost claimant pod (10% of top-5% spend) | C16: 0–6 mo | D16: Quick win | E16: ='Member Spend'!$U$5*0.1 -> 231730.37
B17: ED diversion to urgent care (20% of avoidable) | C17: 0–9 mo | D17: Quick win | E17: ='Category Spend'!$B$42 -> 181353.58
B18: Specialty Rx site-of-care / biosimilar (15%) | C18: 3–12 mo | D18: Quick win | E18: ='Category Spend'!$D$31 -> 118685.01
B19: BH engagement → downstream ED avoidance | C19: 6–12 mo | D19: Strategic | E19: =('Behavioral Health'!$B$20*('Behavioral Health'!$B$21-'Behavioral Health'!$C$21))*0.5*'Category Spend'!$E$4 -> 121100.91
B20: TOTAL Year-1 addressable savings | E20: =SUM(E16:E19) -> 652869.86
B21: % of total allowed spend | E21: =E20/'Member Spend'!$U$6 -> 0.057667639
B22: ▶ Strategic prize (Phase 2): Inpatient is 76% of allowed ($8.6M). A readmission-reduction + discharge-planning + SNF-at-home program here can exceed all quick wins combined — the biggest curve-bender, flagged for Phase 2.
A24: NOTEWORTHY PROPOSITIONS (the differentiators)
B25: ▪ The 40-Member P&L — A small concierge pod managing 40 members can bend more cost (~$232K) than any plan-wide program. Concentrate resources where the dollars actually are.
B26: ▪ Make triage the front door — An 8x cost gap between the ED ($1,127) and urgent care ($135) means every appropriately diverted visit is near-pure margin.
B27: ▪ Behavioral health is a medical-cost lever, not a carve-out — BH members use 48% more ED. Funding sustained BH treatment is cost avoidance, not just a benefit expense.
B28: ▪ Retention is underwriting — We're shedding members at 36% higher PMPM but similar risk. That is adverse retention; cost-transparency tools are a medical-cost instrument.
B29: ▪ Data as an operating system — A monthly claims + enrollment + provider integration (this workbook) moves utilization management and pricing from retrospective to prospective.
B30: ▪ Quality-neutral by design — None of the ~$653K requires denying care; it is site-of-care, engagement, and steering. Leadership can approve without clinical risk.
A32: WHY THIS WINS
B33: The recommendation is evidence-based (every number traces to the model), quantified (~$653K Year-1, ~5.8% of allowed, with a larger inpatient prize in Phase 2), quality-neutral, prioritized (quick wins vs. strategic), and operationalized — a live dashboard with KPI definitions, refresh cadence, and named owners. It answers all four case tasks and gives leadership a plan they can fund on Monday.
A35: APPENDIX: METHODOLOGY & ASSUMPTIONS
A36: Data & scope | B36: 2024 analytic sample: 800 members · 8,462 member-months · 5,961 claim lines · $11.3M allowed. Primary cost metric = allowed_amount. This is a sample, not the full ~$2.1B / 420K-life book — rates are directional, mix and concentration patterns are the takeaway.
A37: Definitions | B37: PMPM = allowed ÷ member-months. ED/1,000 = (ED claims ÷ member-months) × 1,000. High-cost = top 5% of members by allowed (≥ 95th-pct cutoff, 40 members). Avoidable ED = claims whose primary ICD-10 maps to 'Avoidable'/'Potentially Avoidable' in the reference table. OON = in_network_flag = 'N'.
A38: Joins | B38: claims↔enrollment (member_id): demographics, state, attributed PCP. claims↔avoidable_ed_reference (diagnosis_code_1): ED avoidability. enrollment↔providers (attributed_pcp_npi): PCP quality. spend↔member_months (member_id / calendar_month): exposure & PMPM. All via XLOOKUP/SUMIFS — auditable in helper cols AA:AG on 'claims'.
A39: Savings model | B39: High-cost pod: 10% reduction on top-5% allowed ($2.32M). ED diversion: 20% of avoidable+potentially-avoidable ED visits shifted to urgent care, valued at (avg ED $1,127 − avg UC $135)/visit. Specialty Rx: 5/10/15% reduction on $791K. BH→ED: 50% of excess ED among BH members (1.83 vs 1.24 visits) × avg ED cost. Figures are gross, quality-neutral (site-of-care/engagement, no care denials), pre-implementation cost.
A40: Caveats | B40: Monthly trend charts use Mar–Dec (full 800-member exposure); Jan–Feb excluded (enrollment ramp). OON (55 lines) and some age/state cells are small-sample — treat as directional. 7-day post-ED PCP follow-up and 30-day readmission require visit-sequencing/admission linkage not in this extract — defined as prospective KPIs. Retention impact is framed as protected premium (no premium field to quantify directly).

Sheet External Benchmarks
A1: External Benchmarks — Official & Government Sources
A2: SummitBridge findings validated against national data (AHRQ, CDC/NCHS, CMS, MedPAC). Every benchmark cell carries its source + URL as a comment.
A4: # | B4: Theme | C4: SummitBridge (our data) | D4: National benchmark (official) | E4: Source | F4: Implication / proposition
A5: 1 | B5: High-cost concentration | C5: Top 5% of members = 20.5% of allowed spend; $5,280 vs $1,150 PMPM. | D5: Nationally, the top 5% of people account for ~50% of all U.S. health spending (50.8% in 2015); the bottom 50% just 2.8%. | E5: AHRQ MEPS Stat Brief #506 / #521 | F5: Concentration is structural, not anomalous. A high-cost claimant care pod is the highest-ROI lever — our 20.5% understates the ceiling because our book excludes the uninsured/institutionalized.
A6: 2 | B6: Avoidable ED use | C6: 76% of ED visits avoidable/potentially avoidable; ED $1,127 vs urgent care $135 (8x). | D6: 155 million U.S. ED visits in 2022; ~10% triaged non-urgent; highest visit rate among adults 75+ (76 per 100). | E6: CDC NCHS Data Brief #503 (2024) | F6: ED overuse and an elderly skew are national patterns — our 65+ hotspot mirrors the data. Triage lines + urgent-care/telehealth routing are proven diversion levers.
A7: 3 | B7: Specialty pharmacy trend | C7: Specialty Rx $791K; oncology biologics 43%; GLP-1 a top class. | D7: U.S. retail Rx spending reached $467.0B in 2024 (+7.9%); projected fastest-growing NHE category (5.7%/yr, 2025-34); diabetes/obesity (GLP-1) drugs a key driver. | E7: CMS NHE 2024 Highlights | F7: Specialty/GLP-1 is the steepest national cost curve. PA refinement, biosimilar & site-of-care shifts protect SummitBridge against a trend that is accelerating faster than any other category.
A8: 4 | B8: Inpatient & readmissions | C8: Inpatient = 76% of our allowed spend ($8.6M); the single largest bucket. | D8: ~1 in 5 Medicare patients are readmitted within 30 days; MedPAC estimated ~75% of 30-day readmissions are potentially preventable (~$12B in Medicare spend). | E8: MedPAC (2007 Report to Congress) | F8: The Phase-2 prize. Inpatient dwarfs every quick win; national evidence says most 30-day readmissions are preventable. Discharge planning + transitional care target the largest, most-addressable bucket.
A9: 5 | B9: Retention & affordability | C9: 11.6% disenrollment; leavers 36% higher PMPM; 'Premium Affordability' the #1 exit reason. | D9: CMS projects ~4.7M direct-purchase (Marketplace) enrollees will drop when enhanced subsidies expire in 2026; insured share falls from 91.8% (2024) toward 90.5% (2034). | E9: CMS NHE Projections 2024-33 | F9: Affordability pressure is systemic and about to intensify. Cost-transparency tools + proactive retention outreach to high-PMPM members protect the book precisely as subsidy-driven affordability shocks hit.
A11: BOTTOM LINE: Every SummitBridge storyline is directionally consistent with national government data — our recommendations aren't outliers, they target the same cost drivers CMS, AHRQ, CDC and MedPAC flag nationally.

Sheet README
A1: SummitBridge Health Plan — Medical Cost & Utilization Analysis
A2: Analysis period: Jan 1 – Dec 31, 2024 | Cost metric: allowed_amount | Prepared by: Healthcare Analytics
A4: 1. DATA SOURCES
A5: Sheet | B5: Grain | C5: Rows | D5: Key fields
A6: claims | B6: 1 claim line | C6: =COUNTA(claims!A2:A100000) -> 5961 | D6: member_id, rendering_npi, service dates, service_category, allowed_amount, in_network_flag, diagnosis_code_1
A7: enrollment | B7: 1 member | C7: =COUNTA(enrollment!A2:A100000) -> 800 | D7: member_id, lob, state, county, age, gender, risk_score, attributed_pcp_npi, disenrollment_reason
A8: member_months | B8: 1 member-month | C8: =COUNTA(member_months!A2:A100000) -> 8462 | D8: member_id, lob, state, calendar_month, member_months (exposure)
A9: providers | B9: 1 provider | C9: =COUNTA(providers!A2:A100000) -> 10 | D9: npi, provider_type, specialty_desc, network_status, quality_score, panel_size, state
A10: avoidable_ed_reference | B10: 1 ICD-10 code | C10: =COUNTA(avoidable_ed_reference!A2:A100000) -> 12 | D10: icd10_code, description, avoidable_category (Avoidable / Potentially Avoidable / Non-Avoidable)
A12: 2. JOINS
A13: claims.member_id → enrollment.member_id | B13: adds member demographics, state, attributed PCP to each claim (helper cols AB-AE)
A14: claims.diagnosis_code_1 → avoidable_ed_reference.icd10_code | B14: classifies ED visits as Avoidable / Potentially Avoidable / Non-Avoidable (helper col AA)
A15: enrollment.attributed_pcp_npi → providers.npi | B15: adds PCP quality_score & network_status (helper col AF; Member Spend tab)
A16: claims.member_id / member_months.member_id | B16: aligns spend to exposure for PMPM (SUMIFS on member-level)
A18: 3. FILTERS & SCOPE
A19: • All 5,961 claim lines fall within 2024 service dates (serial 45292–45656); no period filter needed.
A20: • avoidable_category applies to ED visits only in downstream analysis; other categories retain the label but are not acted on.
A21: • ED avoidable-shift savings model uses Avoidable + Potentially Avoidable ED visits as the divertible pool.
A22: • OON defined as in_network_flag = 'N'. Only 55 of 5,961 lines are OON in this dataset.
A23: • Member months are pre-calculated (1 row = 1 member-month); total exposure = 8,462.
A25: 4. ASSUMPTIONS & KPI DEFINITIONS
A26: Metric | B26: Definition
A27: Primary cost metric | B27: allowed_amount (health-plan liability + member cost share), per assumptions.
A28: PMPM | B28: Total Allowed Amount ÷ Member Months.
A29: ED visits per 1,000 | B29: (ED claims ÷ Member Months) × 1,000.
A30: High-cost member | B30: Member in the top 5% of total allowed spend in the period (allowed ≥ 95th percentile). 800 members → ~40 members.
A31: IP utilization / 1,000 | B31: (Inpatient claim lines ÷ Member Months) × 1,000.
A32: OON rate | B32: Out-of-network allowed ÷ total allowed (also shown as % of claim lines).
A34: 5. HELPER COLUMNS ADDED TO 'claims' (AA:AF)
A35: AA avoidable_category · AB member_state · AC member_age · AD age_band · AE attributed_pcp_npi · AF pcp_quality_score — all XLOOKUP-based, auditable in the formula bar.
A37: 6. TAB INDEX
A38: Member Spend · Category Spend (+ savings scenarios) · Avoidable ED · Behavioral Health · OON & Retention · Dashboard (final)

Sheet Member Spend
A1: member_id | B1: lob | C1: state | D1: county | E1: age | F1: age_band | G1: gender | H1: risk_score | I1: attributed_pcp_npi | J1: pcp_quality_score | K1: member_months | L1: total_allowed | M1: PMPM | N1: inpatient_allowed | O1: ED_allowed | P1: specialtyRx_allowed | Q1: high_cost_flag | S1: HIGH-COST CONCENTRATION (top 5%) | AA1: bh_claims | AB1: ed_visits | AC1: ip_visits | AD1: bh_flag | AE1: disenroll_reason | AF1: disenroll_flag
A2: =enrollment!A2 -> M-000001 | B2: =enrollment!F2 -> Commercial | C2: =enrollment!I2 -> KY | D2: =enrollment!J2 -> Jefferson | E2: =enrollment!L2 -> 53 | F2: {=_xlfn.IFS(E2<18,"0-17",E2<35,"18-34",E2<50,"35-49",E2<65,"50-64",TRUE,"65+")} -> 50-64 | G2: =enrollment!M2 -> F | H2: =enrollment!N2 -> 0.82 | I2: =enrollment!O2 -> 9012345678 | J2: =IFERROR(_xlfn.XLOOKUP(I2,providers!$B$2:$B$11,providers!$Q$2:$Q$11),"") -> 4.3 | K2: =SUMIFS(member_months!$F:$F,member_months!$A:$A,$A2) -> 11 | L2: =SUMIFS(claims!$Q:$Q,claims!$B:$B,$A2) -> 484.53 | M2: =IF(K2=0,0,L2/K2) -> 44.048182 | N2: =SUMIFS(claims!$Q:$Q,claims!$B:$B,$A2,claims!$Z:$Z,"Inpatient") -> 0 | O2: =SUMIFS(claims!$Q:$Q,claims!$B:$B,$A2,claims!$Z:$Z,"ED") -> 0 | P2: =SUMIFS(claims!$Q:$Q,claims!$B:$B,$A2,claims!$Z:$Z,"Specialty Rx") -> 0 | Q2: =IF($L2>=$U$2,1,0) -> 0 | S2: High-cost threshold (40th highest allowed) | U2: =LARGE($L$2:$L$801,40) -> 43489.4 | AA2: =COUNTIFS(claims!$B:$B,$A2,claims!$Z:$Z,"Behavioral Health") -> 1 | AB2: =COUNTIFS(claims!$B:$B,$A2,claims!$Z:$Z,"ED") -> 0 | AC2: =COUNTIFS(claims!$B:$B,$A2,claims!$Z:$Z,"Inpatient") -> 0 | AD2: =IF(AA2>0,1,0) -> 1 | AE2: =IF(enrollment!P2="","",enrollment!P2) | AF2: =IF(enrollment!P2="",0,1) -> 0
A3: =enrollment!A3 -> M-000002 | B3: =enrollment!F3 -> Marketplace | C3: =enrollment!I3 -> KY | D3: =enrollment!J3 -> Jefferson | E3: =enrollment!L3 -> 36 | F3: {=_xlfn.IFS(E3<18,"0-17",E3<35,"18-34",E3<50,"35-49",E3<65,"50-64",TRUE,"65+")} -> 35-49 | G3: =enrollment!M3 -> M | H3: =enrollment!N3 -> 0.88 | I3: =enrollment!O3 -> 9012345678 | J3: =IFERROR(_xlfn.XLOOKUP(I3,providers!$B$2:$B$11,providers!$Q$2:$Q$11),"") -> 4.3 | K3: =SUMIFS(member_months!$F:$F,member_months!$A:$A,$A3) -> 10 | L3: =SUMIFS(claims!$Q:$Q,claims!$B:$B,$A3) -> 2712.06 | M3: =IF(K3=0,0,L3/K3) -> 271.206 | N3: =SUMIFS(claims!$Q:$Q,claims!$B:$B,$A3,claims!$Z:$Z,"Inpatient") -> 0 | O3: =SUMIFS(claims!$Q:$Q,claims!$B:$B,$A3,claims!$Z:$Z,"ED") -> 2394.88 | P3: =SUMIFS(claims!$Q:$Q,claims!$B:$B,$A3,claims!$Z:$Z,"Specialty Rx") -> 0 | Q3: =IF($L3>=$U$2,1,0) -> 0 | S3: # high-cost members | U3: =SUM($Q$2:$Q$801) -> 40 | AA3: =COUNTIFS(claims!$B:$B,$A3,claims!$Z:$Z,"Behavioral Health") -> 0 | AB3: =COUNTIFS(claims!$B:$B,$A3,claims!$Z:$Z,"ED") -> 2 | AC3: =COUNTIFS(claims!$B:$B,$A3,claims!$Z:$Z,"Inpatient") -> 0 | AD3: =IF(AA3>0,1,0) -> 0 | AE3: =IF(enrollment!P3="","",enrollment!P3) | AF3: =IF(enrollment!P3="",0,1) -> 0
A4: =enrollment!A4 -> M-000003 | B4: =enrollment!F4 -> Marketplace | C4: =enrollment!I4 -> GA | D4: =enrollment!J4 -> Fulton | E4: =enrollment!L4 -> 24 | F4: {=_xlfn.IFS(E4<18,"0-17",E4<35,"18-34",E4<50,"35-49",E4<65,"50-64",TRUE,"65+")} -> 18-34 | G4: =enrollment!M4 -> M | H4: =enrollment!N4 -> 1.27 | I4: =enrollment!O4 -> 8901234567 | J4: =IFERROR(_xlfn.XLOOKUP(I4,providers!$B$2:$B$11,providers!$Q$2:$Q$11),"") -> 3.7 | K4: =SUMIFS(member_months!$F:$F,member_months!$A:$A,$A4) -> 6 | L4: =SUMIFS(claims!$Q:$Q,claims!$B:$B,$A4) -> 23008.12 | M4: =IF(K4=0,0,L4/K4) -> 3834.6867 | N4: =SUMIFS(claims!$Q:$Q,claims!$B:$B,$A4,claims!$Z:$Z,"Inpatient") -> 17493.55 | O4: =SUMIFS(claims!$Q:$Q,claims!$B:$B,$A4,claims!$Z:$Z,"ED") -> 3570.21 | P4: =SUMIFS(claims!$Q:$Q,claims!$B:$B,$A4,claims!$Z:$Z,"Specialty Rx") -> 1192.21 | Q4: =IF($L4>=$U$2,1,0) -> 0 | S4: % of members | U4: =U3/COUNTA($A$2:$A$801) -> 0.05 | AA4: =COUNTIFS(claims!$B:$B,$A4,claims!$Z:$Z,"Behavioral Health") -> 0 | AB4: =COUNTIFS(claims!$B:$B,$A4,claims!$Z:$Z,"ED") -> 3 | AC4: =COUNTIFS(claims!$B:$B,$A4,claims!$Z:$Z,"Inpatient") -> 1 | AD4: =IF(AA4>0,1,0) -> 0 | AE4: =IF(enrollment!P4="","",enrollment!P4) -> Premium Affordability | AF4: =IF(enrollment!P4="",0,1) -> 1
A5: =enrollment!A5 -> M-000004 | B5: =enrollment!F5 -> Marketplace | C5: =enrollment!I5 -> TN | D5: =enrollment!J5 -> Davidson | E5: =enrollment!L5 -> 71 | F5: {=_xlfn.IFS(E5<18,"0-17",E5<35,"18-34",E5<50,"35-49",E5<65,"50-64",TRUE,"65+")} -> 65+ | G5: =enrollment!M5 -> M | H5: =enrollment!N5 -> 2.08 | I5: =enrollment!O5 -> 5678901234 | J5: =IFERROR(_xlfn.XLOOKUP(I5,providers!$B$2:$B$11,providers!$Q$2:$Q$11),"") -> 3.8 | K5: =SUMIFS(member_months!$F:$F,member_months!$A:$A,$A5) -> 12 | L5: =SUMIFS(claims!$Q:$Q,claims!$B:$B,$A5) -> 17525.56 | M5: =IF(K5=0,0,L5/K5) -> 1460.4633 | N5: =SUMIFS(claims!$Q:$Q,claims!$B:$B,$A5,claims!$Z:$Z,"Inpatient") -> 14200.28 | O5: =SUMIFS(claims!$Q:$Q,claims!$B:$B,$A5,claims!$Z:$Z,"ED") -> 1999.87 | P5: =SUMIFS(claims!$Q:$Q,claims!$B:$B,$A5,claims!$Z:$Z,"Specialty Rx") -> 721.52 | Q5: =IF($L5>=$U$2,1,0) -> 0 | S5: High-cost total allowed | U5: =SUMIFS($L$2:$L$801,$Q$2:$Q$801,1) -> 2317303.7 | AA5: =COUNTIFS(claims!$B:$B,$A5,claims!$Z:$Z,"Behavioral Health") -> 1 | AB5: =COUNTIFS(claims!$B:$B,$A5,claims!$Z:$Z,"ED") -> 2 | AC5: =COUNTIFS(claims!$B:$B,$A5,claims!$Z:$Z,"Inpatient") -> 1 | AD5: =IF(AA5>0,1,0) -> 1 | AE5: =IF(enrollment!P5="","",enrollment!P5) | AF5: =IF(enrollment!P5="",0,1) -> 0
A6: =enrollment!A6 -> M-000005 | B6: =enrollment!F6 -> Marketplace | C6: =enrollment!I6 -> TN | D6: =enrollment!J6 -> Rural-Cannon | E6: =enrollment!L6 -> 53 | F6: {=_xlfn.IFS(E6<18,"0-17",E6<35,"18-34",E6<50,"35-49",E6<65,"50-64",TRUE,"65+")} -> 50-64 | G6: =enrollment!M6 -> F | H6: =enrollment!N6 -> 1.03 | I6: =enrollment!O6 -> 0 | J6: =IFERROR(_xlfn.XLOOKUP(I6,providers!$B$2:$B$11,providers!$Q$2:$Q$11),"") | K6: =SUMIFS(member_months!$F:$F,member_months!$A:$A,$A6) -> 6 | L6: =SUMIFS(claims!$Q:$Q,claims!$B:$B,$A6) -> 3356.94 | M6: =IF(K6=0,0,L6/K6) -> 559.49 | N6: =SUMIFS(claims!$Q:$Q,claims!$B:$B,$A6,claims!$Z:$Z,"Inpatient") -> 0 | O6: =SUMIFS(claims!$Q:$Q,claims!$B:$B,$A6,claims!$Z:$Z,"ED") -> 2569.05 | P6: =SUMIFS(claims!$Q:$Q,claims!$B:$B,$A6,claims!$Z:$Z,"Specialty Rx") -> 0 | Q6: =IF($L6>=$U$2,1,0) -> 0 | S6: Total allowed (all members) | U6: =SUM($L$2:$L$801) -> 11321252 | AA6: =COUNTIFS(claims!$B:$B,$A6,claims!$Z:$Z,"Behavioral Health") -> 1 | AB6: =COUNTIFS(claims!$B:$B,$A6,claims!$Z:$Z,"ED") -> 2 | AC6: =COUNTIFS(claims!$B:$B,$A6,claims!$Z:$Z,"Inpatient") -> 0 | AD6: =IF(AA6>0,1,0) -> 1 | AE6: =IF(enrollment!P6="","",enrollment!P6) -> Network Adequacy | AF6: =IF(enrollment!P6="",0,1) -> 1
A7: =enrollment!A7 -> M-000006 | B7: =enrollment!F7 -> Commercial | C7: =enrollment!I7 -> KY | D7: =enrollment!J7 -> Hardin | E7: =enrollment!L7 -> 54 | F7: {=_xlfn.IFS(E7<18,"0-17",E7<35,"18-34",E7<50,"35-49",E7<65,"50-64",TRUE,"65+")} -> 50-64 | G7: =enrollment!M7 -> M | H7: =enrollment!N7 -> 1.26 | I7: =enrollment!O7 -> 9012345678 | J7: =IFERROR(_xlfn.XLOOKUP(I7,providers!$B$2:$B$11,providers!$Q$2:$Q$11),"") -> 4.3 | K7: =SUMIFS(member_months!$F:$F,member_months!$A:$A,$A7) -> 10 | L7: =SUMIFS(claims!$Q:$Q,claims!$B:$B,$A7) -> 21092.86 | M7: =IF(K7=0,0,L7/K7) -> 2109.286 | N7: =SUMIFS(claims!$Q:$Q,claims!$B:$B,$A7,claims!$Z:$Z,"Inpatient") -> 20651.94 | O7: =SUMIFS(claims!$Q:$Q,claims!$B:$B,$A7,claims!$Z:$Z,"ED") -> 0 | P7: =SUMIFS(claims!$Q:$Q,claims!$B:$B,$A7,claims!$Z:$Z,"Specialty Rx") -> 0 | Q7: =IF($L7>=$U$2,1,0) -> 0 | S7: High-cost share of allowed | U7: =U5/U6 -> 0.20468617 | AA7: =COUNTIFS(claims!$B:$B,$A7,claims!$Z:$Z,"Behavioral Health") -> 0 | AB7: =COUNTIFS(claims!$B:$B,$A7,claims!$Z:$Z,"ED") -> 0 | AC7: =COUNTIFS(claims!$B:$B,$A7,claims!$Z:$Z,"Inpatient") -> 1 | AD7: =IF(AA7>0,1,0) -> 0 | AE7: =IF(enrollment!P7="","",enrollment!P7) | AF7: =IF(enrollment!P7="",0,1) -> 0
A8: =enrollment!A8 -> M-000007 | B8: =enrollment!F8 -> Commercial | C8: =enrollment!I8 -> TN | D8: =enrollment!J8 -> Davidson | E8: =enrollment!L8 -> 69 | F8: {=_xlfn.IFS(E8<18,"0-17",E8<35,"18-34",E8<50,"35-49",E8<65,"50-64",TRUE,"65+")} -> 65+ | G8: =enrollment!M8 -> F | H8: =enrollment!N8 -> 2.21 | I8: =enrollment!O8 -> 5678901234 | J8: =IFERROR(_xlfn.XLOOKUP(I8,providers!$B$2:$B$11,providers!$Q$2:$Q$11),"") -> 3.8 | K8: =SUMIFS(member_months!$F:$F,member_months!$A:$A,$A8) -> 10 | L8: =SUMIFS(claims!$Q:$Q,claims!$B:$B,$A8) -> 2461.01 | M8: =IF(K8=0,0,L8/K8) -> 246.101 | N8: =SUMIFS(claims!$Q:$Q,claims!$B:$B,$A8,claims!$Z:$Z,"Inpatient") -> 0 | O8: =SUMIFS(claims!$Q:$Q,claims!$B:$B,$A8,claims!$Z:$Z,"ED") -> 1186.92 | P8: =SUMIFS(claims!$Q:$Q,claims!$B:$B,$A8,claims!$Z:$Z,"Specialty Rx") -> 820.55 | Q8: =IF($L8>=$U$2,1,0) -> 0 | S8: Avg PMPM – high-cost | U8: =AVERAGEIFS($M$2:$M$801,$Q$2:$Q$801,1) -> 5280.3967 | AA8: =COUNTIFS(claims!$B:$B,$A8,claims!$Z:$Z,"Behavioral Health") -> 0 | AB8: =COUNTIFS(claims!$B:$B,$A8,claims!$Z:$Z,"ED") -> 1 | AC8: =COUNTIFS(claims!$B:$B,$A8,claims!$Z:$Z,"Inpatient") -> 0 | AD8: =IF(AA8>0,1,0) -> 0 | AE8: =IF(enrollment!P8="","",enrollment!P8) | AF8: =IF(enrollment!P8="",0,1) -> 0
A9: =enrollment!A9 -> M-000008 | B9: =enrollment!F9 -> Marketplace | C9: =enrollment!I9 -> OH | D9: =enrollment!J9 -> Franklin | E9: =enrollment!L9 -> 30 | F9: {=_xlfn.IFS(E9<18,"0-17",E9<35,"18-34",E9<50,"35-49",E9<65,"50-64",TRUE,"65+")} -> 18-34 | G9: =enrollment!M9 -> M | H9: =enrollment!N9 -> 0.73 | I9: =enrollment!O9 -> 6789012345 | J9: =IFERROR(_xlfn.XLOOKUP(I9,providers!$B$2:$B$11,providers!$Q$2:$Q$11),"") -> 4.1 | K9: =SUMIFS(member_months!$F:$F,member_months!$A:$A,$A9) -> 12 | L9: =SUMIFS(claims!$Q:$Q,claims!$B:$B,$A9) -> 761.05 | M9: =IF(K9=0,0,L9/K9) -> 63.420833 | N9: =SUMIFS(claims!$Q:$Q,claims!$B:$B,$A9,claims!$Z:$Z,"Inpatient") -> 0 | O9: =SUMIFS(claims!$Q:$Q,claims!$B:$B,$A9,claims!$Z:$Z,"ED") -> 0 | P9: =SUMIFS(claims!$Q:$Q,claims!$B:$B,$A9,claims!$Z:$Z,"Specialty Rx") -> 0 | Q9: =IF($L9>=$U$2,1,0) -> 0 | S9: Avg PMPM – all other members | U9: =AVERAGEIFS($M$2:$M$801,$Q$2:$Q$801,0) -> 1149.9835 | AA9: =COUNTIFS(claims!$B:$B,$A9,claims!$Z:$Z,"Behavioral Health") -> 0 | AB9: =COUNTIFS(claims!$B:$B,$A9,claims!$Z:$Z,"ED") -> 0 | AC9: =COUNTIFS(claims!$B:$B,$A9,claims!$Z:$Z,"Inpatient") -> 0 | AD9: =IF(AA9>0,1,0) -> 0 | AE9: =IF(enrollment!P9="","",enrollment!P9) | AF9: =IF(enrollment!P9="",0,1) -> 0
A10: =enrollment!A10 -> M-000009 | B10: =enrollment!F10 -> Marketplace | C10: =enrollment!I10 -> GA | D10: =enrollment!J10 -> Cherokee | E10: =enrollment!L10 -> 35 | F10: {=_xlfn.IFS(E10<18,"0-17",E10<35,"18-34",E10<50,"35-49",E10<65,"50-64",TRUE,"65+")} -> 35-49 | G10: =enrollment!M10 -> F | H10: =enrollment!N10 -> 0.71 | I10: =enrollment!O10 -> 8901234567 | J10: =IFERROR(_xlfn.XLOOKUP(I10,providers!$B$2:$B$11,providers!$Q$2:$Q$11),"") -> 3.7 | K10: =SUMIFS(member_months!$F:$F,member_months!$A:$A,$A10) -> 11 | L10: =SUMIFS(claims!$Q:$Q,claims!$B:$B,$A10) -> 3030.2 | M10: =IF(K10=0,0,L10/K10) -> 275.47273 | N10: =SUMIFS(claims!$Q:$Q,claims!$B:$B,$A10,claims!$Z:$Z,"Inpatient") -> 0 | O10: =SUMIFS(claims!$Q:$Q,claims!$B:$B,$A10,claims!$Z:$Z,"ED") -> 1326.41 | P10: =SUMIFS(claims!$Q:$Q,claims!$B:$B,$A10,claims!$Z:$Z,"Specialty Rx") -> 1088.66 | Q10: =IF($L10>=$U$2,1,0) -> 0 | S10: Total member months | U10: =SUM($K$2:$K$801) -> 8462 | AA10: =COUNTIFS(claims!$B:$B,$A10,claims!$Z:$Z,"Behavioral Health") -> 0 | AB10: =COUNTIFS(claims!$B:$B,$A10,claims!$Z:$Z,"ED") -> 1 | AC10: =COUNTIFS(claims!$B:$B,$A10,claims!$Z:$Z,"Inpatient") -> 0 | AD10: =IF(AA10>0,1,0) -> 0 | AE10: =IF(enrollment!P10="","",enrollment!P10) -> Employer Change | AF10: =IF(enrollment!P10="",0,1) -> 1
A11: =enrollment!A11 -> M-000010 | B11: =enrollment!F11 -> Commercial | C11: =enrollment!I11 -> TN | D11: =enrollment!J11 -> Rural-Cannon | E11: =enrollment!L11 -> 50 | F11: {=_xlfn.IFS(E11<18,"0-17",E11<35,"18-34",E11<50,"35-49",E11<65,"50-64",TRUE,"65+")} -> 50-64 | G11: =enrollment!M11 -> M | H11: =enrollment!N11 -> 0.91 | I11: =enrollment!O11 -> 2233445566 | J11: =IFERROR(_xlfn.XLOOKUP(I11,providers!$B$2:$B$11,providers!$Q$2:$Q$11),"") -> 3.5 | K11: =SUMIFS(member_months!$F:$F,member_months!$A:$A,$A11) -> 12 | L11: =SUMIFS(claims!$Q:$Q,claims!$B:$B,$A11) -> 9566.78 | M11: =IF(K11=0,0,L11/K11) -> 797.23167 | N11: =SUMIFS(claims!$Q:$Q,claims!$B:$B,$A11,claims!$Z:$Z,"Inpatient") -> 0 | O11: =SUMIFS(claims!$Q:$Q,claims!$B:$B,$A11,claims!$Z:$Z,"ED") -> 8807.99 | P11: =SUMIFS(claims!$Q:$Q,claims!$B:$B,$A11,claims!$Z:$Z,"Specialty Rx") -> 0 | Q11: =IF($L11>=$U$2,1,0) -> 0 | S11: Blended PMPM | U11: =U6/U10 -> 1337.8931 | AA11: =COUNTIFS(claims!$B:$B,$A11,claims!$Z:$Z,"Behavioral Health") -> 1 | AB11: =COUNTIFS(claims!$B:$B,$A11,claims!$Z:$Z,"ED") -> 8 | AC11: =COUNTIFS(claims!$B:$B,$A11,claims!$Z:$Z,"Inpatient") -> 0 | AD11: =IF(AA11>0,1,0) -> 1 | AE11: =IF(enrollment!P11="","",enrollment!P11) | AF11: =IF(enrollment!P11="",0,1) -> 0
A12: =enrollment!A12 -> M-000011 | B12: =enrollment!F12 -> Commercial | C12: =enrollment!I12 -> KY | D12: =enrollment!J12 -> Warren | E12: =enrollment!L12 -> 72 | F12: {=_xlfn.IFS(E12<18,"0-17",E12<35,"18-34",E12<50,"35-49",E12<65,"50-64",TRUE,"65+")} -> 65+ | G12: =enrollment!M12 -> F | H12: =enrollment!N12 -> 2.01 | I12: =enrollment!O12 -> 9012345678 | J12: =IFERROR(_xlfn.XLOOKUP(I12,providers!$B$2:$B$11,providers!$Q$2:$Q$11),"") -> 4.3 | K12: =SUMIFS(member_months!$F:$F,member_months!$A:$A,$A12) -> 12 | L12: =SUMIFS(claims!$Q:$Q,claims!$B:$B,$A12) -> 2396.58 | M12: =IF(K12=0,0,L12/K12) -> 199.715 | N12: =SUMIFS(claims!$Q:$Q,claims!$B:$B,$A12,claims!$Z:$Z,"Inpatient") -> 0 | O12: =SUMIFS(claims!$Q:$Q,claims!$B:$B,$A12,claims!$Z:$Z,"ED") -> 2242.76 | P12: =SUMIFS(claims!$Q:$Q,claims!$B:$B,$A12,claims!$Z:$Z,"Specialty Rx") -> 0 | Q12: =IF($L12>=$U$2,1,0) -> 0 | AA12: =COUNTIFS(claims!$B:$B,$A12,claims!$Z:$Z,"Behavioral Health") -> 0 | AB12: =COUNTIFS(claims!$B:$B,$A12,claims!$Z:$Z,"ED") -> 2 | AC12: =COUNTIFS(claims!$B:$B,$A12,claims!$Z:$Z,"Inpatient") -> 0 | AD12: =IF(AA12>0,1,0) -> 0 | AE12: =IF(enrollment!P12="","",enrollment!P12) | AF12: =IF(enrollment!P12="",0,1) -> 0
A13: =enrollment!A13 -> M-000012 | B13: =enrollment!F13 -> Medicare Advantage | C13: =enrollment!I13 -> KY | D13: =enrollment!J13 -> Jefferson | E13: =enrollment!L13 -> 74 | F13: {=_xlfn.IFS(E13<18,"0-17",E13<35,"18-34",E13<50,"35-49",E13<65,"50-64",TRUE,"65+")} -> 65+ | G13: =enrollment!M13 -> F | H13: =enrollment!N13 -> 3.11 | I13: =enrollment!O13 -> 3456789012 | J13: =IFERROR(_xlfn.XLOOKUP(I13,providers!$B$2:$B$11,providers!$Q$2:$Q$11),"") -> 4 | K13: =SUMIFS(member_months!$F:$F,member_months!$A:$A,$A13) -> 10 | L13: =SUMIFS(claims!$Q:$Q,claims!$B:$B,$A13) -> 23944.18 | M13: =IF(K13=0,0,L13/K13) -> 2394.418 | N13: =SUMIFS(claims!$Q:$Q,claims!$B:$B,$A13,claims!$Z:$Z,"Inpatient") -> 21231.22 | O13: =SUMIFS(claims!$Q:$Q,claims!$B:$B,$A13,claims!$Z:$Z,"ED") -> 1081.46 | P13: =SUMIFS(claims!$Q:$Q,claims!$B:$B,$A13,claims!$Z:$Z,"Specialty Rx") -> 1104.9 | Q13: =IF($L13>=$U$2,1,0) -> 0 | S13: PMPM & HIGH-COST BY LOB | AA13: =COUNTIFS(claims!$B:$B,$A13,claims!$Z:$Z,"Behavioral Health") -> 0 | AB13: =COUNTIFS(claims!$B:$B,$A13,claims!$Z:$Z,"ED") -> 1 | AC13: =COUNTIFS(claims!$B:$B,$A13,claims!$Z:$Z,"Inpatient") -> 1 | AD13: =IF(AA13>0,1,0) -> 0 | AE13: =IF(enrollment!P13="","",enrollment!P13) | AF13: =IF(enrollment!P13="",0,1) -> 0
A14: =enrollment!A14 -> M-000013 | B14: =enrollment!F14 -> Marketplace | C14: =enrollment!I14 -> TN | D14: =enrollment!J14 -> Knox | E14: =enrollment!L14 -> 54 | F14: {=_xlfn.IFS(E14<18,"0-17",E14<35,"18-34",E14<50,"35-49",E14<65,"50-64",TRUE,"65+")} -> 50-64 | G14: =enrollment!M14 -> F | H14: =enrollment!N14 -> 0.98 | I14: =enrollment!O14 -> 7890123456 | J14: =IFERROR(_xlfn.XLOOKUP(I14,providers!$B$2:$B$11,providers!$Q$2:$Q$11),"") -> 3.9 | K14: =SUMIFS(member_months!$F:$F,member_months!$A:$A,$A14) -> 11 | L14: =SUMIFS(claims!$Q:$Q,claims!$B:$B,$A14) -> 3461.98 | M14: =IF(K14=0,0,L14/K14) -> 314.72545 | N14: =SUMIFS(claims!$Q:$Q,claims!$B:$B,$A14,claims!$Z:$Z,"Inpatient") -> 0 | O14: =SUMIFS(claims!$Q:$Q,claims!$B:$B,$A14,claims!$Z:$Z,"ED") -> 1274.49 | P14: =SUMIFS(claims!$Q:$Q,claims!$B:$B,$A14,claims!$Z:$Z,"Specialty Rx") -> 1742.76 | Q14: =IF($L14>=$U$2,1,0) -> 0 | S14: LOB | T14: Members | U14: Member Mos | V14: Allowed | W14: PMPM | X14: # High-cost | Y14: HC % of LOB $ | AA14: =COUNTIFS(claims!$B:$B,$A14,claims!$Z:$Z,"Behavioral Health") -> 1 | AB14: =COUNTIFS(claims!$B:$B,$A14,claims!$Z:$Z,"ED") -> 1 | AC14: =COUNTIFS(claims!$B:$B,$A14,claims!$Z:$Z,"Inpatient") -> 0 | AD14: =IF(AA14>0,1,0) -> 1 | AE14: =IF(enrollment!P14="","",enrollment!P14) | AF14: =IF(enrollment!P14="",0,1) -> 0
A15: =enrollment!A15 -> M-000014 | B15: =enrollment!F15 -> Commercial | C15: =enrollment!I15 -> KY | D15: =enrollment!J15 -> Hardin | E15: =enrollment!L15 -> 75 | F15: {=_xlfn.IFS(E15<18,"0-17",E15<35,"18-34",E15<50,"35-49",E15<65,"50-64",TRUE,"65+")} -> 65+ | G15: =enrollment!M15 -> M | H15: =enrollment!N15 -> 2.6 | I15: =enrollment!O15 -> 3456789012 | J15: =IFERROR(_xlfn.XLOOKUP(I15,providers!$B$2:$B$11,providers!$Q$2:$Q$11),"") -> 4 | K15: =SUMIFS(member_months!$F:$F,member_months!$A:$A,$A15) -> 12 | L15: =SUMIFS(claims!$Q:$Q,claims!$B:$B,$A15) -> 42510.65 | M15: =IF(K15=0,0,L15/K15) -> 3542.5542 | N15: =SUMIFS(claims!$Q:$Q,claims!$B:$B,$A15,claims!$Z:$Z,"Inpatient") -> 41635.03 | O15: =SUMIFS(claims!$Q:$Q,claims!$B:$B,$A15,claims!$Z:$Z,"ED") -> 0 | P15: =SUMIFS(claims!$Q:$Q,claims!$B:$B,$A15,claims!$Z:$Z,"Specialty Rx") -> 747.61 | Q15: =IF($L15>=$U$2,1,0) -> 0 | S15: Commercial | T15: =COUNTIFS($B$2:$B$801,$S15) -> 349 | U15: =SUMIFS($K$2:$K$801,$B$2:$B$801,$S15) -> 3733 | V15: =SUMIFS($L$2:$L$801,$B$2:$B$801,$S15) -> 4480145.7 | W15: =V15/U15 -> 1200.1462 | X15: =SUMIFS($Q$2:$Q$801,$B$2:$B$801,$S15) -> 13 | Y15: =SUMIFS($L$2:$L$801,$B$2:$B$801,$S15,$Q$2:$Q$801,1)/V15 -> 0.15735332 | AA15: =COUNTIFS(claims!$B:$B,$A15,claims!$Z:$Z,"Behavioral Health") -> 0 | AB15: =COUNTIFS(claims!$B:$B,$A15,claims!$Z:$Z,"ED") -> 0 | AC15: =COUNTIFS(claims!$B:$B,$A15,claims!$Z:$Z,"Inpatient") -> 2 | AD15: =IF(AA15>0,1,0) -> 0 | AE15: =IF(enrollment!P15="","",enrollment!P15) | AF15: =IF(enrollment!P15="",0,1) -> 0
A16: =enrollment!A16 -> M-000015 | B16: =enrollment!F16 -> Marketplace | C16: =enrollment!I16 -> TN | D16: =enrollment!J16 -> Davidson | E16: =enrollment!L16 -> 42 | F16: {=_xlfn.IFS(E16<18,"0-17",E16<35,"18-34",E16<50,"35-49",E16<65,"50-64",TRUE,"65+")} -> 35-49 | G16: =enrollment!M16 -> F | H16: =enrollment!N16 -> 1.24 | I16: =enrollment!O16 -> 5678901234 | J16: =IFERROR(_xlfn.XLOOKUP(I16,providers!$B$2:$B$11,providers!$Q$2:$Q$11),"") -> 3.8 | K16: =SUMIFS(member_months!$F:$F,member_months!$A:$A,$A16) -> 7 | L16: =SUMIFS(claims!$Q:$Q,claims!$B:$B,$A16) -> 17078.79 | M16: =IF(K16=0,0,L16/K16) -> 2439.8271 | N16: =SUMIFS(claims!$Q:$Q,claims!$B:$B,$A16,claims!$Z:$Z,"Inpatient") -> 14057.22 | O16: =SUMIFS(claims!$Q:$Q,claims!$B:$B,$A16,claims!$Z:$Z,"ED") -> 1020.44 | P16: =SUMIFS(claims!$Q:$Q,claims!$B:$B,$A16,claims!$Z:$Z,"Specialty Rx") -> 909.78 | Q16: =IF($L16>=$U$2,1,0) -> 0 | S16: Marketplace | T16: =COUNTIFS($B$2:$B$801,$S16) -> 299 | U16: =SUMIFS($K$2:$K$801,$B$2:$B$801,$S16) -> 3088 | V16: =SUMIFS($L$2:$L$801,$B$2:$B$801,$S16) -> 4230001.4 | W16: =V16/U16 -> 1369.8191 | X16: =SUMIFS($Q$2:$Q$801,$B$2:$B$801,$S16) -> 15 | Y16: =SUMIFS($L$2:$L$801,$B$2:$B$801,$S16,$Q$2:$Q$801,1)/V16 -> 0.20440639 | AA16: =COUNTIFS(claims!$B:$B,$A16,claims!$Z:$Z,"Behavioral Health") -> 2 | AB16: =COUNTIFS(claims!$B:$B,$A16,claims!$Z:$Z,"ED") -> 1 | AC16: =COUNTIFS(claims!$B:$B,$A16,claims!$Z:$Z,"Inpatient") -> 1 | AD16: =IF(AA16>0,1,0) -> 1 | AE16: =IF(enrollment!P16="","",enrollment!P16) -> Premium Affordability | AF16: =IF(enrollment!P16="",0,1) -> 1
A17: =enrollment!A17 -> M-000016 | B17: =enrollment!F17 -> Marketplace | C17: =enrollment!I17 -> TN | D17: =enrollment!J17 -> Knox | E17: =enrollment!L17 -> 82 | F17: {=_xlfn.IFS(E17<18,"0-17",E17<35,"18-34",E17<50,"35-49",E17<65,"50-64",TRUE,"65+")} -> 65+ | G17: =enrollment!M17 -> M | H17: =enrollment!N17 -> 3.21 | I17: =enrollment!O17 -> 5678901234 | J17: =IFERROR(_xlfn.XLOOKUP(I17,providers!$B$2:$B$11,providers!$Q$2:$Q$11),"") -> 3.8 | K17: =SUMIFS(member_months!$F:$F,member_months!$A:$A,$A17) -> 12 | L17: =SUMIFS(claims!$Q:$Q,claims!$B:$B,$A17) -> 4010.99 | M17: =IF(K17=0,0,L17/K17) -> 334.24917 | N17: =SUMIFS(claims!$Q:$Q,claims!$B:$B,$A17,claims!$Z:$Z,"Inpatient") -> 0 | O17: =SUMIFS(claims!$Q:$Q,claims!$B:$B,$A17,claims!$Z:$Z,"ED") -> 3479.86 | P17: =SUMIFS(claims!$Q:$Q,claims!$B:$B,$A17,claims!$Z:$Z,"Specialty Rx") -> 0 | Q17: =IF($L17>=$U$2,1,0) -> 0 | S17: Medicare Advantage | T17: =COUNTIFS($B$2:$B$801,$S17) -> 152 | U17: =SUMIFS($K$2:$K$801,$B$2:$B$801,$S17) -> 1641 | V17: =SUMIFS($L$2:$L$801,$B$2:$B$801,$S17) -> 2611104.8 | W17: =V17/U17 -> 1591.1668 | X17: =SUMIFS($Q$2:$Q$801,$B$2:$B$801,$S17) -> 12 | Y17: =SUMIFS($L$2:$L$801,$B$2:$B$801,$S17,$Q$2:$Q$801,1)/V17 -> 0.28635334 | AA17: =COUNTIFS(claims!$B:$B,$A17,claims!$Z:$Z,"Behavioral Health") -> 0 | AB17: =COUNTIFS(claims!$B:$B,$A17,claims!$Z:$Z,"ED") -> 3 | AC17: =COUNTIFS(claims!$B:$B,$A17,claims!$Z:$Z,"Inpatient") -> 0 | AD17: =IF(AA17>0,1,0) -> 0 | AE17: =IF(enrollment!P17="","",enrollment!P17) | AF17: =IF(enrollment!P17="",0,1) -> 0
A18: =enrollment!A18 -> M-000017 | B18: =enrollment!F18 -> Medicare Advantage | C18: =enrollment!I18 -> GA | D18: =enrollment!J18 -> Cherokee | E18: =enrollment!L18 -> 65 | F18: {=_xlfn.IFS(E18<18,"0-17",E18<35,"18-34",E18<50,"35-49",E18<65,"50-64",TRUE,"65+")} -> 65+ | G18: =enrollment!M18 -> F | H18: =enrollment!N18 -> 3.67 | I18: =enrollment!O18 -> 8901234567 | J18: =IFERROR(_xlfn.XLOOKUP(I18,providers!$B$2:$B$11,providers!$Q$2:$Q$11),"") -> 3.7 | K18: =SUMIFS(member_months!$F:$F,member_months!$A:$A,$A18) -> 10 | L18: =SUMIFS(claims!$Q:$Q,claims!$B:$B,$A18) -> 1711.61 | M18: =IF(K18=0,0,L18/K18) -> 171.161 | N18: =SUMIFS(claims!$Q:$Q,claims!$B:$B,$A18,claims!$Z:$Z,"Inpatient") -> 0 | O18: =SUMIFS(claims!$Q:$Q,claims!$B:$B,$A18,claims!$Z:$Z,"ED") -> 1229.36 | P18: =SUMIFS(claims!$Q:$Q,claims!$B:$B,$A18,claims!$Z:$Z,"Specialty Rx") -> 0 | Q18: =IF($L18>=$U$2,1,0) -> 0 | S18: Total | T18: =SUM(T15:T17) -> 800 | U18: =SUM(U15:U17) -> 8462 | V18: =SUM(V15:V17) -> 11321252 | W18: =V18/U18 -> 1337.8931 | X18: =SUM(X15:X17) -> 40 | Y18: =SUMIFS($L$2:$L$801,$Q$2:$Q$801,1)/V18 -> 0.20468617 | AA18: =COUNTIFS(claims!$B:$B,$A18,claims!$Z:$Z,"Behavioral Health") -> 1 | AB18: =COUNTIFS(claims!$B:$B,$A18,claims!$Z:$Z,"ED") -> 1 | AC18: =COUNTIFS(claims!$B:$B,$A18,claims!$Z:$Z,"Inpatient") -> 0 | AD18: =IF(AA18>0,1,0) -> 1 | AE18: =IF(enrollment!P18="","",enrollment!P18) | AF18: =IF(enrollment!P18="",0,1) -> 0
A19: =enrollment!A19 -> M-000018 | B19: =enrollment!F19 -> Commercial | C19: =enrollment!I19 -> TN | D19: =enrollment!J19 -> Davidson | E19: =enrollment!L19 -> 35 | F19: {=_xlfn.IFS(E19<18,"0-17",E19<35,"18-34",E19<50,"35-49",E19<65,"50-64",TRUE,"65+")} -> 35-49 | G19: =enrollment!M19 -> F | H19: =enrollment!N19 -> 1.11 | I19: =enrollment!O19 -> 5678901234 | J19: =IFERROR(_xlfn.XLOOKUP(I19,providers!$B$2:$B$11,providers!$Q$2:$Q$11),"") -> 3.8 | K19: =SUMIFS(member_months!$F:$F,member_months!$A:$A,$A19) -> 9 | L19: =SUMIFS(claims!$Q:$Q,claims!$B:$B,$A19) -> 21544.32 | M19: =IF(K19=0,0,L19/K19) -> 2393.8133 | N19: =SUMIFS(claims!$Q:$Q,claims!$B:$B,$A19,claims!$Z:$Z,"Inpatient") -> 18187.45 | O19: =SUMIFS(claims!$Q:$Q,claims!$B:$B,$A19,claims!$Z:$Z,"ED") -> 0 | P19: =SUMIFS(claims!$Q:$Q,claims!$B:$B,$A19,claims!$Z:$Z,"Specialty Rx") -> 1770.26 | Q19: =IF($L19>=$U$2,1,0) -> 0 | AA19: =COUNTIFS(claims!$B:$B,$A19,claims!$Z:$Z,"Behavioral Health") -> 1 | AB19: =COUNTIFS(claims!$B:$B,$A19,claims!$Z:$Z,"ED") -> 0 | AC19: =COUNTIFS(claims!$B:$B,$A19,claims!$Z:$Z,"Inpatient") -> 1 | AD19: =IF(AA19>0,1,0) -> 1 | AE19: =IF(enrollment!P19="","",enrollment!P19) -> Premium Affordability | AF19: =IF(enrollment!P19="",0,1) -> 1
A20: =enrollment!A20 -> M-000019 | B20: =enrollment!F20 -> Commercial | C20: =enrollment!I20 -> OH | D20: =enrollment!J20 -> Franklin | E20: =enrollment!L20 -> 41 | F20: {=_xlfn.IFS(E20<18,"0-17",E20<35,"18-34",E20<50,"35-49",E20<65,"50-64",TRUE,"65+")} -> 35-49 | G20: =enrollment!M20 -> M | H20: =enrollment!N20 -> 0.93 | I20: =enrollment!O20 -> 6789012345 | J20: =IFERROR(_xlfn.XLOOKUP(I20,providers!$B$2:$B$11,providers!$Q$2:$Q$11),"") -> 4.1 | K20: =SUMIFS(member_months!$F:$F,member_months!$A:$A,$A20) -> 10 | L20: =SUMIFS(claims!$Q:$Q,claims!$B:$B,$A20) -> 2215.33 | M20: =IF(K20=0,0,L20/K20) -> 221.533 | N20: =SUMIFS(claims!$Q:$Q,claims!$B:$B,$A20,claims!$Z:$Z,"Inpatient") -> 0 | O20: =SUMIFS(claims!$Q:$Q,claims!$B:$B,$A20,claims!$Z:$Z,"ED") -> 0 | P20: =SUMIFS(claims!$Q:$Q,claims!$B:$B,$A20,claims!$Z:$Z,"Specialty Rx") -> 1132.07 | Q20: =IF($L20>=$U$2,1,0) -> 0 | S20: PMPM & HIGH-COST BY STATE | AA20: =COUNTIFS(claims!$B:$B,$A20,claims!$Z:$Z,"Behavioral Health") -> 1 | AB20: =COUNTIFS(claims!$B:$B,$A20,claims!$Z:$Z,"ED") -> 0 | AC20: =COUNTIFS(claims!$B:$B,$A20,claims!$Z:$Z,"Inpatient") -> 0 | AD20: =IF(AA20>0,1,0) -> 1 | AE20: =IF(enrollment!P20="","",enrollment!P20) | AF20: =IF(enrollment!P20="",0,1) -> 0
A21: =enrollment!A21 -> M-000020 | B21: =enrollment!F21 -> Medicare Advantage | C21: =enrollment!I21 -> TN | D21: =enrollment!J21 -> Rural-Cannon | E21: =enrollment!L21 -> 84 | F21: {=_xlfn.IFS(E21<18,"0-17",E21<35,"18-34",E21<50,"35-49",E21<65,"50-64",TRUE,"65+")} -> 65+ | G21: =enrollment!M21 -> M | H21: =enrollment!N21 -> 2.7 | I21: =enrollment!O21 -> 2233445566 | J21: =IFERROR(_xlfn.XLOOKUP(I21,providers!$B$2:$B$11,providers!$Q$2:$Q$11),"") -> 3.5 | K21: =SUMIFS(member_months!$F:$F,member_months!$A:$A,$A21) -> 12 | L21: =SUMIFS(claims!$Q:$Q,claims!$B:$B,$A21) -> 11451.14 | M21: =IF(K21=0,0,L21/K21) -> 954.26167 | N21: =SUMIFS(claims!$Q:$Q,claims!$B:$B,$A21,claims!$Z:$Z,"Inpatient") -> 0 | O21: =SUMIFS(claims!$Q:$Q,claims!$B:$B,$A21,claims!$Z:$Z,"ED") -> 11257.01 | P21: =SUMIFS(claims!$Q:$Q,claims!$B:$B,$A21,claims!$Z:$Z,"Specialty Rx") -> 0 | Q21: =IF($L21>=$U$2,1,0) -> 0 | S21: State | T21: Members | U21: Member Mos | V21: Allowed | W21: PMPM | X21: # High-cost | Y21: HC % of state $ | AA21: =COUNTIFS(claims!$B:$B,$A21,claims!$Z:$Z,"Behavioral Health") -> 1 | AB21: =COUNTIFS(claims!$B:$B,$A21,claims!$Z:$Z,"ED") -> 10 | AC21: =COUNTIFS(claims!$B:$B,$A21,claims!$Z:$Z,"Inpatient") -> 0 | AD21: =IF(AA21>0,1,0) -> 1 | AE21: =IF(enrollment!P21="","",enrollment!P21) | AF21: =IF(enrollment!P21="",0,1) -> 0
A22: =enrollment!A22 -> M-000021 | B22: =enrollment!F22 -> Commercial | C22: =enrollment!I22 -> KY | D22: =enrollment!J22 -> Jefferson | E22: =enrollment!L22 -> 33 | F22: {=_xlfn.IFS(E22<18,"0-17",E22<35,"18-34",E22<50,"35-49",E22<65,"50-64",TRUE,"65+")} -> 18-34 | G22: =enrollment!M22 -> F | H22: =enrollment!N22 -> 0.72 | I22: =enrollment!O22 -> 9012345678 | J22: =IFERROR(_xlfn.XLOOKUP(I22,providers!$B$2:$B$11,providers!$Q$2:$Q$11),"") -> 4.3 | K22: =SUMIFS(member_months!$F:$F,member_months!$A:$A,$A22) -> 12 | L22: =SUMIFS(claims!$Q:$Q,claims!$B:$B,$A22) -> 31297.49 | M22: =IF(K22=0,0,L22/K22) -> 2608.1242 | N22: =SUMIFS(claims!$Q:$Q,claims!$B:$B,$A22,claims!$Z:$Z,"Inpatient") -> 30396.44 | O22: =SUMIFS(claims!$Q:$Q,claims!$B:$B,$A22,claims!$Z:$Z,"ED") -> 0 | P22: =SUMIFS(claims!$Q:$Q,claims!$B:$B,$A22,claims!$Z:$Z,"Specialty Rx") -> 0 | Q22: =IF($L22>=$U$2,1,0) -> 0 | S22: KY | T22: =COUNTIFS($C$2:$C$801,$S22) -> 182 | U22: =SUMIFS($K$2:$K$801,$C$2:$C$801,$S22) -> 1911 | V22: =SUMIFS($L$2:$L$801,$C$2:$C$801,$S22) -> 2600619.4 | W22: =V22/U22 -> 1360.8684 | X22: =SUMIFS($Q$2:$Q$801,$C$2:$C$801,$S22) -> 9 | Y22: =SUMIFS($L$2:$L$801,$C$2:$C$801,$S22,$Q$2:$Q$801,1)/V22 -> 0.22720377 | AA22: =COUNTIFS(claims!$B:$B,$A22,claims!$Z:$Z,"Behavioral Health") -> 0 | AB22: =COUNTIFS(claims!$B:$B,$A22,claims!$Z:$Z,"ED") -> 0 | AC22: =COUNTIFS(claims!$B:$B,$A22,claims!$Z:$Z,"Inpatient") -> 2 | AD22: =IF(AA22>0,1,0) -> 0 | AE22: =IF(enrollment!P22="","",enrollment!P22) | AF22: =IF(enrollment!P22="",0,1) -> 0
A23: =enrollment!A23 -> M-000022 | B23: =enrollment!F23 -> Commercial | C23: =enrollment!I23 -> OH | D23: =enrollment!J23 -> Cuyahoga | E23: =enrollment!L23 -> 75 | F23: {=_xlfn.IFS(E23<18,"0-17",E23<35,"18-34",E23<50,"35-49",E23<65,"50-64",TRUE,"65+")} -> 65+ | G23: =enrollment!M23 -> M | H23: =enrollment!N23 -> 2.53 | I23: =enrollment!O23 -> 2345678901 | J23: =IFERROR(_xlfn.XLOOKUP(I23,providers!$B$2:$B$11,providers!$Q$2:$Q$11),"") -> 4.2 | K23: =SUMIFS(member_months!$F:$F,member_months!$A:$A,$A23) -> 10 | L23: =SUMIFS(claims!$Q:$Q,claims!$B:$B,$A23) -> 36502.46 | M23: =IF(K23=0,0,L23/K23) -> 3650.246 | N23: =SUMIFS(claims!$Q:$Q,claims!$B:$B,$A23,claims!$Z:$Z,"Inpatient") -> 34570.53 | O23: =SUMIFS(claims!$Q:$Q,claims!$B:$B,$A23,claims!$Z:$Z,"ED") -> 883.04 | P23: =SUMIFS(claims!$Q:$Q,claims!$B:$B,$A23,claims!$Z:$Z,"Specialty Rx") -> 769.27 | Q23: =IF($L23>=$U$2,1,0) -> 0 | S23: GA | T23: =COUNTIFS($C$2:$C$801,$S23) -> 194 | U23: =SUMIFS($K$2:$K$801,$C$2:$C$801,$S23) -> 2043 | V23: =SUMIFS($L$2:$L$801,$C$2:$C$801,$S23) -> 2772066.4 | W23: =V23/U23 -> 1356.8607 | X23: =SUMIFS($Q$2:$Q$801,$C$2:$C$801,$S23) -> 10 | Y23: =SUMIFS($L$2:$L$801,$C$2:$C$801,$S23,$Q$2:$Q$801,1)/V23 -> 0.19819586 | AA23: =COUNTIFS(claims!$B:$B,$A23,claims!$Z:$Z,"Behavioral Health") -> 0 | AB23: =COUNTIFS(claims!$B:$B,$A23,claims!$Z:$Z,"ED") -> 1 | AC23: =COUNTIFS(claims!$B:$B,$A23,claims!$Z:$Z,"Inpatient") -> 2 | AD23: =IF(AA23>0,1,0) -> 0 | AE23: =IF(enrollment!P23="","",enrollment!P23) | AF23: =IF(enrollment!P23="",0,1) -> 0
A24: =enrollment!A24 -> M-000023 | B24: =enrollment!F24 -> Marketplace | C24: =enrollment!I24 -> KY | D24: =enrollment!J24 -> Jefferson | E24: =enrollment!L24 -> 45 | F24: {=_xlfn.IFS(E24<18,"0-17",E24<35,"18-34",E24<50,"35-49",E24<65,"50-64",TRUE,"65+")} -> 35-49 | G24: =enrollment!M24 -> F | H24: =enrollment!N24 -> 1.32 | I24: =enrollment!O24 -> 3456789012 | J24: =IFERROR(_xlfn.XLOOKUP(I24,providers!$B$2:$B$11,providers!$Q$2:$Q$11),"") -> 4 | K24: =SUMIFS(member_months!$F:$F,member_months!$A:$A,$A24) -> 11 | L24: =SUMIFS(claims!$Q:$Q,claims!$B:$B,$A24) -> 26060.63 | M24: =IF(K24=0,0,L24/K24) -> 2369.1482 | N24: =SUMIFS(claims!$Q:$Q,claims!$B:$B,$A24,claims!$Z:$Z,"Inpatient") -> 19822.22 | O24: =SUMIFS(claims!$Q:$Q,claims!$B:$B,$A24,claims!$Z:$Z,"ED") -> 2445.36 | P24: =SUMIFS(claims!$Q:$Q,claims!$B:$B,$A24,claims!$Z:$Z,"Specialty Rx") -> 3332.78 | Q24: =IF($L24>=$U$2,1,0) -> 0 | S24: TN | T24: =COUNTIFS($C$2:$C$801,$S24) -> 204 | U24: =SUMIFS($K$2:$K$801,$C$2:$C$801,$S24) -> 2160 | V24: =SUMIFS($L$2:$L$801,$C$2:$C$801,$S24) -> 2757008.3 | W24: =V24/U24 -> 1276.3928 | X24: =SUMIFS($Q$2:$Q$801,$C$2:$C$801,$S24) -> 12 | Y24: =SUMIFS($L$2:$L$801,$C$2:$C$801,$S24,$Q$2:$Q$801,1)/V24 -> 0.24345866 | AA24: =COUNTIFS(claims!$B:$B,$A24,claims!$Z:$Z,"Behavioral Health") -> 1 | AB24: =COUNTIFS(claims!$B:$B,$A24,claims!$Z:$Z,"ED") -> 2 | AC24: =COUNTIFS(claims!$B:$B,$A24,claims!$Z:$Z,"Inpatient") -> 1 | AD24: =IF(AA24>0,1,0) -> 1 | AE24: =IF(enrollment!P24="","",enrollment!P24) | AF24: =IF(enrollment!P24="",0,1) -> 0
A25: =enrollment!A25 -> M-000024 | B25: =enrollment!F25 -> Marketplace | C25: =enrollment!I25 -> OH | D25: =enrollment!J25 -> Franklin | E25: =enrollment!L25 -> 79 | F25: {=_xlfn.IFS(E25<18,"0-17",E25<35,"18-34",E25<50,"35-49",E25<65,"50-64",TRUE,"65+")} -> 65+ | G25: =enrollment!M25 -> F | H25: =enrollment!N25 -> 2.23 | I25: =enrollment!O25 -> 6789012345 | J25: =IFERROR(_xlfn.XLOOKUP(I25,providers!$B$2:$B$11,providers!$Q$2:$Q$11),"") -> 4.1 | K25: =SUMIFS(member_months!$F:$F,member_months!$A:$A,$A25) -> 9 | L25: =SUMIFS(claims!$Q:$Q,claims!$B:$B,$A25) -> 21822.16 | M25: =IF(K25=0,0,L25/K25) -> 2424.6844 | N25: =SUMIFS(claims!$Q:$Q,claims!$B:$B,$A25,claims!$Z:$Z,"Inpatient") -> 17977.44 | O25: =SUMIFS(claims!$Q:$Q,claims!$B:$B,$A25,claims!$Z:$Z,"ED") -> 1201.91 | P25: =SUMIFS(claims!$Q:$Q,claims!$B:$B,$A25,claims!$Z:$Z,"Specialty Rx") -> 1768.12 | Q25: =IF($L25>=$U$2,1,0) -> 0 | S25: OH | T25: =COUNTIFS($C$2:$C$801,$S25) -> 220 | U25: =SUMIFS($K$2:$K$801,$C$2:$C$801,$S25) -> 2348 | V25: =SUMIFS($L$2:$L$801,$C$2:$C$801,$S25) -> 3191557.7 | W25: =V25/U25 -> 1359.2665 | X25: =SUMIFS($Q$2:$Q$801,$C$2:$C$801,$S25) -> 9 | Y25: =SUMIFS($L$2:$L$801,$C$2:$C$801,$S25,$Q$2:$Q$801,1)/V25 -> 0.1584817 | AA25: =COUNTIFS(claims!$B:$B,$A25,claims!$Z:$Z,"Behavioral Health") -> 1 | AB25: =COUNTIFS(claims!$B:$B,$A25,claims!$Z:$Z,"ED") -> 1 | AC25: =COUNTIFS(claims!$B:$B,$A25,claims!$Z:$Z,"Inpatient") -> 1 | AD25: =IF(AA25>0,1,0) -> 1 | AE25: =IF(enrollment!P25="","",enrollment!P25) -> Premium Affordability | AF25: =IF(enrollment!P25="",0,1) -> 1
A26: =enrollment!A26 -> M-000025 | B26: =enrollment!F26 -> Marketplace | C26: =enrollment!I26 -> TN | D26: =enrollment!J26 -> Rural-Cannon | E26: =enrollment!L26 -> 46 | F26: {=_xlfn.IFS(E26<18,"0-17",E26<35,"18-34",E26<50,"35-49",E26<65,"50-64",TRUE,"65+")} -> 35-49 | G26: =enrollment!M26 -> F | H26: =enrollment!N26 -> 1.31 | I26: =enrollment!O26 -> 2233445566 | J26: =IFERROR(_xlfn.XLOOKUP(I26,providers!$B$2:$B$11,providers!$Q$2:$Q$11),"") -> 3.5 | K26: =SUMIFS(member_months!$F:$F,member_months!$A:$A,$A26) -> 10 | L26: =SUMIFS(claims!$Q:$Q,claims!$B:$B,$A26) -> 4310.33 | M26: =IF(K26=0,0,L26/K26) -> 431.033 | N26: =SUMIFS(claims!$Q:$Q,claims!$B:$B,$A26,claims!$Z:$Z,"Inpatient") -> 0 | O26: =SUMIFS(claims!$Q:$Q,claims!$B:$B,$A26,claims!$Z:$Z,"ED") -> 3528.49 | P26: =SUMIFS(claims!$Q:$Q,claims!$B:$B,$A26,claims!$Z:$Z,"Specialty Rx") -> 0 | Q26: =IF($L26>=$U$2,1,0) -> 0 | S26: Total | T26: =SUM(T22:T25) -> 800 | U26: =SUM(U22:U25) -> 8462 | V26: =SUM(V22:V25) -> 11321252 | W26: =V26/U26 -> 1337.8931 | X26: =SUM(X22:X25) -> 40 | Y26: =SUMIFS($L$2:$L$801,$Q$2:$Q$801,1)/V26 -> 0.20468617 | AA26: =COUNTIFS(claims!$B:$B,$A26,claims!$Z:$Z,"Behavioral Health") -> 2 | AB26: =COUNTIFS(claims!$B:$B,$A26,claims!$Z:$Z,"ED") -> 3 | AC26: =COUNTIFS(claims!$B:$B,$A26,claims!$Z:$Z,"Inpatient") -> 0 | AD26: =IF(AA26>0,1,0) -> 1 | AE26: =IF(enrollment!P26="","",enrollment!P26) | AF26: =IF(enrollment!P26="",0,1) -> 0
A27: =enrollment!A27 -> M-000026 | B27: =enrollment!F27 -> Medicare Advantage | C27: =enrollment!I27 -> OH | D27: =enrollment!J27 -> Cuyahoga | E27: =enrollment!L27 -> 72 | F27: {=_xlfn.IFS(E27<18,"0-17",E27<35,"18-34",E27<50,"35-49",E27<65,"50-64",TRUE,"65+")} -> 65+ | G27: =enrollment!M27 -> M | H27: =enrollment!N27 -> 3.11 | I27: =enrollment!O27 -> 6789012345 | J27: =IFERROR(_xlfn.XLOOKUP(I27,providers!$B$2:$B$11,providers!$Q$2:$Q$11),"") -> 4.1 | K27: =SUMIFS(member_months!$F:$F,member_months!$A:$A,$A27) -> 12 | L27: =SUMIFS(claims!$Q:$Q,claims!$B:$B,$A27) -> 2788.55 | M27: =IF(K27=0,0,L27/K27) -> 232.37917 | N27: =SUMIFS(claims!$Q:$Q,claims!$B:$B,$A27,claims!$Z:$Z,"Inpatient") -> 0 | O27: =SUMIFS(claims!$Q:$Q,claims!$B:$B,$A27,claims!$Z:$Z,"ED") -> 0 | P27: =SUMIFS(claims!$Q:$Q,claims!$B:$B,$A27,claims!$Z:$Z,"Specialty Rx") -> 1657.15 | Q27: =IF($L27>=$U$2,1,0) -> 0 | AA27: =COUNTIFS(claims!$B:$B,$A27,claims!$Z:$Z,"Behavioral Health") -> 0 | AB27: =COUNTIFS(claims!$B:$B,$A27,claims!$Z:$Z,"ED") -> 0 | AC27: =COUNTIFS(claims!$B:$B,$A27,claims!$Z:$Z,"Inpatient") -> 0 | AD27: =IF(AA27>0,1,0) -> 0 | AE27: =IF(enrollment!P27="","",enrollment!P27) | AF27: =IF(enrollment!P27="",0,1) -> 0
A28: =enrollment!A28 -> M-000027 | B28: =enrollment!F28 -> Marketplace | C28: =enrollment!I28 -> GA | D28: =enrollment!J28 -> Fulton | E28: =enrollment!L28 -> 71 | F28: {=_xlfn.IFS(E28<18,"0-17",E28<35,"18-34",E28<50,"35-49",E28<65,"50-64",TRUE,"65+")} -> 65+ | G28: =enrollment!M28 -> M | H28: =enrollment!N28 -> 3.6 | I28: =enrollment!O28 -> 8901234567 | J28: =IFERROR(_xlfn.XLOOKUP(I28,providers!$B$2:$B$11,providers!$Q$2:$Q$11),"") -> 3.7 | K28: =SUMIFS(member_months!$F:$F,member_months!$A:$A,$A28) -> 10 | L28: =SUMIFS(claims!$Q:$Q,claims!$B:$B,$A28) -> 23890.73 | M28: =IF(K28=0,0,L28/K28) -> 2389.073 | N28: =SUMIFS(claims!$Q:$Q,claims!$B:$B,$A28,claims!$Z:$Z,"Inpatient") -> 20943.86 | O28: =SUMIFS(claims!$Q:$Q,claims!$B:$B,$A28,claims!$Z:$Z,"ED") -> 1394.16 | P28: =SUMIFS(claims!$Q:$Q,claims!$B:$B,$A28,claims!$Z:$Z,"Specialty Rx") -> 842.29 | Q28: =IF($L28>=$U$2,1,0) -> 0 | AA28: =COUNTIFS(claims!$B:$B,$A28,claims!$Z:$Z,"Behavioral Health") -> 0 | AB28: =COUNTIFS(claims!$B:$B,$A28,claims!$Z:$Z,"ED") -> 1 | AC28: =COUNTIFS(claims!$B:$B,$A28,claims!$Z:$Z,"Inpatient") -> 1 | AD28: =IF(AA28>0,1,0) -> 0 | AE28: =IF(enrollment!P28="","",enrollment!P28) | AF28: =IF(enrollment!P28="",0,1) -> 0
A29: =enrollment!A29 -> M-000028 | B29: =enrollment!F29 -> Commercial | C29: =enrollment!I29 -> TN | D29: =enrollment!J29 -> Davidson | E29: =enrollment!L29 -> 72 | F29: {=_xlfn.IFS(E29<18,"0-17",E29<35,"18-34",E29<50,"35-49",E29<65,"50-64",TRUE,"65+")} -> 65+ | G29: =enrollment!M29 -> F | H29: =enrollment!N29 -> 2.15 | I29: =enrollment!O29 -> 5678901234 | J29: =IFERROR(_xlfn.XLOOKUP(I29,providers!$B$2:$B$11,providers!$Q$2:$Q$11),"") -> 3.8 | K29: =SUMIFS(member_months!$F:$F,member_months!$A:$A,$A29) -> 10 | L29: =SUMIFS(claims!$Q:$Q,claims!$B:$B,$A29) -> 17721.04 | M29: =IF(K29=0,0,L29/K29) -> 1772.104 | N29: =SUMIFS(claims!$Q:$Q,claims!$B:$B,$A29,claims!$Z:$Z,"Inpatient") -> 17435.93 | O29: =SUMIFS(claims!$Q:$Q,claims!$B:$B,$A29,claims!$Z:$Z,"ED") -> 0 | P29: =SUMIFS(claims!$Q:$Q,claims!$B:$B,$A29,claims!$Z:$Z,"Specialty Rx") -> 0 | Q29: =IF($L29>=$U$2,1,0) -> 0 | AA29: =COUNTIFS(claims!$B:$B,$A29,claims!$Z:$Z,"Behavioral Health") -> 0 | AB29: =COUNTIFS(claims!$B:$B,$A29,claims!$Z:$Z,"ED") -> 0 | AC29: =COUNTIFS(claims!$B:$B,$A29,claims!$Z:$Z,"Inpatient") -> 1 | AD29: =IF(AA29>0,1,0) -> 0 | AE29: =IF(enrollment!P29="","",enrollment!P29) | AF29: =IF(enrollment!P29="",0,1) -> 0
A30: =enrollment!A30 -> M-000029 | B30: =enrollment!F30 -> Marketplace | C30: =enrollment!I30 -> OH | D30: =enrollment!J30 -> Cuyahoga | E30: =enrollment!L30 -> 80 | F30: {=_xlfn.IFS(E30<18,"0-17",E30<35,"18-34",E30<50,"35-49",E30<65,"50-64",TRUE,"65+")} -> 65+ | G30: =enrollment!M30 -> M | H30: =enrollment!N30 -> 2.84 | I30: =enrollment!O30 -> 6789012345 | J30: =IFERROR(_xlfn.XLOOKUP(I30,providers!$B$2:$B$11,providers!$Q$2:$Q$11),"") -> 4.1 | K30: =SUMIFS(member_months!$F:$F,member_months!$A:$A,$A30) -> 11 | L30: =SUMIFS(claims!$Q:$Q,claims!$B:$B,$A30) -> 2936.92 | M30: =IF(K30=0,0,L30/K30) -> 266.99273 | N30: =SUMIFS(claims!$Q:$Q,claims!$B:$B,$A30,claims!$Z:$Z,"Inpatient") -> 0 | O30: =SUMIFS(claims!$Q:$Q,claims!$B:$B,$A30,claims!$Z:$Z,"ED") -> 2327.46 | P30: =SUMIFS(claims!$Q:$Q,claims!$B:$B,$A30,claims!$Z:$Z,"Specialty Rx") -> 0 | Q30: =IF($L30>=$U$2,1,0) -> 0 | AA30: =COUNTIFS(claims!$B:$B,$A30,claims!$Z:$Z,"Behavioral Health") -> 1 | AB30: =COUNTIFS(claims!$B:$B,$A30,claims!$Z:$Z,"ED") -> 2 | AC30: =COUNTIFS(claims!$B:$B,$A30,claims!$Z:$Z,"Inpatient") -> 0 | AD30: =IF(AA30>0,1,0) -> 1 | AE30: =IF(enrollment!P30="","",enrollment!P30) | AF30: =IF(enrollment!P30="",0,1) -> 0
A31: =enrollment!A31 -> M-000030 | B31: =enrollment!F31 -> Commercial | C31: =enrollment!I31 -> TN | D31: =enrollment!J31 -> Knox | E31: =enrollment!L31 -> 60 | F31: {=_xlfn.IFS(E31<18,"0-17",E31<35,"18-34",E31<50,"35-49",E31<65,"50-64",TRUE,"65+")} -> 50-64 | G31: =enrollment!M31 -> M | H31: =enrollment!N31 -> 1.05 | I31: =enrollment!O31 -> 7890123456 | J31: =IFERROR(_xlfn.XLOOKUP(I31,providers!$B$2:$B$11,providers!$Q$2:$Q$11),"") -> 3.9 | K31: =SUMIFS(member_months!$F:$F,member_months!$A:$A,$A31) -> 12 | L31: =SUMIFS(claims!$Q:$Q,claims!$B:$B,$A31) -> 3469.88 | M31: =IF(K31=0,0,L31/K31) -> 289.15667 | N31: =SUMIFS(claims!$Q:$Q,claims!$B:$B,$A31,claims!$Z:$Z,"Inpatient") -> 0 | O31: =SUMIFS(claims!$Q:$Q,claims!$B:$B,$A31,claims!$Z:$Z,"ED") -> 1222.1 | P31: =SUMIFS(claims!$Q:$Q,claims!$B:$B,$A31,claims!$Z:$Z,"Specialty Rx") -> 1962.6 | Q31: =IF($L31>=$U$2,1,0) -> 0 | AA31: =COUNTIFS(claims!$B:$B,$A31,claims!$Z:$Z,"Behavioral Health") -> 0 | AB31: =COUNTIFS(claims!$B:$B,$A31,claims!$Z:$Z,"ED") -> 1 | AC31: =COUNTIFS(claims!$B:$B,$A31,claims!$Z:$Z,"Inpatient") -> 0 | AD31: =IF(AA31>0,1,0) -> 0 | AE31: =IF(enrollment!P31="","",enrollment!P31) | AF31: =IF(enrollment!P31="",0,1) -> 0
A32: =enrollment!A32 -> M-000031 | B32: =enrollment!F32 -> Commercial | C32: =enrollment!I32 -> TN | D32: =enrollment!J32 -> Rural-Cannon | E32: =enrollment!L32 -> 53 | F32: {=_xlfn.IFS(E32<18,"0-17",E32<35,"18-34",E32<50,"35-49",E32<65,"50-64",TRUE,"65+")} -> 50-64 | G32: =enrollment!M32 -> F | H32: =enrollment!N32 -> 1.4 | I32: =enrollment!O32 -> 2233445566 | J32: =IFERROR(_xlfn.XLOOKUP(I32,providers!$B$2:$B$11,providers!$Q$2:$Q$11),"") -> 3.5 | K32: =SUMIFS(member_months!$F:$F,member_months!$A:$A,$A32) -> 12 | L32: =SUMIFS(claims!$Q:$Q,claims!$B:$B,$A32) -> 2391.46 | M32: =IF(K32=0,0,L32/K32) -> 199.28833 | N32: =SUMIFS(claims!$Q:$Q,claims!$B:$B,$A32,claims!$Z:$Z,"Inpatient") -> 0 | O32: =SUMIFS(claims!$Q:$Q,claims!$B:$B,$A32,claims!$Z:$Z,"ED") -> 1782.4 | P32: =SUMIFS(claims!$Q:$Q,claims!$B:$B,$A32,claims!$Z:$Z,"Specialty Rx") -> 0 | Q32: =IF($L32>=$U$2,1,0) -> 0 | AA32: =COUNTIFS(claims!$B:$B,$A32,claims!$Z:$Z,"Behavioral Health") -> 0 | AB32: =COUNTIFS(claims!$B:$B,$A32,claims!$Z:$Z,"ED") -> 2 | AC32: =COUNTIFS(claims!$B:$B,$A32,claims!$Z:$Z,"Inpatient") -> 0 | AD32: =IF(AA32>0,1,0) -> 0 | AE32: =IF(enrollment!P32="","",enrollment!P32) | AF32: =IF(enrollment!P32="",0,1) -> 0
A33: =enrollment!A33 -> M-000032 | B33: =enrollment!F33 -> Commercial | C33: =enrollment!I33 -> OH | D33: =enrollment!J33 -> Cuyahoga | E33: =enrollment!L33 -> 79 | F33: {=_xlfn.IFS(E33<18,"0-17",E33<35,"18-34",E33<50,"35-49",E33<65,"50-64",TRUE,"65+")} -> 65+ | G33: =enrollment!M33 -> F | H33: =enrollment!N33 -> 2.1 | I33: =enrollment!O33 -> 2345678901 | J33: =IFERROR(_xlfn.XLOOKUP(I33,providers!$B$2:$B$11,providers!$Q$2:$Q$11),"") -> 4.2 | K33: =SUMIFS(member_months!$F:$F,member_months!$A:$A,$A33) -> 12 | L33: =SUMIFS(claims!$Q:$Q,claims!$B:$B,$A33) -> 28865.21 | M33: =IF(K33=0,0,L33/K33) -> 2405.4342 | N33: =SUMIFS(claims!$Q:$Q,claims!$B:$B,$A33,claims!$Z:$Z,"Inpatient") -> 27155.48 | O33: =SUMIFS(claims!$Q:$Q,claims!$B:$B,$A33,claims!$Z:$Z,"ED") -> 0 | P33: =SUMIFS(claims!$Q:$Q,claims!$B:$B,$A33,claims!$Z:$Z,"Specialty Rx") -> 840.18 | Q33: =IF($L33>=$U$2,1,0) -> 0 | AA33: =COUNTIFS(claims!$B:$B,$A33,claims!$Z:$Z,"Behavioral Health") -> 1 | AB33: =COUNTIFS(claims!$B:$B,$A33,claims!$Z:$Z,"ED") -> 0 | AC33: =COUNTIFS(claims!$B:$B,$A33,claims!$Z:$Z,"Inpatient") -> 2 | AD33: =IF(AA33>0,1,0) -> 1 | AE33: =IF(enrollment!P33="","",enrollment!P33) | AF33: =IF(enrollment!P33="",0,1) -> 0
A34: =enrollment!A34 -> M-000033 | B34: =enrollment!F34 -> Commercial | C34: =enrollment!I34 -> TN | D34: =enrollment!J34 -> Davidson | E34: =enrollment!L34 -> 75 | F34: {=_xlfn.IFS(E34<18,"0-17",E34<35,"18-34",E34<50,"35-49",E34<65,"50-64",TRUE,"65+")} -> 65+ | G34: =enrollment!M34 -> F | H34: =enrollment!N34 -> 2.66 | I34: =enrollment!O34 -> 7890123456 | J34: =IFERROR(_xlfn.XLOOKUP(I34,providers!$B$2:$B$11,providers!$Q$2:$Q$11),"") -> 3.9 | K34: =SUMIFS(member_months!$F:$F,member_months!$A:$A,$A34) -> 12 | L34: =SUMIFS(claims!$Q:$Q,claims!$B:$B,$A34) -> 23139.01 | M34: =IF(K34=0,0,L34/K34) -> 1928.2508 | N34: =SUMIFS(claims!$Q:$Q,claims!$B:$B,$A34,claims!$Z:$Z,"Inpatient") -> 20664.86 | O34: =SUMIFS(claims!$Q:$Q,claims!$B:$B,$A34,claims!$Z:$Z,"ED") -> 2135.9 | P34: =SUMIFS(claims!$Q:$Q,claims!$B:$B,$A34,claims!$Z:$Z,"Specialty Rx") -> 0 | Q34: =IF($L34>=$U$2,1,0) -> 0 | AA34: =COUNTIFS(claims!$B:$B,$A34,claims!$Z:$Z,"Behavioral Health") -> 1 | AB34: =COUNTIFS(claims!$B:$B,$A34,claims!$Z:$Z,"ED") -> 2 | AC34: =COUNTIFS(claims!$B:$B,$A34,claims!$Z:$Z,"Inpatient") -> 1 | AD34: =IF(AA34>0,1,0) -> 1 | AE34: =IF(enrollment!P34="","",enrollment!P34) | AF34: =IF(enrollment!P34="",0,1) -> 0
A35: =enrollment!A35 -> M-000034 | B35: =enrollment!F35 -> Medicare Advantage | C35: =enrollment!I35 -> OH | D35: =enrollment!J35 -> Cuyahoga | E35: =enrollment!L35 -> 82 | F35: {=_xlfn.IFS(E35<18,"0-17",E35<35,"18-34",E35<50,"35-49",E35<65,"50-64",TRUE,"65+")} -> 65+ | G35: =enrollment!M35 -> M | H35: =enrollment!N35 -> 2.33 | I35: =enrollment!O35 -> 6789012345 | J35: =IFERROR(_xlfn.XLOOKUP(I35,providers!$B$2:$B$11,providers!$Q$2:$Q$11),"") -> 4.1 | K35: =SUMIFS(member_months!$F:$F,member_months!$A:$A,$A35) -> 12 | L35: =SUMIFS(claims!$Q:$Q,claims!$B:$B,$A35) -> 2574.64 | M35: =IF(K35=0,0,L35/K35) -> 214.55333 | N35: =SUMIFS(claims!$Q:$Q,claims!$B:$B,$A35,claims!$Z:$Z,"Inpatient") -> 0 | O35: =SUMIFS(claims!$Q:$Q,claims!$B:$B,$A35,claims!$Z:$Z,"ED") -> 1097.76 | P35: =SUMIFS(claims!$Q:$Q,claims!$B:$B,$A35,claims!$Z:$Z,"Specialty Rx") -> 819.55 | Q35: =IF($L35>=$U$2,1,0) -> 0 | AA35: =COUNTIFS(claims!$B:$B,$A35,claims!$Z:$Z,"Behavioral Health") -> 1 | AB35: =COUNTIFS(claims!$B:$B,$A35,claims!$Z:$Z,"ED") -> 1 | AC35: =COUNTIFS(claims!$B:$B,$A35,claims!$Z:$Z,"Inpatient") -> 0 | AD35: =IF(AA35>0,1,0) -> 1 | AE35: =IF(enrollment!P35="","",enrollment!P35) | AF35: =IF(enrollment!P35="",0,1) -> 0
A36: =enrollment!A36 -> M-000035 | B36: =enrollment!F36 -> Commercial | C36: =enrollment!I36 -> GA | D36: =enrollment!J36 -> Cherokee | E36: =enrollment!L36 -> 50 | F36: {=_xlfn.IFS(E36<18,"0-17",E36<35,"18-34",E36<50,"35-49",E36<65,"50-64",TRUE,"65+")} -> 50-64 | G36: =enrollment!M36 -> F | H36: =enrollment!N36 -> 1.32 | I36: =enrollment!O36 -> 8901234567 | J36: =IFERROR(_xlfn.XLOOKUP(I36,providers!$B$2:$B$11,providers!$Q$2:$Q$11),"") -> 3.7 | K36: =SUMIFS(member_months!$F:$F,member_months!$A:$A,$A36) -> 12 | L36: =SUMIFS(claims!$Q:$Q,claims!$B:$B,$A36) -> 22105.83 | M36: =IF(K36=0,0,L36/K36) -> 1842.1525 | N36: =SUMIFS(claims!$Q:$Q,claims!$B:$B,$A36,claims!$Z:$Z,"Inpatient") -> 21302.15 | O36: =SUMIFS(claims!$Q:$Q,claims!$B:$B,$A36,claims!$Z:$Z,"ED") -> 0 | P36: =SUMIFS(claims!$Q:$Q,claims!$B:$B,$A36,claims!$Z:$Z,"Specialty Rx") -> 0 | Q36: =IF($L36>=$U$2,1,0) -> 0 | AA36: =COUNTIFS(claims!$B:$B,$A36,claims!$Z:$Z,"Behavioral Health") -> 0 | AB36: =COUNTIFS(claims!$B:$B,$A36,claims!$Z:$Z,"ED") -> 0 | AC36: =COUNTIFS(claims!$B:$B,$A36,claims!$Z:$Z,"Inpatient") -> 1 | AD36: =IF(AA36>0,1,0) -> 0 | AE36: =IF(enrollment!P36="","",enrollment!P36) | AF36: =IF(enrollment!P36="",0,1) -> 0
A37: =enrollment!A37 -> M-000036 | B37: =enrollment!F37 -> Commercial | C37: =enrollment!I37 -> OH | D37: =enrollment!J37 -> Cuyahoga | E37: =enrollment!L37 -> 40 | F37: {=_xlfn.IFS(E37<18,"0-17",E37<35,"18-34",E37<50,"35-49",E37<65,"50-64",TRUE,"65+")} -> 35-49 | G37: =enrollment!M37 -> F | H37: =enrollment!N37 -> 1.11 | I37: =enrollment!O37 -> 2345678901 | J37: =IFERROR(_xlfn.XLOOKUP(I37,providers!$B$2:$B$11,providers!$Q$2:$Q$11),"") -> 4.2 | K37: =SUMIFS(member_months!$F:$F,member_months!$A:$A,$A37) -> 10 | L37: =SUMIFS(claims!$Q:$Q,claims!$B:$B,$A37) -> 24165.55 | M37: =IF(K37=0,0,L37/K37) -> 2416.555 | N37: =SUMIFS(claims!$Q:$Q,claims!$B:$B,$A37,claims!$Z:$Z,"Inpatient") -> 18270.83 | O37: =SUMIFS(claims!$Q:$Q,claims!$B:$B,$A37,claims!$Z:$Z,"ED") -> 2619.25 | P37: =SUMIFS(claims!$Q:$Q,claims!$B:$B,$A37,claims!$Z:$Z,"Specialty Rx") -> 2878.85 | Q37: =IF($L37>=$U$2,1,0) -> 0 | AA37: =COUNTIFS(claims!$B:$B,$A37,claims!$Z:$Z,"Behavioral Health") -> 0 | AB37: =COUNTIFS(claims!$B:$B,$A37,claims!$Z:$Z,"ED") -> 2 | AC37: =COUNTIFS(claims!$B:$B,$A37,claims!$Z:$Z,"Inpatient") -> 1 | AD37: =IF(AA37>0,1,0) -> 0 | AE37: =IF(enrollment!P37="","",enrollment!P37) | AF37: =IF(enrollment!P37="",0,1) -> 0
A38: =enrollment!A38 -> M-000037 | B38: =enrollment!F38 -> Medicare Advantage | C38: =enrollment!I38 -> KY | D38: =enrollment!J38 -> Warren | E38: =enrollment!L38 -> 84 | F38: {=_xlfn.IFS(E38<18,"0-17",E38<35,"18-34",E38<50,"35-49",E38<65,"50-64",TRUE,"65+")} -> 65+ | G38: =enrollment!M38 -> F | H38: =enrollment!N38 -> 2.06 | I38: =enrollment!O38 -> 9012345678 | J38: =IFERROR(_xlfn.XLOOKUP(I38,providers!$B$2:$B$11,providers!$Q$2:$Q$11),"") -> 4.3 | K38: =SUMIFS(member_months!$F:$F,member_months!$A:$A,$A38) -> 10 | L38: =SUMIFS(claims!$Q:$Q,claims!$B:$B,$A38) -> 39188.72 | M38: =IF(K38=0,0,L38/K38) -> 3918.872 | N38: =SUMIFS(claims!$Q:$Q,claims!$B:$B,$A38,claims!$Z:$Z,"Inpatient") -> 39024.93 | O38: =SUMIFS(claims!$Q:$Q,claims!$B:$B,$A38,claims!$Z:$Z,"ED") -> 0 | P38: =SUMIFS(claims!$Q:$Q,claims!$B:$B,$A38,claims!$Z:$Z,"Specialty Rx") -> 0 | Q38: =IF($L38>=$U$2,1,0) -> 0 | AA38: =COUNTIFS(claims!$B:$B,$A38,claims!$Z:$Z,"Behavioral Health") -> 0 | AB38: =COUNTIFS(claims!$B:$B,$A38,claims!$Z:$Z,"ED") -> 0 | AC38: =COUNTIFS(claims!$B:$B,$A38,claims!$Z:$Z,"Inpatient") -> 2 | AD38: =IF(AA38>0,1,0) -> 0 | AE38: =IF(enrollment!P38="","",enrollment!P38) | AF38: =IF(enrollment!P38="",0,1) -> 0
... A801: =enrollment!A801 -> M-000800 | B801: =enrollment!F801 -> Medicare Advantage | C801: =enrollment!I801 -> GA | D801: =enrollment!J801 -> Fulton | E801: =enrollment!L801 -> 72 | F801: {=_xlfn.IFS(E801<18,"0-17",E801<35,"18-34",E801<50,"35-49",E801<65,"50-64",TRUE,"65+")} -> 65+ | G801: =enrollment!M801 -> F | H801: =enrollment!N801 -> 3.49 | I801: =enrollment!O801 -> 8901234567 | J801: =IFERROR(_xlfn.XLOOKUP(I801,providers!$B$2:$B$11,providers!$Q$2:$Q$11),"") -> 3.7 | K801: =SUMIFS(member_months!$F:$F,member_months!$A:$A,$A801) -> 11 | L801: =SUMIFS(claims!$Q:$Q,claims!$B:$B,$A801) -> 2384.85 | M801: =IF(K801=0,0,L801/K801) -> 216.80455 | N801: =SUMIFS(claims!$Q:$Q,claims!$B:$B,$A801,claims!$Z:$Z,"Inpatient") -> 0 | O801: =SUMIFS(claims!$Q:$Q,claims!$B:$B,$A801,claims!$Z:$Z,"ED") -> 0 | P801: =SUMIFS(claims!$Q:$Q,claims!$B:$B,$A801,claims!$Z:$Z,"Specialty Rx") -> 1608.17 | Q801: =IF($L801>=$U$2,1,0) -> 0 | AA801: =COUNTIFS(claims!$B:$B,$A801,claims!$Z:$Z,"Behavioral Health") -> 0 | AB801: =COUNTIFS(claims!$B:$B,$A801,claims!$Z:$Z,"ED") -> 0 | AC801: =COUNTIFS(claims!$B:$B,$A801,claims!$Z:$Z,"Inpatient") -> 0 | AD801: =IF(AA801>0,1,0) -> 0 | AE801: =IF(enrollment!P801="","",enrollment!P801) | AF801: =IF(enrollment!P801="",0,1) -> 0

Sheet Category Spend
A1: SPEND BY SERVICE CATEGORY (2024 allowed)
A2: Category | B2: Claims | C2: Allowed | D2: % of Allowed | E2: Avg Allowed/Claim
A3: Inpatient | B3: =COUNTIFS(claims!$Z:$Z,$A3) -> 528 | C3: =SUMIFS(claims!$Q:$Q,claims!$Z:$Z,$A3) -> 8631818.3 | D3: =C3/$C$9 -> 0.7624438 | E3: =IF(B3=0,0,C3/B3) -> 16348.141
A4: ED | B4: =COUNTIFS(claims!$Z:$Z,$A4) -> 1209 | C4: =SUMIFS(claims!$Q:$Q,claims!$Z:$Z,$A4) -> 1362281.7 | D4: =C4/$C$9 -> 0.1203296 | E4: =IF(B4=0,0,C4/B4) -> 1126.7839
A5: Specialty Rx | B5: =COUNTIFS(claims!$Z:$Z,$A5) -> 657 | C5: =SUMIFS(claims!$Q:$Q,claims!$Z:$Z,$A5) -> 791233.42 | D5: =C5/$C$9 -> 0.069889217 | E5: =IF(B5=0,0,C5/B5) -> 1204.3127
A6: PCP | B6: =COUNTIFS(claims!$Z:$Z,$A6) -> 2387 | C6: =SUMIFS(claims!$Q:$Q,claims!$Z:$Z,$A6) -> 357410.25 | D6: =C6/$C$9 -> 0.031569852 | E6: =IF(B6=0,0,C6/B6) -> 149.73199
A7: Urgent Care | B7: =COUNTIFS(claims!$Z:$Z,$A7) -> 700 | C7: =SUMIFS(claims!$Q:$Q,claims!$Z:$Z,$A7) -> 94287.55 | D7: =C7/$C$9 -> 0.0083283679 | E7: =IF(B7=0,0,C7/B7) -> 134.6965
A8: Behavioral Health | B8: =COUNTIFS(claims!$Z:$Z,$A8) -> 480 | C8: =SUMIFS(claims!$Q:$Q,claims!$Z:$Z,$A8) -> 84220.61 | D8: =C8/$C$9 -> 0.0074391606 | E8: =IF(B8=0,0,C8/B8) -> 175.4596
A9: Total | B9: =SUM(B3:B8) -> 5961 | C9: =SUM(C3:C8) -> 11321252 | D9: =C9/$C$9 -> 1 | E9: =C9/B9 -> 1899.2202
A11: SPECIALTY Rx BY THERAPEUTIC CLASS
A12: Therapeutic Class | B12: Scripts | C12: Allowed | D12: Avg/Script | E12: % of Specialty Rx
A13: Oncology Biologic | B13: =COUNTIFS(claims!$N:$N,$A13) -> 175 | C13: =SUMIFS(claims!$Q:$Q,claims!$N:$N,$A13) -> 337014.63 | D13: =IF(B13=0,0,C13/B13) -> 1925.7979 | E13: =C13/$C$5 -> 0.42593579
A14: GLP-1 Agonist | B14: =COUNTIFS(claims!$N:$N,$A14) -> 193 | C14: =SUMIFS(claims!$Q:$Q,claims!$N:$N,$A14) -> 181625.17 | D14: =IF(B14=0,0,C14/B14) -> 941.06306 | E14: =C14/$C$5 -> 0.22954689
A15: Autoimmune Biologic | B15: =COUNTIFS(claims!$N:$N,$A15) -> 138 | C15: =SUMIFS(claims!$Q:$Q,claims!$N:$N,$A15) -> 132809.59 | D15: =IF(B15=0,0,C15/B15) -> 962.38833 | E15: =C15/$C$5 -> 0.16785134
A16: Diabetes | B16: =COUNTIFS(claims!$N:$N,$A16) -> 151 | C16: =SUMIFS(claims!$Q:$Q,claims!$N:$N,$A16) -> 139784.03 | D16: =IF(B16=0,0,C16/B16) -> 925.72205 | E16: =C16/$C$5 -> 0.17666598
A17: Total | B17: =SUM(B13:B16) -> 657 | C17: =SUM(C13:C16) -> 791233.42 | D17: =C17/B17 -> 1204.3127 | E17: =C17/$C$5 -> 1
A19: ALLOWED BY CATEGORY × LOB
A20: Category | B20: Commercial | C20: Marketplace | D20: Medicare Advantage | E20: Total
A21: Inpatient | B21: =SUMIFS(claims!$Q:$Q,claims!$Z:$Z,$A21,claims!$Y:$Y,B$20) -> 3400019.9 | C21: =SUMIFS(claims!$Q:$Q,claims!$Z:$Z,$A21,claims!$Y:$Y,C$20) -> 3310145.1 | D21: =SUMIFS(claims!$Q:$Q,claims!$Z:$Z,$A21,claims!$Y:$Y,D$20) -> 1921653.3 | E21: =SUM(B21:D21) -> 8631818.3
A22: ED | B22: =SUMIFS(claims!$Q:$Q,claims!$Z:$Z,$A22,claims!$Y:$Y,B$20) -> 618563.94 | C22: =SUMIFS(claims!$Q:$Q,claims!$Z:$Z,$A22,claims!$Y:$Y,C$20) -> 496647.01 | D22: =SUMIFS(claims!$Q:$Q,claims!$Z:$Z,$A22,claims!$Y:$Y,D$20) -> 247070.78 | E22: =SUM(B22:D22) -> 1362281.7
A23: Specialty Rx | B23: =SUMIFS(claims!$Q:$Q,claims!$Z:$Z,$A23,claims!$Y:$Y,B$20) -> 236147.02 | C23: =SUMIFS(claims!$Q:$Q,claims!$Z:$Z,$A23,claims!$Y:$Y,C$20) -> 222957.52 | D23: =SUMIFS(claims!$Q:$Q,claims!$Z:$Z,$A23,claims!$Y:$Y,D$20) -> 332128.88 | E23: =SUM(B23:D23) -> 791233.42
A24: PCP | B24: =SUMIFS(claims!$Q:$Q,claims!$Z:$Z,$A24,claims!$Y:$Y,B$20) -> 144676.18 | C24: =SUMIFS(claims!$Q:$Q,claims!$Z:$Z,$A24,claims!$Y:$Y,C$20) -> 138307.42 | D24: =SUMIFS(claims!$Q:$Q,claims!$Z:$Z,$A24,claims!$Y:$Y,D$20) -> 74426.65 | E24: =SUM(B24:D24) -> 357410.25
A25: Urgent Care | B25: =SUMIFS(claims!$Q:$Q,claims!$Z:$Z,$A25,claims!$Y:$Y,B$20) -> 42770.27 | C25: =SUMIFS(claims!$Q:$Q,claims!$Z:$Z,$A25,claims!$Y:$Y,C$20) -> 31785.17 | D25: =SUMIFS(claims!$Q:$Q,claims!$Z:$Z,$A25,claims!$Y:$Y,D$20) -> 19732.11 | E25: =SUM(B25:D25) -> 94287.55
A26: Behavioral Health | B26: =SUMIFS(claims!$Q:$Q,claims!$Z:$Z,$A26,claims!$Y:$Y,B$20) -> 37968.4 | C26: =SUMIFS(claims!$Q:$Q,claims!$Z:$Z,$A26,claims!$Y:$Y,C$20) -> 30159.15 | D26: =SUMIFS(claims!$Q:$Q,claims!$Z:$Z,$A26,claims!$Y:$Y,D$20) -> 16093.06 | E26: =SUM(B26:D26) -> 84220.61
A27: Total | B27: =SUM(B21:B26) -> 4480145.7 | C27: =SUM(C21:C26) -> 4230001.4 | D27: =SUM(D21:D26) -> 2611104.8 | E27: =SUM(E21:E26) -> 11321252
A29: SCENARIO A — SPECIALTY PHARMACY ALLOWED REDUCTION
A30: Reduction % (input) | B30: 0.05 | C30: 0.1 | D30: 0.15
A31: Annual savings | B31: =$C$5*B30 -> 39561.671 | C31: =$C$5*C30 -> 79123.342 | D31: =$C$5*D30 -> 118685.01
A32: Blended PMPM impact | B32: =B31/'Member Spend'!$U$10 -> 4.6752152 | C32: =C31/'Member Spend'!$U$10 -> 9.3504304 | D32: =D31/'Member Spend'!$U$10 -> 14.025646
A33: Applied to current Specialty Rx allowed: | B33: =C5 -> 791233.42
A35: SCENARIO B — ED DIVERSION TO URGENT CARE
A36: Avoidable + Potentially Avoidable ED visits | B36: =COUNTIFS(claims!$Z:$Z,"ED",claims!$AA:$AA,"Avoidable")+COUNTIFS(claims!$Z:$Z,"ED",claims!$AA:$AA,"Potentially Avoidable") -> 914
A37: Shift rate to urgent care (input) | B37: 0.2
A38: Diverted visits | B38: =B36*B37 -> 182.8
A39: Avg allowed per ED visit | B39: =E4 -> 1126.7839
A40: Avg allowed per urgent care visit | B40: =E7 -> 134.6965
A41: Savings per diverted visit | B41: =B39-B40 -> 992.0874
A42: Total ED diversion savings | B42: =B38*B41 -> 181353.58
A43: Blended PMPM impact | B43: =B42/'Member Spend'!$U$10 -> 21.431526
A45: COMBINED ANNUAL SAVINGS OPPORTUNITY
A46: Specialty Rx reduction (10% case) | B46: =C31 -> 79123.342
A47: ED diversion (20% shift) | B47: =B42 -> 181353.58
A48: Total identified savings | B48: =B46+B47 -> 260476.92
A49: % of total allowed | B49: =B48/$C$9 -> 0.023007784

Sheet Avoidable ED
A1: ED VISITS BY AVOIDABILITY (ICD-10 join)
A2: Category | B2: Visits | C2: Allowed | D2: Avg/Visit | E2: % of ED Visits | F2: % of ED Allowed
A3: Avoidable | B3: =COUNTIFS(claims!$Z:$Z,"ED",claims!$AA:$AA,$A3) -> 613 | C3: =SUMIFS(claims!$Q:$Q,claims!$Z:$Z,"ED",claims!$AA:$AA,$A3) -> 694188.55 | D3: =IF(B3=0,0,C3/B3) -> 1132.4446 | E3: =B3/$B$6 -> 0.5070306 | F3: =C3/$C$6 -> 0.50957782
A4: Potentially Avoidable | B4: =COUNTIFS(claims!$Z:$Z,"ED",claims!$AA:$AA,$A4) -> 301 | C4: =SUMIFS(claims!$Q:$Q,claims!$Z:$Z,"ED",claims!$AA:$AA,$A4) -> 333395.24 | D4: =IF(B4=0,0,C4/B4) -> 1107.6254 | E4: =B4/$B$6 -> 0.24896609 | F4: =C4/$C$6 -> 0.24473296
A5: Non-Avoidable | B5: =COUNTIFS(claims!$Z:$Z,"ED",claims!$AA:$AA,$A5) -> 295 | C5: =SUMIFS(claims!$Q:$Q,claims!$Z:$Z,"ED",claims!$AA:$AA,$A5) -> 334697.94 | D5: =IF(B5=0,0,C5/B5) -> 1134.5693 | E5: =B5/$B$6 -> 0.24400331 | F5: =C5/$C$6 -> 0.24568922
A6: Total | B6: =COUNTIFS(claims!$Z:$Z,"ED") -> 1209 | C6: =SUMIFS(claims!$Q:$Q,claims!$Z:$Z,"ED") -> 1362281.7 | D6: =C6/B6 -> 1126.7839 | E6: =B6/$B$6 -> 1 | F6: =C6/$C$6 -> 1
A8: ED UTILIZATION PER 1,000 BY LOB
A9: LOB | B9: ED Visits | C9: Member Months | D9: ED / 1,000 | E9: Avoidable+PA Visits | F9: Avoidable ED / 1,000
A10: Commercial | B10: =COUNTIFS(claims!$Z:$Z,"ED",claims!$Y:$Y,$A10) -> 547 | C10: =SUMIFS(member_months!$F:$F,member_months!$C:$C,$A10) -> 3733 | D10: =B10/C10*1000 -> 146.53094 | E10: =COUNTIFS(claims!$Z:$Z,"ED",claims!$Y:$Y,$A10,claims!$AA:$AA,"Avoidable")+COUNTIFS(claims!$Z:$Z,"ED",claims!$Y:$Y,$A10,claims!$AA:$AA,"Potentially Avoidable") -> 417 | F10: =E10/C10*1000 -> 111.7064
A11: Marketplace | B11: =COUNTIFS(claims!$Z:$Z,"ED",claims!$Y:$Y,$A11) -> 444 | C11: =SUMIFS(member_months!$F:$F,member_months!$C:$C,$A11) -> 3088 | D11: =B11/C11*1000 -> 143.78238 | E11: =COUNTIFS(claims!$Z:$Z,"ED",claims!$Y:$Y,$A11,claims!$AA:$AA,"Avoidable")+COUNTIFS(claims!$Z:$Z,"ED",claims!$Y:$Y,$A11,claims!$AA:$AA,"Potentially Avoidable") -> 326 | F11: =E11/C11*1000 -> 105.56995
A12: Medicare Advantage | B12: =COUNTIFS(claims!$Z:$Z,"ED",claims!$Y:$Y,$A12) -> 218 | C12: =SUMIFS(member_months!$F:$F,member_months!$C:$C,$A12) -> 1641 | D12: =B12/C12*1000 -> 132.84583 | E12: =COUNTIFS(claims!$Z:$Z,"ED",claims!$Y:$Y,$A12,claims!$AA:$AA,"Avoidable")+COUNTIFS(claims!$Z:$Z,"ED",claims!$Y:$Y,$A12,claims!$AA:$AA,"Potentially Avoidable") -> 171 | F12: =E12/C12*1000 -> 104.20475
A13: Total | B13: =SUM(B10:B12) -> 1209 | C13: =SUM(C10:C12) -> 8462 | D13: =B13/C13*1000 -> 142.87403 | E13: =SUM(E10:E12) -> 914 | F13: =E13/C13*1000 -> 108.01229
A15: ED BY AGE BAND
A16: Age Band | B16: ED Visits | C16: Avoidable+PA | D16: Avoidable % | E16: Allowed | F16: Avg/Visit
A17: 0-17 | B17: =COUNTIFS(claims!$Z:$Z,"ED",claims!$AD:$AD,$A17) -> 0 | C17: =COUNTIFS(claims!$Z:$Z,"ED",claims!$AD:$AD,$A17,claims!$AA:$AA,"Avoidable")+COUNTIFS(claims!$Z:$Z,"ED",claims!$AD:$AD,$A17,claims!$AA:$AA,"Potentially Avoidable") -> 0 | D17: =IF(B17=0,0,C17/B17) -> 0 | E17: =SUMIFS(claims!$Q:$Q,claims!$Z:$Z,"ED",claims!$AD:$AD,$A17) -> 0 | F17: =IF(B17=0,0,E17/B17) -> 0
A18: 18-34 | B18: =COUNTIFS(claims!$Z:$Z,"ED",claims!$AD:$AD,$A18) -> 201 | C18: =COUNTIFS(claims!$Z:$Z,"ED",claims!$AD:$AD,$A18,claims!$AA:$AA,"Avoidable")+COUNTIFS(claims!$Z:$Z,"ED",claims!$AD:$AD,$A18,claims!$AA:$AA,"Potentially Avoidable") -> 157 | D18: =IF(B18=0,0,C18/B18) -> 0.78109453 | E18: =SUMIFS(claims!$Q:$Q,claims!$Z:$Z,"ED",claims!$AD:$AD,$A18) -> 226987.48 | F18: =IF(B18=0,0,E18/B18) -> 1129.2909
A19: 35-49 | B19: =COUNTIFS(claims!$Z:$Z,"ED",claims!$AD:$AD,$A19) -> 246 | C19: =COUNTIFS(claims!$Z:$Z,"ED",claims!$AD:$AD,$A19,claims!$AA:$AA,"Avoidable")+COUNTIFS(claims!$Z:$Z,"ED",claims!$AD:$AD,$A19,claims!$AA:$AA,"Potentially Avoidable") -> 191 | D19: =IF(B19=0,0,C19/B19) -> 0.77642276 | E19: =SUMIFS(claims!$Q:$Q,claims!$Z:$Z,"ED",claims!$AD:$AD,$A19) -> 273468.42 | F19: =IF(B19=0,0,E19/B19) -> 1111.6602
A20: 50-64 | B20: =COUNTIFS(claims!$Z:$Z,"ED",claims!$AD:$AD,$A20) -> 280 | C20: =COUNTIFS(claims!$Z:$Z,"ED",claims!$AD:$AD,$A20,claims!$AA:$AA,"Avoidable")+COUNTIFS(claims!$Z:$Z,"ED",claims!$AD:$AD,$A20,claims!$AA:$AA,"Potentially Avoidable") -> 208 | D20: =IF(B20=0,0,C20/B20) -> 0.74285714 | E20: =SUMIFS(claims!$Q:$Q,claims!$Z:$Z,"ED",claims!$AD:$AD,$A20) -> 317173.67 | F20: =IF(B20=0,0,E20/B20) -> 1132.7631
A21: 65+ | B21: =COUNTIFS(claims!$Z:$Z,"ED",claims!$AD:$AD,$A21) -> 482 | C21: =COUNTIFS(claims!$Z:$Z,"ED",claims!$AD:$AD,$A21,claims!$AA:$AA,"Avoidable")+COUNTIFS(claims!$Z:$Z,"ED",claims!$AD:$AD,$A21,claims!$AA:$AA,"Potentially Avoidable") -> 358 | D21: =IF(B21=0,0,C21/B21) -> 0.74273859 | E21: =SUMIFS(claims!$Q:$Q,claims!$Z:$Z,"ED",claims!$AD:$AD,$A21) -> 544652.16 | F21: =IF(B21=0,0,E21/B21) -> 1129.9837
A22: Total | B22: =SUM(B17:B21) -> 1209 | C22: =SUM(C17:C21) -> 914 | D22: =IF(B22=0,0,C22/B22) -> 0.75599669 | E22: =SUM(E17:E21) -> 1362281.7 | F22: =IF(B22=0,0,E22/B22) -> 1126.7839
A24: ED BY STATE
A25: State | B25: ED Visits | C25: Member Months | D25: ED / 1,000 | E25: Avoidable % | F25: Allowed
A26: KY | B26: =COUNTIFS(claims!$Z:$Z,"ED",claims!$AB:$AB,$A26) -> 193 | C26: =SUMIFS(member_months!$F:$F,member_months!$D:$D,$A26) -> 1911 | D26: =B26/C26*1000 -> 100.99424 | E26: =(COUNTIFS(claims!$Z:$Z,"ED",claims!$AB:$AB,$A26,claims!$AA:$AA,"Avoidable")+COUNTIFS(claims!$Z:$Z,"ED",claims!$AB:$AB,$A26,claims!$AA:$AA,"Potentially Avoidable"))/B26 -> 0.7253886 | F26: =SUMIFS(claims!$Q:$Q,claims!$Z:$Z,"ED",claims!$AB:$AB,$A26) -> 217692.64
A27: GA | B27: =COUNTIFS(claims!$Z:$Z,"ED",claims!$AB:$AB,$A27) -> 223 | C27: =SUMIFS(member_months!$F:$F,member_months!$D:$D,$A27) -> 2043 | D27: =B27/C27*1000 -> 109.15321 | E27: =(COUNTIFS(claims!$Z:$Z,"ED",claims!$AB:$AB,$A27,claims!$AA:$AA,"Avoidable")+COUNTIFS(claims!$Z:$Z,"ED",claims!$AB:$AB,$A27,claims!$AA:$AA,"Potentially Avoidable"))/B27 -> 0.76233184 | F27: =SUMIFS(claims!$Q:$Q,claims!$Z:$Z,"ED",claims!$AB:$AB,$A27) -> 248450.22
A28: TN | B28: =COUNTIFS(claims!$Z:$Z,"ED",claims!$AB:$AB,$A28) -> 537 | C28: =SUMIFS(member_months!$F:$F,member_months!$D:$D,$A28) -> 2160 | D28: =B28/C28*1000 -> 248.61111 | E28: =(COUNTIFS(claims!$Z:$Z,"ED",claims!$AB:$AB,$A28,claims!$AA:$AA,"Avoidable")+COUNTIFS(claims!$Z:$Z,"ED",claims!$AB:$AB,$A28,claims!$AA:$AA,"Potentially Avoidable"))/B28 -> 0.77467412 | F28: =SUMIFS(claims!$Q:$Q,claims!$Z:$Z,"ED",claims!$AB:$AB,$A28) -> 607669.77
A29: OH | B29: =COUNTIFS(claims!$Z:$Z,"ED",claims!$AB:$AB,$A29) -> 256 | C29: =SUMIFS(member_months!$F:$F,member_months!$D:$D,$A29) -> 2348 | D29: =B29/C29*1000 -> 109.02896 | E29: =(COUNTIFS(claims!$Z:$Z,"ED",claims!$AB:$AB,$A29,claims!$AA:$AA,"Avoidable")+COUNTIFS(claims!$Z:$Z,"ED",claims!$AB:$AB,$A29,claims!$AA:$AA,"Potentially Avoidable"))/B29 -> 0.734375 | F29: =SUMIFS(claims!$Q:$Q,claims!$Z:$Z,"ED",claims!$AB:$AB,$A29) -> 288469.1
A30: Total | B30: =SUM(B26:B29) -> 1209 | C30: =SUM(C26:C29) -> 8462 | D30: =B30/C30*1000 -> 142.87403 | E30: =(COUNTIFS(claims!$Z:$Z,"ED",claims!$AA:$AA,"Avoidable")+COUNTIFS(claims!$Z:$Z,"ED",claims!$AA:$AA,"Potentially Avoidable"))/B30 -> 0.75599669 | F30: =SUM(F26:F29) -> 1362281.7
A32: AVOIDABLE ED BY ATTRIBUTED-PCP QUALITY TIER
A33: PCP Quality Tier | B33: ED Visits | C33: Avoidable+PA | D33: Avoidable % | E33: ED Allowed
A34: High-quality PCP (score >= 4.0) | B34: =COUNTIFS(claims!$Z:$Z,"ED",claims!$AF:$AF,">=4") -> 449 | C34: =COUNTIFS(claims!$Z:$Z,"ED",claims!$AF:$AF,">=4",claims!$AA:$AA,"Avoidable")+COUNTIFS(claims!$Z:$Z,"ED",claims!$AF:$AF,">=4",claims!$AA:$AA,"Potentially Avoidable") -> 328 | D34: =IF(B34=0,0,C34/B34) -> 0.73051225 | E34: =SUMIFS(claims!$Q:$Q,claims!$Z:$Z,"ED",claims!$AF:$AF,">=4") -> 506161.74
A35: Lower-quality PCP (score < 4.0) | B35: =COUNTIFS(claims!$Z:$Z,"ED",claims!$AF:$AF,"<4") -> 724 | C35: =COUNTIFS(claims!$Z:$Z,"ED",claims!$AF:$AF,"<4",claims!$AA:$AA,"Avoidable")+COUNTIFS(claims!$Z:$Z,"ED",claims!$AF:$AF,"<4",claims!$AA:$AA,"Potentially Avoidable") -> 561 | D35: =IF(B35=0,0,C35/B35) -> 0.77486188 | E35: =SUMIFS(claims!$Q:$Q,claims!$Z:$Z,"ED",claims!$AF:$AF,"<4") -> 814924.92
A37: FINDINGS & RECOMMENDED INTERVENTIONS
A38: • 914 of 1,209 ED visits (75.6%) are Avoidable or Potentially Avoidable; Avoidable alone = $694K allowed (51% of ED spend).
A39: • Diverting 20% of avoidable/PA ED to urgent care saves ~$181K/yr (ED $1,127 vs UC $135 per visit) — see Category Spend, Scenario B.
A40: • Members attributed to lower-quality PCPs (<4.0) have higher avoidable-ED rate (77.5% vs 73.1%). Action: grow panels at 4.0+ PCPs, close attribution gaps.
A41: • 65+ cohort drives the most ED volume (482 visits). Action: MA telehealth triage, post-discharge follow-up, care-management outreach.
A42: • KY shows the highest avoidable-ED share (72.5%). Action: targeted ED-diversion campaign + urgent care access in KY counties.
A43: • Monitoring KPIs: ED/1,000, Avoidable ED/1,000, PCP visit within 7 days of ED, 30-day readmission rate, urgent-care share of low-acuity visits.

Sheet Behavioral Health
A1: BEHAVIORAL HEALTH — VOLUME vs UNIT COST
A3: BH allowed (annual) | B3: =SUMIFS(claims!$Q:$Q,claims!$Z:$Z,"Behavioral Health") -> 84220.61
A4: BH claim volume | B4: =COUNTIFS(claims!$Z:$Z,"Behavioral Health") -> 480
A5: Avg allowed / BH claim (unit cost) | B5: =IF(B4=0,0,B3/B4) -> 175.4596
A6: BH members (≥1 BH claim) | B6: =SUM('Member Spend'!$AD$2:$AD$801) -> 363
A7: BH claims per BH member | B7: =IF(B6=0,0,B4/B6) -> 1.322314
A8: BH penetration (% of members w/ BH claim) | B8: =B6/COUNTA('Member Spend'!$A$2:$A$801) -> 0.45375
A9: BH as % of total allowed | B9: =B3/'Member Spend'!$U$6 -> 0.0074391606
A10: BH PMPM | B10: =B3/'Member Spend'!$U$10 -> 9.9528019
A12: Unit-cost benchmark — avg allowed / claim by setting
A13: Behavioral Health | B13: ='Category Spend'!$E$8 -> 175.4596
A14: PCP | B14: ='Category Spend'!$E$6 -> 149.73199
A15: ED | B15: ='Category Spend'!$E$4 -> 1126.7839
A16: Inpatient | B16: ='Category Spend'!$E$3 -> 16348.141
A18: BH COHORT vs NON-BH COHORT — ED & INPATIENT PATTERNS
A19: Metric | B19: BH members | C19: Non-BH members | D19: Difference
A20: Members | B20: =B6 -> 363 | C20: =COUNTA('Member Spend'!$A$2:$A$801)-B6 -> 437
A21: Avg ED visits / member | B21: =AVERAGEIFS('Member Spend'!$AB$2:$AB$801,'Member Spend'!$AD$2:$AD$801,1) -> 1.8347107 | C21: =AVERAGEIFS('Member Spend'!$AB$2:$AB$801,'Member Spend'!$AD$2:$AD$801,0) -> 1.2425629 | D21: =B21-C21 -> 0.59214781
A22: Avg IP stays / member | B22: =AVERAGEIFS('Member Spend'!$AC$2:$AC$801,'Member Spend'!$AD$2:$AD$801,1) -> 0.66115702 | C22: =AVERAGEIFS('Member Spend'!$AC$2:$AC$801,'Member Spend'!$AD$2:$AD$801,0) -> 0.6590389 | D22: =B22-C22 -> 0.0021181232
A23: Avg total allowed / member | B23: =AVERAGEIFS('Member Spend'!$L$2:$L$801,'Member Spend'!$AD$2:$AD$801,1) -> 14953.037 | C23: =AVERAGEIFS('Member Spend'!$L$2:$L$801,'Member Spend'!$AD$2:$AD$801,0) -> 13485.811 | D23: =B23-C23 -> 1467.2257
A24: Avg PMPM | B24: =AVERAGEIFS('Member Spend'!$M$2:$M$801,'Member Spend'!$AD$2:$AD$801,1) -> 1419.0208 | C24: =AVERAGEIFS('Member Spend'!$M$2:$M$801,'Member Spend'!$AD$2:$AD$801,0) -> 1304.574 | D24: =B24-C24 -> 114.44682
A25: % with ≥1 ED visit | B25: =COUNTIFS('Member Spend'!$AD$2:$AD$801,1,'Member Spend'!$AB$2:$AB$801,">=1")/B20 -> 0.75482094 | C25: =COUNTIFS('Member Spend'!$AD$2:$AD$801,0,'Member Spend'!$AB$2:$AB$801,">=1")/C20 -> 0.65446224 | D25: =B25-C25 -> 0.10035869
A26: % with ≥1 IP stay | B26: =COUNTIFS('Member Spend'!$AD$2:$AD$801,1,'Member Spend'!$AC$2:$AC$801,">=1")/B20 -> 0.46831956 | C26: =COUNTIFS('Member Spend'!$AD$2:$AD$801,0,'Member Spend'!$AC$2:$AC$801,">=1")/C20 -> 0.46681922 | D26: =B26-C26 -> 0.0015003373
A28: FINDINGS & INTERVENTIONS
A29: • Low BH spend is a low-intensity story, not low unit cost: $175/BH claim (~PCP level) with 45% member penetration, but only 1.3 claims per BH member — points to an engagement / follow-up gap, not cheap pricing or lack of need.
A30: • BH members average 1.83 ED visits vs 1.24 for non-BH (+48%); 75.5% had ≥1 ED visit vs 65.4%. Inpatient rates are identical (~0.66), so the BH signal concentrates in ED, not IP.
A31: • BH members carry ~$114 higher PMPM. Intervention: collaborative-care / measurement-based BH, telehealth BH access, and ED-to-BH warm handoffs to convert one-off BH touches into sustained treatment and divert avoidable ED.
A32: • KPIs: BH follow-up within 7/30 days of an ED visit with BH diagnosis; BH claims per engaged member; % BH members with ≥2 visits.

Sheet OON & Retention
A1: OUT-OF-NETWORK (OON) LEAKAGE
A3: OON claim lines | B3: =COUNTIFS(claims!$T:$T,"N") -> 55
A4: Total claim lines | B4: =COUNTA(claims!$A$2:$A$100000) -> 5961
A5: OON % of claim lines | B5: =B3/B4 -> 0.0092266398
A6: OON allowed | B6: =SUMIFS(claims!$Q:$Q,claims!$T:$T,"N") -> 138734.48
A7: Total allowed | B7: ='Member Spend'!$U$6 -> 11321252
A8: OON leakage rate (% of allowed) | B8: =B6/B7 -> 0.012254341
A9: Avg allowed / OON claim | B9: =IF(B3=0,0,B6/B3) -> 2522.4451
A10: Avg allowed / in-network claim | B10: =SUMIFS(claims!$Q:$Q,claims!$T:$T,"Y")/COUNTIFS(claims!$T:$T,"Y") -> 1893.4164
A11: OON vs in-network cost premium | B11: =IF(B10=0,0,B9/B10-1) -> 0.33221888
A13: OON BY SERVICE CATEGORY
A14: Category | B14: OON claims | C14: OON allowed | D14: % of category allowed OON
A15: Inpatient | B15: =COUNTIFS(claims!$Z:$Z,$A15,claims!$T:$T,"N") -> 8 | C15: =SUMIFS(claims!$Q:$Q,claims!$Z:$Z,$A15,claims!$T:$T,"N") -> 131655.63 | D15: =IFERROR(C15/SUMIFS(claims!$Q:$Q,claims!$Z:$Z,$A15),0) -> 0.015252364
A16: ED | B16: =COUNTIFS(claims!$Z:$Z,$A16,claims!$T:$T,"N") -> 0 | C16: =SUMIFS(claims!$Q:$Q,claims!$Z:$Z,$A16,claims!$T:$T,"N") -> 0 | D16: =IFERROR(C16/SUMIFS(claims!$Q:$Q,claims!$Z:$Z,$A16),0) -> 0
A17: Specialty Rx | B17: =COUNTIFS(claims!$Z:$Z,$A17,claims!$T:$T,"N") -> 0 | C17: =SUMIFS(claims!$Q:$Q,claims!$Z:$Z,$A17,claims!$T:$T,"N") -> 0 | D17: =IFERROR(C17/SUMIFS(claims!$Q:$Q,claims!$Z:$Z,$A17),0) -> 0
A18: PCP | B18: =COUNTIFS(claims!$Z:$Z,$A18,claims!$T:$T,"N") -> 47 | C18: =SUMIFS(claims!$Q:$Q,claims!$Z:$Z,$A18,claims!$T:$T,"N") -> 7078.85 | D18: =IFERROR(C18/SUMIFS(claims!$Q:$Q,claims!$Z:$Z,$A18),0) -> 0.019805951
A19: Urgent Care | B19: =COUNTIFS(claims!$Z:$Z,$A19,claims!$T:$T,"N") -> 0 | C19: =SUMIFS(claims!$Q:$Q,claims!$Z:$Z,$A19,claims!$T:$T,"N") -> 0 | D19: =IFERROR(C19/SUMIFS(claims!$Q:$Q,claims!$Z:$Z,$A19),0) -> 0
A20: Behavioral Health | B20: =COUNTIFS(claims!$Z:$Z,$A20,claims!$T:$T,"N") -> 0 | C20: =SUMIFS(claims!$Q:$Q,claims!$Z:$Z,$A20,claims!$T:$T,"N") -> 0 | D20: =IFERROR(C20/SUMIFS(claims!$Q:$Q,claims!$Z:$Z,$A20),0) -> 0
A22: MEMBER RETENTION & DISENROLLMENT
A24: Total members | B24: =COUNTA('Member Spend'!$A$2:$A$801) -> 800
A25: Disenrolled members | B25: =SUM('Member Spend'!$AF$2:$AF$801) -> 93
A26: Disenrollment rate | B26: =B25/B24 -> 0.11625
A27: Avg PMPM — disenrolled | B27: =AVERAGEIFS('Member Spend'!$M$2:$M$801,'Member Spend'!$AF$2:$AF$801,1) -> 1769.8979
A28: Avg PMPM — retained | B28: =AVERAGEIFS('Member Spend'!$M$2:$M$801,'Member Spend'!$AF$2:$AF$801,0) -> 1302.1257
A29: Avg risk score — disenrolled | B29: =AVERAGEIFS('Member Spend'!$H$2:$H$801,'Member Spend'!$AF$2:$AF$801,1) -> 1.7132258
A30: Avg risk score — retained | B30: =AVERAGEIFS('Member Spend'!$H$2:$H$801,'Member Spend'!$AF$2:$AF$801,0) -> 1.8643564
A32: DISENROLLMENT BY REASON
A33: Reason | B33: Members | C33: % of disenrolled | D33: Avg PMPM | E33: Avg PCP quality
A34: Premium Affordability | B34: =COUNTIFS('Member Spend'!$AE$2:$AE$801,$A34) -> 26 | C34: =IFERROR(B34/$B$25,0) -> 0.27956989 | D34: =IFERROR(AVERAGEIFS('Member Spend'!$M$2:$M$801,'Member Spend'!$AE$2:$AE$801,$A34),0) -> 2684.7197 | E34: =IFERROR(AVERAGEIFS('Member Spend'!$J$2:$J$801,'Member Spend'!$AE$2:$AE$801,$A34),0) -> 4.0230769
A35: Network Adequacy | B35: =COUNTIFS('Member Spend'!$AE$2:$AE$801,$A35) -> 25 | C35: =IFERROR(B35/$B$25,0) -> 0.2688172 | D35: =IFERROR(AVERAGEIFS('Member Spend'!$M$2:$M$801,'Member Spend'!$AE$2:$AE$801,$A35),0) -> 1155.5417 | E35: =IFERROR(AVERAGEIFS('Member Spend'!$J$2:$J$801,'Member Spend'!$AE$2:$AE$801,$A35),0) -> 3.8409091
A36: Access Issues | B36: =COUNTIFS('Member Spend'!$AE$2:$AE$801,$A36) -> 15 | C36: =IFERROR(B36/$B$25,0) -> 0.16129032 | D36: =IFERROR(AVERAGEIFS('Member Spend'!$M$2:$M$801,'Member Spend'!$AE$2:$AE$801,$A36),0) -> 2458.8282 | E36: =IFERROR(AVERAGEIFS('Member Spend'!$J$2:$J$801,'Member Spend'!$AE$2:$AE$801,$A36),0) -> 3.9266667
A37: Employer Change | B37: =COUNTIFS('Member Spend'!$AE$2:$AE$801,$A37) -> 14 | C37: =IFERROR(B37/$B$25,0) -> 0.15053763 | D37: =IFERROR(AVERAGEIFS('Member Spend'!$M$2:$M$801,'Member Spend'!$AE$2:$AE$801,$A37),0) -> 1174.2244 | E37: =IFERROR(AVERAGEIFS('Member Spend'!$J$2:$J$801,'Member Spend'!$AE$2:$AE$801,$A37),0) -> 3.8714286
A38: Moved Out of Area | B38: =COUNTIFS('Member Spend'!$AE$2:$AE$801,$A38) -> 13 | C38: =IFERROR(B38/$B$25,0) -> 0.13978495 | D38: =IFERROR(AVERAGEIFS('Member Spend'!$M$2:$M$801,'Member Spend'!$AE$2:$AE$801,$A38),0) -> 968.28353 | E38: =IFERROR(AVERAGEIFS('Member Spend'!$J$2:$J$801,'Member Spend'!$AE$2:$AE$801,$A38),0) -> 4.0615385
A40: DISENROLLMENT RATE BY LOB
A41: LOB | B41: Members | C41: Disenrolled | D41: Rate | E41: Avg PMPM (disenrolled)
A42: Commercial | B42: =COUNTIFS('Member Spend'!$B$2:$B$801,$A42) -> 349 | C42: =COUNTIFS('Member Spend'!$B$2:$B$801,$A42,'Member Spend'!$AF$2:$AF$801,1) -> 28 | D42: =IFERROR(C42/B42,0) -> 0.080229226 | E42: =IFERROR(AVERAGEIFS('Member Spend'!$M$2:$M$801,'Member Spend'!$B$2:$B$801,$A42,'Member Spend'!$AF$2:$AF$801,1),0) -> 1445.2653
A43: Marketplace | B43: =COUNTIFS('Member Spend'!$B$2:$B$801,$A43) -> 299 | C43: =COUNTIFS('Member Spend'!$B$2:$B$801,$A43,'Member Spend'!$AF$2:$AF$801,1) -> 54 | D43: =IFERROR(C43/B43,0) -> 0.18060201 | E43: =IFERROR(AVERAGEIFS('Member Spend'!$M$2:$M$801,'Member Spend'!$B$2:$B$801,$A43,'Member Spend'!$AF$2:$AF$801,1),0) -> 1615.7739
A44: Medicare Advantage | B44: =COUNTIFS('Member Spend'!$B$2:$B$801,$A44) -> 152 | C44: =COUNTIFS('Member Spend'!$B$2:$B$801,$A44,'Member Spend'!$AF$2:$AF$801,1) -> 11 | D44: =IFERROR(C44/B44,0) -> 0.072368421 | E44: =IFERROR(AVERAGEIFS('Member Spend'!$M$2:$M$801,'Member Spend'!$B$2:$B$801,$A44,'Member Spend'!$AF$2:$AF$801,1),0) -> 3352.8442
A47: PCP QUALITY SCORE vs PMPM
A48: Tier | B48: Members | C48: Avg PMPM | D48: Avg risk score | E48: Avg quality score
A49: High (≥4.0) | B49: =COUNTIFS('Member Spend'!$J$2:$J$801,">=4") -> 402 | C49: =AVERAGEIFS('Member Spend'!$M$2:$M$801,'Member Spend'!$J$2:$J$801,">=4") -> 1380.2514 | D49: =AVERAGEIFS('Member Spend'!$H$2:$H$801,'Member Spend'!$J$2:$J$801,">=4") -> 1.8371891 | E49: =AVERAGEIFS('Member Spend'!$J$2:$J$801,'Member Spend'!$J$2:$J$801,">=4") -> 4.1465174
A50: Lower (<4.0) | B50: =COUNTIFS('Member Spend'!$J$2:$J$801,"<4") -> 391 | C50: =AVERAGEIFS('Member Spend'!$M$2:$M$801,'Member Spend'!$J$2:$J$801,"<4") -> 1343.6389 | D50: =AVERAGEIFS('Member Spend'!$H$2:$H$801,'Member Spend'!$J$2:$J$801,"<4") -> 1.85711 | E50: =AVERAGEIFS('Member Spend'!$J$2:$J$801,'Member Spend'!$J$2:$J$801,"<4") -> 3.7217391
A52: PMPM BY PCP QUALITY TIER WITHIN LOB (confounding check)
A53: LOB | B53: High-quality PMPM | C53: Lower-quality PMPM | D53: Members High | E53: Members Low
A54: Commercial | B54: =IFERROR(AVERAGEIFS('Member Spend'!$M$2:$M$801,'Member Spend'!$B$2:$B$801,$A54,'Member Spend'!$J$2:$J$801,">=4"),0) -> 1203.79 | C54: =IFERROR(AVERAGEIFS('Member Spend'!$M$2:$M$801,'Member Spend'!$B$2:$B$801,$A54,'Member Spend'!$J$2:$J$801,"<4"),0) -> 1191.5165 | D54: =COUNTIFS('Member Spend'!$B$2:$B$801,$A54,'Member Spend'!$J$2:$J$801,">=4") -> 163 | E54: =COUNTIFS('Member Spend'!$B$2:$B$801,$A54,'Member Spend'!$J$2:$J$801,"<4") -> 186
A55: Marketplace | B55: =IFERROR(AVERAGEIFS('Member Spend'!$M$2:$M$801,'Member Spend'!$B$2:$B$801,$A55,'Member Spend'!$J$2:$J$801,">=4"),0) -> 1317.6032 | C55: =IFERROR(AVERAGEIFS('Member Spend'!$M$2:$M$801,'Member Spend'!$B$2:$B$801,$A55,'Member Spend'!$J$2:$J$801,"<4"),0) -> 1533.2679 | D55: =COUNTIFS('Member Spend'!$B$2:$B$801,$A55,'Member Spend'!$J$2:$J$801,">=4") -> 157 | E55: =COUNTIFS('Member Spend'!$B$2:$B$801,$A55,'Member Spend'!$J$2:$J$801,"<4") -> 135
A56: Medicare Advantage | B56: =IFERROR(AVERAGEIFS('Member Spend'!$M$2:$M$801,'Member Spend'!$B$2:$B$801,$A56,'Member Spend'!$J$2:$J$801,">=4"),0) -> 1850.9707 | C56: =IFERROR(AVERAGEIFS('Member Spend'!$M$2:$M$801,'Member Spend'!$B$2:$B$801,$A56,'Member Spend'!$J$2:$J$801,"<4"),0) -> 1382.1366 | D56: =COUNTIFS('Member Spend'!$B$2:$B$801,$A56,'Member Spend'!$J$2:$J$801,">=4") -> 82 | E56: =COUNTIFS('Member Spend'!$B$2:$B$801,$A56,'Member Spend'!$J$2:$J$801,"<4") -> 70
A58: FINDINGS & INTERVENTIONS
A59: • OON leakage is small overall (1.2% of allowed, $139K) but concentrated: ~95% of OON dollars are inpatient (8 stays, $132K), and OON claims run ~33% above in-network unit cost — balance-billing and steerage risk. Target network contracting / steerage at OON inpatient & orthopedic facilities.
A60: • Disenrollment is 11.6% (93/800). Leavers had 36% higher PMPM ($1,770 vs $1,302) at similar/lower risk (1.71 vs 1.86) — cost exposure, not acuity, drives exits. Premium Affordability (28% of exits, PMPM $2,685) and Network Adequacy + Access Issues (~43% combined) are the top drivers.
A61: • Retention levers: proactive cost transparency & out-of-pocket estimators for high-PMPM members; rural network-adequacy build-out (drive-time standards); digital in-network provider finder.
A62: • PCP-quality hypothesis NOT supported: PMPM is essentially flat across attributed-PCP quality tiers ($1,380 high vs $1,344 low) at equal risk, and the gap stays negligible within every LOB — so the small raw difference is not a hidden LOB/geography confound. No evidence that low-quality PCP attribution drives higher cost in this dataset.
A63: • KPIs: disenrollment rate by LOB, OON inpatient rate, cost-estimator adoption, rural network adequacy (% members meeting drive-time standard).

Sheet Dashboard
A1: SummitBridge Health Plan — Medical Cost & Utilization Dashboard (FY2024) | P1: Category | Q1: Allowed | S1: Month | T1: Allowed | U1: Member Months | V1: PMPM | W1: ED Visits | X1: ED / 1,000
A2: Cost metric: allowed amount · Exposure: 8,462 member-months · 800 members · All figures formula-linked to source tabs | P2: ='Category Spend'!A3 -> Inpatient | Q2: ='Category Spend'!C3 -> 8631818.3 | S2: =DATE(2024,1,1) -> 45292 | T2: =SUMIFS(claims!$Q:$Q,claims!$AG:$AG,$S2) -> 849978.77 | U2: =SUMIFS(member_months!$F:$F,member_months!$E:$E,$S2) -> 258 | V2: =IFERROR(T2/U2,0) -> 3294.4914 | W2: =COUNTIFS(claims!$Z:$Z,"ED",claims!$AG:$AG,$S2) -> 109 | X2: =IFERROR(W2/U2*1000,0) -> 422.48062
P3: ='Category Spend'!A4 -> ED | Q3: ='Category Spend'!C4 -> 1362281.7 | S3: =EDATE(S2,1) -> 45323 | T3: =SUMIFS(claims!$Q:$Q,claims!$AG:$AG,$S3) -> 846649.49 | U3: =SUMIFS(member_months!$F:$F,member_months!$E:$E,$S3) -> 520 | V3: =IFERROR(T3/U3,0) -> 1628.1721 | W3: =COUNTIFS(claims!$Z:$Z,"ED",claims!$AG:$AG,$S3) -> 93 | X3: =IFERROR(W3/U3*1000,0) -> 178.84615
B4: Blended PMPM (Allowed) | D4: High-Cost Concentration (Top 5%) | F4: ED Visits / 1,000 | P4: ='Category Spend'!A5 -> Specialty Rx | Q4: ='Category Spend'!C5 -> 791233.42 | S4: =EDATE(S3,1) -> 45352 | T4: =SUMIFS(claims!$Q:$Q,claims!$AG:$AG,$S4) -> 1021721.6 | U4: =SUMIFS(member_months!$F:$F,member_months!$E:$E,$S4) -> 800 | V4: =IFERROR(T4/U4,0) -> 1277.1519 | W4: =COUNTIFS(claims!$Z:$Z,"ED",claims!$AG:$AG,$S4) -> 109 | X4: =IFERROR(W4/U4*1000,0) -> 136.25
B5: ='Member Spend'!$U$11 -> 1337.8931 | D5: ='Member Spend'!$U$7 -> 0.20468617 | F5: =COUNTIFS(claims!$Z:$Z,"ED")/'Member Spend'!$U$10*1000 -> 142.87403 | P5: ='Category Spend'!A6 -> PCP | Q5: ='Category Spend'!C6 -> 357410.25 | S5: =EDATE(S4,1) -> 45383 | T5: =SUMIFS(claims!$Q:$Q,claims!$AG:$AG,$S5) -> 817218.1 | U5: =SUMIFS(member_months!$F:$F,member_months!$E:$E,$S5) -> 800 | V5: =IFERROR(T5/U5,0) -> 1021.5226 | W5: =COUNTIFS(claims!$Z:$Z,"ED",claims!$AG:$AG,$S5) -> 82 | X5: =IFERROR(W5/U5*1000,0) -> 102.5
P6: ='Category Spend'!A7 -> Urgent Care | Q6: ='Category Spend'!C7 -> 94287.55 | S6: =EDATE(S5,1) -> 45413 | T6: =SUMIFS(claims!$Q:$Q,claims!$AG:$AG,$S6) -> 900677.21 | U6: =SUMIFS(member_months!$F:$F,member_months!$E:$E,$S6) -> 800 | V6: =IFERROR(T6/U6,0) -> 1125.8465 | W6: =COUNTIFS(claims!$Z:$Z,"ED",claims!$AG:$AG,$S6) -> 101 | X6: =IFERROR(W6/U6*1000,0) -> 126.25
B7: Avoidable ED / 1,000 | D7: Inpatient Stays / 1,000 | F7: OON Leakage (% Allowed) | P7: ='Category Spend'!A8 -> Behavioral Health | Q7: ='Category Spend'!C8 -> 84220.61 | S7: =EDATE(S6,1) -> 45444 | T7: =SUMIFS(claims!$Q:$Q,claims!$AG:$AG,$S7) -> 808683.3 | U7: =SUMIFS(member_months!$F:$F,member_months!$E:$E,$S7) -> 796 | V7: =IFERROR(T7/U7,0) -> 1015.9338 | W7: =COUNTIFS(claims!$Z:$Z,"ED",claims!$AG:$AG,$S7) -> 99 | X7: =IFERROR(W7/U7*1000,0) -> 124.37186
B8: =(COUNTIFS(claims!$Z:$Z,"ED",claims!$AA:$AA,"Avoidable")+COUNTIFS(claims!$Z:$Z,"ED",claims!$AA:$AA,"Potentially Avoidable"))/'Member Spend'!$U$10*1000 -> 108.01229 | D8: =COUNTIFS(claims!$Z:$Z,"Inpatient")/'Member Spend'!$U$10*1000 -> 62.396597 | F8: =SUMIFS(claims!$Q:$Q,claims!$T:$T,"N")/'Member Spend'!$U$6 -> 0.012254341 | S8: =EDATE(S7,1) -> 45474 | T8: =SUMIFS(claims!$Q:$Q,claims!$AG:$AG,$S8) -> 881627.95 | U8: =SUMIFS(member_months!$F:$F,member_months!$E:$E,$S8) -> 784 | V8: =IFERROR(T8/U8,0) -> 1124.5254 | W8: =COUNTIFS(claims!$Z:$Z,"ED",claims!$AG:$AG,$S8) -> 112 | X8: =IFERROR(W8/U8*1000,0) -> 142.85714
P9: ED Avoidability | Q9: Visits | S9: =EDATE(S8,1) -> 45505 | T9: =SUMIFS(claims!$Q:$Q,claims!$AG:$AG,$S9) -> 935327.17 | U9: =SUMIFS(member_months!$F:$F,member_months!$E:$E,$S9) -> 766 | V9: =IFERROR(T9/U9,0) -> 1221.0537 | W9: =COUNTIFS(claims!$Z:$Z,"ED",claims!$AG:$AG,$S9) -> 97 | X9: =IFERROR(W9/U9*1000,0) -> 126.63185
P10: ='Avoidable ED'!A3 -> Avoidable | Q10: ='Avoidable ED'!B3 -> 613 | S10: =EDATE(S9,1) -> 45536 | T10: =SUMIFS(claims!$Q:$Q,claims!$AG:$AG,$S10) -> 1077625.7 | U10: =SUMIFS(member_months!$F:$F,member_months!$E:$E,$S10) -> 750 | V10: =IFERROR(T10/U10,0) -> 1436.8343 | W10: =COUNTIFS(claims!$Z:$Z,"ED",claims!$AG:$AG,$S10) -> 93 | X10: =IFERROR(W10/U10*1000,0) -> 124
A11: KPI TRACKER — DEFINITION, CADENCE & OWNERSHIP | P11: ='Avoidable ED'!A4 -> Potentially Avoidable | Q11: ='Avoidable ED'!B4 -> 301 | S11: =EDATE(S10,1) -> 45566 | T11: =SUMIFS(claims!$Q:$Q,claims!$AG:$AG,$S11) -> 1016722 | U11: =SUMIFS(member_months!$F:$F,member_months!$E:$E,$S11) -> 743 | V11: =IFERROR(T11/U11,0) -> 1368.4011 | W11: =COUNTIFS(claims!$Z:$Z,"ED",claims!$AG:$AG,$S11) -> 107 | X11: =IFERROR(W11/U11*1000,0) -> 144.01077
A12: KPI | B12: FY2024 | C12: Definition | E12: Refresh | F12: Owner | P12: ='Avoidable ED'!A5 -> Non-Avoidable | Q12: ='Avoidable ED'!B5 -> 295 | S12: =EDATE(S11,1) -> 45597 | T12: =SUMIFS(claims!$Q:$Q,claims!$AG:$AG,$S12) -> 1053103.9 | U12: =SUMIFS(member_months!$F:$F,member_months!$E:$E,$S12) -> 731 | V12: =IFERROR(T12/U12,0) -> 1440.6345 | W12: =COUNTIFS(claims!$Z:$Z,"ED",claims!$AG:$AG,$S12) -> 107 | X12: =IFERROR(W12/U12*1000,0) -> 146.37483
A13: PMPM (Allowed) | B13: =B5 -> 1337.8931 | C13: Total allowed ÷ member months | E13: Monthly | F13: Actuarial / Finance | S13: =EDATE(S12,1) -> 45627 | T13: =SUMIFS(claims!$Q:$Q,claims!$AG:$AG,$S13) -> 1111916.7 | U13: =SUMIFS(member_months!$F:$F,member_months!$E:$E,$S13) -> 714 | V13: =IFERROR(T13/U13,0) -> 1557.3063 | W13: =COUNTIFS(claims!$Z:$Z,"ED",claims!$AG:$AG,$S13) -> 100 | X13: =IFERROR(W13/U13*1000,0) -> 140.05602
A14: High-cost concentration | B14: =D5 -> 0.20468617 | C14: Top 5% members' share of allowed | E14: Quarterly | F14: Care Management | P14: LOB | Q14: PMPM
A15: ED visits / 1,000 | B15: =F5 -> 142.87403 | C15: (ED claims ÷ MM) × 1,000 | E15: Monthly | F15: Population Health | P15: ='Member Spend'!S15 -> Commercial | Q15: ='Member Spend'!W15 -> 1200.1462
A16: Avoidable ED / 1,000 | B16: =B8 -> 108.01229 | C16: (Avoidable+Potentially Avoidable ED ÷ MM) × 1,000 | E16: Monthly | F16: Population Health | P16: ='Member Spend'!S16 -> Marketplace | Q16: ='Member Spend'!W16 -> 1369.8191
A17: Inpatient stays / 1,000 | B17: =D8 -> 62.396597 | C17: (Inpatient claims ÷ MM) × 1,000 | E17: Monthly | F17: Utilization Mgmt | P17: ='Member Spend'!S17 -> Medicare Advantage | Q17: ='Member Spend'!W17 -> 1591.1668
A18: OON leakage rate | B18: =F8 -> 0.012254341 | C18: OON allowed ÷ total allowed | E18: Quarterly | F18: Network Mgmt
A19: Specialty Rx PMPM | B19: ='Category Spend'!$C$5/'Member Spend'!$U$10 -> 93.504304 | C19: Specialty Rx allowed ÷ member months | E19: Monthly | F19: Pharmacy | P19: Disenroll Reason | Q19: Members
A20: Disenrollment rate | B20: ='OON & Retention'!$B$26 -> 0.11625 | C20: Disenrolled members ÷ total members | E20: Quarterly | F20: Member Experience | P20: ='OON & Retention'!A34 -> Premium Affordability | Q20: ='OON & Retention'!B34 -> 26
A21: PCP visit within 7 days of ED | B21: track prospectively | C21: Requires ED→PCP visit sequencing (not in current extract) | E21: Monthly | F21: Care Coordination | P21: ='OON & Retention'!A35 -> Network Adequacy | Q21: ='OON & Retention'!B35 -> 25
A22: 30-day readmission rate | B22: track prospectively | C22: Requires admit/readmit linkage (not in current extract) | E22: Monthly | F22: Quality | P22: ='OON & Retention'!A36 -> Access Issues | Q22: ='OON & Retention'!B36 -> 15
P23: ='OON & Retention'!A37 -> Employer Change | Q23: ='OON & Retention'!B37 -> 14
P24: ='OON & Retention'!A38 -> Moved Out of Area | Q24: ='OON & Retention'!B38 -> 13
P26: Segment | Q26: Allowed
P27: Top 5% (High-cost) | Q27: ='Member Spend'!U5 -> 2317303.7
P28: Other 95% | Q28: ='Member Spend'!U6-'Member Spend'!U5 -> 9003948.1
A73: Monthly Trends (Mar–Dec 2024, full 800-member book — Jan–Feb excluded due to enrollment ramp / partial exposure)

Sheet Datasets >>
A1: Intentionally left blank

Sheet claims
A1: claim_id | B1: member_id | C1: rendering_npi | D1: billing_npi | E1: service_from_date | F1: service_to_date | G1: paid_date | H1: claim_type | I1: place_of_service_code | J1: diagnosis_code_1 | K1: procedure_code | L1: ndc_code | M1: drug_name | N1: therapeutic_class | O1: units | P1: billed_amount | Q1: allowed_amount | R1: paid_amount | S1: member_cost_share | T1: in_network_flag | U1: authorization_id | V1: admission_type | W1: discharge_status | X1: plan_id | Y1: lob | Z1: service_category | AA1: avoidable_category | AB1: member_state | AC1: member_age | AD1: age_band | AE1: attributed_pcp_npi | AF1: pcp_quality_score | AG1: service_month
A2: CLM-000001 | B2: M-000001 | C2: 9012345678 | D2: 9012345678 | E2: 45647 | F2: 45647 | G2: 45673 | H2: Professional | I2: 22 | J2: F32.9 | K2: 90837 | O2: 1 | P2: 268.29 | Q2: 198.73 | R2: 158.98 | S2: 39.75 | T2: Y | X2: PLN-COM-250 | Y2: Commercial | Z2: Behavioral Health | AA2: =IFERROR(_xlfn.XLOOKUP($J2,avoidable_ed_reference!$A$2:$A$13,avoidable_ed_reference!$C$2:$C$13),"Not Classified") -> Potentially Avoidable | AB2: =IFERROR(_xlfn.XLOOKUP($B2,enrollment!$A$2:$A$801,enrollment!$I$2:$I$801),"") -> KY | AC2: =IFERROR(_xlfn.XLOOKUP($B2,enrollment!$A$2:$A$801,enrollment!$L$2:$L$801),"") -> 53 | AD2: {=_xlfn.IFS(AC2="","Unknown",AC2<18,"0-17",AC2<35,"18-34",AC2<50,"35-49",AC2<65,"50-64",TRUE,"65+")} -> 50-64 | AE2: =IFERROR(_xlfn.XLOOKUP($B2,enrollment!$A$2:$A$801,enrollment!$O$2:$O$801),"") -> 9012345678 | AF2: =IFERROR(_xlfn.XLOOKUP($AE2,providers!$B$2:$B$11,providers!$Q$2:$Q$11),"") -> 4.3 | AG2: =EOMONTH(E2,-1)+1 -> 45627
A3: CLM-000002 | B3: M-000001 | C3: 5678901234 | D3: 5678901234 | E3: 45539 | F3: 45539 | G3: 45572 | H3: Professional | I3: 20 | J3: J06.9 | K3: 99213 | O3: 1 | P3: 174.47 | Q3: 134.21 | R3: 107.37 | S3: 26.84 | T3: Y | X3: PLN-COM-250 | Y3: Commercial | Z3: Urgent Care | AA3: =IFERROR(_xlfn.XLOOKUP($J3,avoidable_ed_reference!$A$2:$A$13,avoidable_ed_reference!$C$2:$C$13),"Not Classified") -> Avoidable | AB3: =IFERROR(_xlfn.XLOOKUP($B3,enrollment!$A$2:$A$801,enrollment!$I$2:$I$801),"") -> KY | AC3: =IFERROR(_xlfn.XLOOKUP($B3,enrollment!$A$2:$A$801,enrollment!$L$2:$L$801),"") -> 53 | AD3: {=_xlfn.IFS(AC3="","Unknown",AC3<18,"0-17",AC3<35,"18-34",AC3<50,"35-49",AC3<65,"50-64",TRUE,"65+")} -> 50-64 | AE3: =IFERROR(_xlfn.XLOOKUP($B3,enrollment!$A$2:$A$801,enrollment!$O$2:$O$801),"") -> 9012345678 | AF3: =IFERROR(_xlfn.XLOOKUP($AE3,providers!$B$2:$B$11,providers!$Q$2:$Q$11),"") -> 4.3 | AG3: =EOMONTH(E3,-1)+1 -> 45536
A4: CLM-000003 | B4: M-000001 | C4: 9012345678 | D4: 9012345678 | E4: 45340 | F4: 45340 | G4: 45369 | H4: Professional | I4: 11 | J4: I10 | K4: 99213 | O4: 1 | P4: 204.65 | Q4: 151.59 | R4: 121.27 | S4: 30.32 | T4: Y | X4: PLN-COM-250 | Y4: Commercial | Z4: PCP | AA4: =IFERROR(_xlfn.XLOOKUP($J4,avoidable_ed_reference!$A$2:$A$13,avoidable_ed_reference!$C$2:$C$13),"Not Classified") -> Not Classified | AB4: =IFERROR(_xlfn.XLOOKUP($B4,enrollment!$A$2:$A$801,enrollment!$I$2:$I$801),"") -> KY | AC4: =IFERROR(_xlfn.XLOOKUP($B4,enrollment!$A$2:$A$801,enrollment!$L$2:$L$801),"") -> 53 | AD4: {=_xlfn.IFS(AC4="","Unknown",AC4<18,"0-17",AC4<35,"18-34",AC4<50,"35-49",AC4<65,"50-64",TRUE,"65+")} -> 50-64 | AE4: =IFERROR(_xlfn.XLOOKUP($B4,enrollment!$A$2:$A$801,enrollment!$O$2:$O$801),"") -> 9012345678 | AF4: =IFERROR(_xlfn.XLOOKUP($AE4,providers!$B$2:$B$11,providers!$Q$2:$Q$11),"") -> 4.3 | AG4: =EOMONTH(E4,-1)+1 -> 45323
A5: CLM-000004 | B5: M-000002 | C5: 9012345678 | D5: 9012345678 | E5: 45480 | F5: 45480 | G5: 45513 | H5: Professional | I5: 23 | J5: I50.9 | K5: 99284 | O5: 1 | P5: 2053.39 | Q5: 1140.77 | R5: 912.62 | S5: 228.15 | T5: Y | X5: PLN-MKT-401 | Y5: Marketplace | Z5: ED | AA5: =IFERROR(_xlfn.XLOOKUP($J5,avoidable_ed_reference!$A$2:$A$13,avoidable_ed_reference!$C$2:$C$13),"Not Classified") -> Non-Avoidable | AB5: =IFERROR(_xlfn.XLOOKUP($B5,enrollment!$A$2:$A$801,enrollment!$I$2:$I$801),"") -> KY | AC5: =IFERROR(_xlfn.XLOOKUP($B5,enrollment!$A$2:$A$801,enrollment!$L$2:$L$801),"") -> 36 | AD5: {=_xlfn.IFS(AC5="","Unknown",AC5<18,"0-17",AC5<35,"18-34",AC5<50,"35-49",AC5<65,"50-64",TRUE,"65+")} -> 35-49 | AE5: =IFERROR(_xlfn.XLOOKUP($B5,enrollment!$A$2:$A$801,enrollment!$O$2:$O$801),"") -> 9012345678 | AF5: =IFERROR(_xlfn.XLOOKUP($AE5,providers!$B$2:$B$11,providers!$Q$2:$Q$11),"") -> 4.3 | AG5: =EOMONTH(E5,-1)+1 -> 45474
A6: CLM-000005 | B6: M-000002 | C6: 9012345678 | D6: 9012345678 | E6: 45422 | F6: 45422 | G6: 45436 | H6: Professional | I6: 11 | J6: E11.9 | K6: 99213 | O6: 1 | P6: 189.28 | Q6: 140.21 | R6: 112.17 | S6: 28.04 | T6: Y | X6: PLN-MKT-401 | Y6: Marketplace | Z6: PCP | AA6: =IFERROR(_xlfn.XLOOKUP($J6,avoidable_ed_reference!$A$2:$A$13,avoidable_ed_reference!$C$2:$C$13),"Not Classified") -> Not Classified | AB6: =IFERROR(_xlfn.XLOOKUP($B6,enrollment!$A$2:$A$801,enrollment!$I$2:$I$801),"") -> KY | AC6: =IFERROR(_xlfn.XLOOKUP($B6,enrollment!$A$2:$A$801,enrollment!$L$2:$L$801),"") -> 36 | AD6: {=_xlfn.IFS(AC6="","Unknown",AC6<18,"0-17",AC6<35,"18-34",AC6<50,"35-49",AC6<65,"50-64",TRUE,"65+")} -> 35-49 | AE6: =IFERROR(_xlfn.XLOOKUP($B6,enrollment!$A$2:$A$801,enrollment!$O$2:$O$801),"") -> 9012345678 | AF6: =IFERROR(_xlfn.XLOOKUP($AE6,providers!$B$2:$B$11,providers!$Q$2:$Q$11),"") -> 4.3 | AG6: =EOMONTH(E6,-1)+1 -> 45413
A7: CLM-000006 | B7: M-000002 | C7: 9012345678 | D7: 9012345678 | E7: 45296 | F7: 45296 | G7: 45314 | H7: Professional | I7: 11 | J7: E11.9 | K7: 99213 | O7: 1 | P7: 238.91 | Q7: 176.97 | R7: 141.58 | S7: 35.39 | T7: Y | X7: PLN-MKT-401 | Y7: Marketplace | Z7: PCP | AA7: =IFERROR(_xlfn.XLOOKUP($J7,avoidable_ed_reference!$A$2:$A$13,avoidable_ed_reference!$C$2:$C$13),"Not Classified") -> Not Classified | AB7: =IFERROR(_xlfn.XLOOKUP($B7,enrollment!$A$2:$A$801,enrollment!$I$2:$I$801),"") -> KY | AC7: =IFERROR(_xlfn.XLOOKUP($B7,enrollment!$A$2:$A$801,enrollment!$L$2:$L$801),"") -> 36 | AD7: {=_xlfn.IFS(AC7="","Unknown",AC7<18,"0-17",AC7<35,"18-34",AC7<50,"35-49",AC7<65,"50-64",TRUE,"65+")} -> 35-49 | AE7: =IFERROR(_xlfn.XLOOKUP($B7,enrollment!$A$2:$A$801,enrollment!$O$2:$O$801),"") -> 9012345678 | AF7: =IFERROR(_xlfn.XLOOKUP($AE7,providers!$B$2:$B$11,providers!$Q$2:$Q$11),"") -> 4.3 | AG7: =EOMONTH(E7,-1)+1 -> 45292
A8: CLM-000007 | B8: M-000002 | C8: 8901234567 | D8: 8901234567 | E8: 45393 | F8: 45393 | G8: 45417 | H8: Professional | I8: 23 | J8: J06.9 | K8: 99284 | O8: 1 | P8: 2257.4 | Q8: 1254.11 | R8: 1003.29 | S8: 250.82 | T8: Y | X8: PLN-MKT-401 | Y8: Marketplace | Z8: ED | AA8: =IFERROR(_xlfn.XLOOKUP($J8,avoidable_ed_reference!$A$2:$A$13,avoidable_ed_reference!$C$2:$C$13),"Not Classified") -> Avoidable | AB8: =IFERROR(_xlfn.XLOOKUP($B8,enrollment!$A$2:$A$801,enrollment!$I$2:$I$801),"") -> KY | AC8: =IFERROR(_xlfn.XLOOKUP($B8,enrollment!$A$2:$A$801,enrollment!$L$2:$L$801),"") -> 36 | AD8: {=_xlfn.IFS(AC8="","Unknown",AC8<18,"0-17",AC8<35,"18-34",AC8<50,"35-49",AC8<65,"50-64",TRUE,"65+")} -> 35-49 | AE8: =IFERROR(_xlfn.XLOOKUP($B8,enrollment!$A$2:$A$801,enrollment!$O$2:$O$801),"") -> 9012345678 | AF8: =IFERROR(_xlfn.XLOOKUP($AE8,providers!$B$2:$B$11,providers!$Q$2:$Q$11),"") -> 4.3 | AG8: =EOMONTH(E8,-1)+1 -> 45383
A9: CLM-000008 | B9: M-000003 | C9: 8901234567 | D9: 8901234567 | E9: 45370 | F9: 45370 | G9: 45388 | H9: Professional | I9: 11 | J9: E11.9 | K9: 99213 | O9: 1 | P9: 227.66 | Q9: 168.64 | R9: 134.91 | S9: 33.73 | T9: Y | X9: PLN-MKT-400 | Y9: Marketplace | Z9: PCP | AA9: =IFERROR(_xlfn.XLOOKUP($J9,avoidable_ed_reference!$A$2:$A$13,avoidable_ed_reference!$C$2:$C$13),"Not Classified") -> Not Classified | AB9: =IFERROR(_xlfn.XLOOKUP($B9,enrollment!$A$2:$A$801,enrollment!$I$2:$I$801),"") -> GA | AC9: =IFERROR(_xlfn.XLOOKUP($B9,enrollment!$A$2:$A$801,enrollment!$L$2:$L$801),"") -> 24 | AD9: {=_xlfn.IFS(AC9="","Unknown",AC9<18,"0-17",AC9<35,"18-34",AC9<50,"35-49",AC9<65,"50-64",TRUE,"65+")} -> 18-34 | AE9: =IFERROR(_xlfn.XLOOKUP($B9,enrollment!$A$2:$A$801,enrollment!$O$2:$O$801),"") -> 8901234567 | AF9: =IFERROR(_xlfn.XLOOKUP($AE9,providers!$B$2:$B$11,providers!$Q$2:$Q$11),"") -> 3.7 | AG9: =EOMONTH(E9,-1)+1 -> 45352
A10: CLM-000009 | B10: M-000003 | C10: 8901234567 | D10: 8901234567 | E10: 45332 | F10: 45332 | G10: 45355 | H10: Professional | I10: 11 | J10: I10 | K10: 99213 | O10: 1 | P10: 162.01 | Q10: 120.01 | R10: 96.01 | S10: 24 | T10: Y | X10: PLN-MKT-400 | Y10: Marketplace | Z10: PCP | AA10: =IFERROR(_xlfn.XLOOKUP($J10,avoidable_ed_reference!$A$2:$A$13,avoidable_ed_reference!$C$2:$C$13),"Not Classified") -> Not Classified | AB10: =IFERROR(_xlfn.XLOOKUP($B10,enrollment!$A$2:$A$801,enrollment!$I$2:$I$801),"") -> GA | AC10: =IFERROR(_xlfn.XLOOKUP($B10,enrollment!$A$2:$A$801,enrollment!$L$2:$L$801),"") -> 24 | AD10: {=_xlfn.IFS(AC10="","Unknown",AC10<18,"0-17",AC10<35,"18-34",AC10<50,"35-49",AC10<65,"50-64",TRUE,"65+")} -> 18-34 | AE10: =IFERROR(_xlfn.XLOOKUP($B10,enrollment!$A$2:$A$801,enrollment!$O$2:$O$801),"") -> 8901234567 | AF10: =IFERROR(_xlfn.XLOOKUP($AE10,providers!$B$2:$B$11,providers!$Q$2:$Q$11),"") -> 3.7 | AG10: =EOMONTH(E10,-1)+1 -> 45323
A11: CLM-000010 | B11: M-000003 | C11: 2345678901 | D11: 2345678901 | E11: 45573 | F11: 45573 | G11: 45595 | H11: Professional | I11: 23 | J11: S09.90XA | K11: 99284 | O11: 1 | P11: 2435 | Q11: 1352.78 | R11: 1082.22 | S11: 270.56 | T11: Y | X11: PLN-MKT-400 | Y11: Marketplace | Z11: ED | AA11: =IFERROR(_xlfn.XLOOKUP($J11,avoidable_ed_reference!$A$2:$A$13,avoidable_ed_reference!$C$2:$C$13),"Not Classified") -> Potentially Avoidable | AB11: =IFERROR(_xlfn.XLOOKUP($B11,enrollment!$A$2:$A$801,enrollment!$I$2:$I$801),"") -> GA | AC11: =IFERROR(_xlfn.XLOOKUP($B11,enrollment!$A$2:$A$801,enrollment!$L$2:$L$801),"") -> 24 | AD11: {=_xlfn.IFS(AC11="","Unknown",AC11<18,"0-17",AC11<35,"18-34",AC11<50,"35-49",AC11<65,"50-64",TRUE,"65+")} -> 18-34 | AE11: =IFERROR(_xlfn.XLOOKUP($B11,enrollment!$A$2:$A$801,enrollment!$O$2:$O$801),"") -> 8901234567 | AF11: =IFERROR(_xlfn.XLOOKUP($AE11,providers!$B$2:$B$11,providers!$Q$2:$Q$11),"") -> 3.7 | AG11: =EOMONTH(E11,-1)+1 -> 45566
A12: CLM-000011 | B12: M-000003 | C12: 5678901234 | D12: 5678901234 | E12: 45361 | F12: 45361 | G12: 45385 | H12: Professional | I12: 20 | J12: J06.9 | K12: 99213 | O12: 1 | P12: 185.04 | Q12: 142.34 | R12: 113.87 | S12: 28.47 | T12: Y | X12: PLN-MKT-400 | Y12: Marketplace | Z12: Urgent Care | AA12: =IFERROR(_xlfn.XLOOKUP($J12,avoidable_ed_reference!$A$2:$A$13,avoidable_ed_reference!$C$2:$C$13),"Not Classified") -> Avoidable | AB12: =IFERROR(_xlfn.XLOOKUP($B12,enrollment!$A$2:$A$801,enrollment!$I$2:$I$801),"") -> GA | AC12: =IFERROR(_xlfn.XLOOKUP($B12,enrollment!$A$2:$A$801,enrollment!$L$2:$L$801),"") -> 24 | AD12: {=_xlfn.IFS(AC12="","Unknown",AC12<18,"0-17",AC12<35,"18-34",AC12<50,"35-49",AC12<65,"50-64",TRUE,"65+")} -> 18-34 | AE12: =IFERROR(_xlfn.XLOOKUP($B12,enrollment!$A$2:$A$801,enrollment!$O$2:$O$801),"") -> 8901234567 | AF12: =IFERROR(_xlfn.XLOOKUP($AE12,providers!$B$2:$B$11,providers!$Q$2:$Q$11),"") -> 3.7 | AG12: =EOMONTH(E12,-1)+1 -> 45352
A13: CLM-000012 | B13: M-000003 | C13: 6789012345 | D13: 6789012345 | E13: 45475 | F13: 45475 | G13: 45509 | H13: Professional | I13: 23 | J13: S09.90XA | K13: 99284 | O13: 1 | P13: 2393.91 | Q13: 1329.95 | R13: 1063.96 | S13: 265.99 | T13: Y | X13: PLN-MKT-400 | Y13: Marketplace | Z13: ED | AA13: =IFERROR(_xlfn.XLOOKUP($J13,avoidable_ed_reference!$A$2:$A$13,avoidable_ed_reference!$C$2:$C$13),"Not Classified") -> Potentially Avoidable | AB13: =IFERROR(_xlfn.XLOOKUP($B13,enrollment!$A$2:$A$801,enrollment!$I$2:$I$801),"") -> GA | AC13: =IFERROR(_xlfn.XLOOKUP($B13,enrollment!$A$2:$A$801,enrollment!$L$2:$L$801),"") -> 24 | AD13: {=_xlfn.IFS(AC13="","Unknown",AC13<18,"0-17",AC13<35,"18-34",AC13<50,"35-49",AC13<65,"50-64",TRUE,"65+")} -> 18-34 | AE13: =IFERROR(_xlfn.XLOOKUP($B13,enrollment!$A$2:$A$801,enrollment!$O$2:$O$801),"") -> 8901234567 | AF13: =IFERROR(_xlfn.XLOOKUP($AE13,providers!$B$2:$B$11,providers!$Q$2:$Q$11),"") -> 3.7 | AG13: =EOMONTH(E13,-1)+1 -> 45474
A14: CLM-000013 | B14: M-000003 | C14: 6789012345 | D14: 6789012345 | E14: 45638 | F14: 45638 | G14: 45662 | H14: Pharmacy | J14: Z79.4 | L14: 00078063941 | M14: Pembrolizumab | N14: Oncology Biologic | O14: 1 | P14: 1311.43 | Q14: 1192.21 | R14: 953.77 | S14: 238.44 | T14: Y | X14: PLN-MKT-400 | Y14: Marketplace | Z14: Specialty Rx | AA14: =IFERROR(_xlfn.XLOOKUP($J14,avoidable_ed_reference!$A$2:$A$13,avoidable_ed_reference!$C$2:$C$13),"Not Classified") -> Not Classified | AB14: =IFERROR(_xlfn.XLOOKUP($B14,enrollment!$A$2:$A$801,enrollment!$I$2:$I$801),"") -> GA | AC14: =IFERROR(_xlfn.XLOOKUP($B14,enrollment!$A$2:$A$801,enrollment!$L$2:$L$801),"") -> 24 | AD14: {=_xlfn.IFS(AC14="","Unknown",AC14<18,"0-17",AC14<35,"18-34",AC14<50,"35-49",AC14<65,"50-64",TRUE,"65+")} -> 18-34 | AE14: =IFERROR(_xlfn.XLOOKUP($B14,enrollment!$A$2:$A$801,enrollment!$O$2:$O$801),"") -> 8901234567 | AF14: =IFERROR(_xlfn.XLOOKUP($AE14,providers!$B$2:$B$11,providers!$Q$2:$Q$11),"") -> 3.7 | AG14: =EOMONTH(E14,-1)+1 -> 45627
A15: CLM-000014 | B15: M-000003 | C15: 2345678901 | D15: 2345678901 | E15: 45490 | F15: 45490 | G15: 45507 | H15: Professional | I15: 23 | J15: S09.90XA | K15: 99284 | O15: 1 | P15: 1597.46 | Q15: 887.48 | R15: 709.98 | S15: 177.5 | T15: Y | X15: PLN-MKT-400 | Y15: Marketplace | Z15: ED | AA15: =IFERROR(_xlfn.XLOOKUP($J15,avoidable_ed_reference!$A$2:$A$13,avoidable_ed_reference!$C$2:$C$13),"Not Classified") -> Potentially Avoidable | AB15: =IFERROR(_xlfn.XLOOKUP($B15,enrollment!$A$2:$A$801,enrollment!$I$2:$I$801),"") -> GA | AC15: =IFERROR(_xlfn.XLOOKUP($B15,enrollment!$A$2:$A$801,enrollment!$L$2:$L$801),"") -> 24 | AD15: {=_xlfn.IFS(AC15="","Unknown",AC15<18,"0-17",AC15<35,"18-34",AC15<50,"35-49",AC15<65,"50-64",TRUE,"65+")} -> 18-34 | AE15: =IFERROR(_xlfn.XLOOKUP($B15,enrollment!$A$2:$A$801,enrollment!$O$2:$O$801),"") -> 8901234567 | AF15: =IFERROR(_xlfn.XLOOKUP($AE15,providers!$B$2:$B$11,providers!$Q$2:$Q$11),"") -> 3.7 | AG15: =EOMONTH(E15,-1)+1 -> 45474
A16: CLM-000015 | B16: M-000003 | C16: 3456789012 | D16: 3456789012 | E16: 45646 | F16: 45646 | G16: 45673 | H16: Institutional | I16: 21 | J16: I50.9 | K16: 99223 | O16: 1 | P16: 27115 | Q16: 17493.55 | R16: 13994.84 | S16: 3498.71 | T16: Y | V16: 1 | W16: 01 | X16: PLN-MKT-400 | Y16: Marketplace | Z16: Inpatient | AA16: =IFERROR(_xlfn.XLOOKUP($J16,avoidable_ed_reference!$A$2:$A$13,avoidable_ed_reference!$C$2:$C$13),"Not Classified") -> Non-Avoidable | AB16: =IFERROR(_xlfn.XLOOKUP($B16,enrollment!$A$2:$A$801,enrollment!$I$2:$I$801),"") -> GA | AC16: =IFERROR(_xlfn.XLOOKUP($B16,enrollment!$A$2:$A$801,enrollment!$L$2:$L$801),"") -> 24 | AD16: {=_xlfn.IFS(AC16="","Unknown",AC16<18,"0-17",AC16<35,"18-34",AC16<50,"35-49",AC16<65,"50-64",TRUE,"65+")} -> 18-34 | AE16: =IFERROR(_xlfn.XLOOKUP($B16,enrollment!$A$2:$A$801,enrollment!$O$2:$O$801),"") -> 8901234567 | AF16: =IFERROR(_xlfn.XLOOKUP($AE16,providers!$B$2:$B$11,providers!$Q$2:$Q$11),"") -> 3.7 | AG16: =EOMONTH(E16,-1)+1 -> 45627
A17: CLM-000016 | B17: M-000003 | C17: 8901234567 | D17: 8901234567 | E17: 45347 | F17: 45347 | G17: 45364 | H17: Professional | I17: 11 | J17: I10 | K17: 99213 | O17: 1 | P17: 191.57 | Q17: 141.9 | R17: 113.52 | S17: 28.38 | T17: Y | X17: PLN-MKT-400 | Y17: Marketplace | Z17: PCP | AA17: =IFERROR(_xlfn.XLOOKUP($J17,avoidable_ed_reference!$A$2:$A$13,avoidable_ed_reference!$C$2:$C$13),"Not Classified") -> Not Classified | AB17: =IFERROR(_xlfn.XLOOKUP($B17,enrollment!$A$2:$A$801,enrollment!$I$2:$I$801),"") -> GA | AC17: =IFERROR(_xlfn.XLOOKUP($B17,enrollment!$A$2:$A$801,enrollment!$L$2:$L$801),"") -> 24 | AD17: {=_xlfn.IFS(AC17="","Unknown",AC17<18,"0-17",AC17<35,"18-34",AC17<50,"35-49",AC17<65,"50-64",TRUE,"65+")} -> 18-34 | AE17: =IFERROR(_xlfn.XLOOKUP($B17,enrollment!$A$2:$A$801,enrollment!$O$2:$O$801),"") -> 8901234567 | AF17: =IFERROR(_xlfn.XLOOKUP($AE17,providers!$B$2:$B$11,providers!$Q$2:$Q$11),"") -> 3.7 | AG17: =EOMONTH(E17,-1)+1 -> 45323
A18: CLM-000017 | B18: M-000003 | C18: 8901234567 | D18: 8901234567 | E18: 45653 | F18: 45653 | G18: 45677 | H18: Professional | I18: 11 | J18: I10 | K18: 99213 | O18: 1 | P18: 242 | Q18: 179.26 | R18: 143.41 | S18: 35.85 | T18: Y | X18: PLN-MKT-400 | Y18: Marketplace | Z18: PCP | AA18: =IFERROR(_xlfn.XLOOKUP($J18,avoidable_ed_reference!$A$2:$A$13,avoidable_ed_reference!$C$2:$C$13),"Not Classified") -> Not Classified | AB18: =IFERROR(_xlfn.XLOOKUP($B18,enrollment!$A$2:$A$801,enrollment!$I$2:$I$801),"") -> GA | AC18: =IFERROR(_xlfn.XLOOKUP($B18,enrollment!$A$2:$A$801,enrollment!$L$2:$L$801),"") -> 24 | AD18: {=_xlfn.IFS(AC18="","Unknown",AC18<18,"0-17",AC18<35,"18-34",AC18<50,"35-49",AC18<65,"50-64",TRUE,"65+")} -> 18-34 | AE18: =IFERROR(_xlfn.XLOOKUP($B18,enrollment!$A$2:$A$801,enrollment!$O$2:$O$801),"") -> 8901234567 | AF18: =IFERROR(_xlfn.XLOOKUP($AE18,providers!$B$2:$B$11,providers!$Q$2:$Q$11),"") -> 3.7 | AG18: =EOMONTH(E18,-1)+1 -> 45627
A19: CLM-000018 | B19: M-000004 | C19: 5678901234 | D19: 5678901234 | E19: 45457 | F19: 45457 | G19: 45474 | H19: Professional | I19: 11 | J19: J06.9 | K19: 99213 | O19: 1 | P19: 183.92 | Q19: 136.24 | R19: 108.99 | S19: 27.25 | T19: Y | X19: PLN-MKT-401 | Y19: Marketplace | Z19: PCP | AA19: =IFERROR(_xlfn.XLOOKUP($J19,avoidable_ed_reference!$A$2:$A$13,avoidable_ed_reference!$C$2:$C$13),"Not Classified") -> Avoidable | AB19: =IFERROR(_xlfn.XLOOKUP($B19,enrollment!$A$2:$A$801,enrollment!$I$2:$I$801),"") -> TN | AC19: =IFERROR(_xlfn.XLOOKUP($B19,enrollment!$A$2:$A$801,enrollment!$L$2:$L$801),"") -> 71 | AD19: {=_xlfn.IFS(AC19="","Unknown",AC19<18,"0-17",AC19<35,"18-34",AC19<50,"35-49",AC19<65,"50-64",TRUE,"65+")} -> 65+ | AE19: =IFERROR(_xlfn.XLOOKUP($B19,enrollment!$A$2:$A$801,enrollment!$O$2:$O$801),"") -> 5678901234 | AF19: =IFERROR(_xlfn.XLOOKUP($AE19,providers!$B$2:$B$11,providers!$Q$2:$Q$11),"") -> 3.8 | AG19: =EOMONTH(E19,-1)+1 -> 45444
A20: CLM-000019 | B20: M-000004 | C20: 5678901234 | D20: 5678901234 | E20: 45504 | F20: 45504 | G20: 45524 | H20: Professional | I20: 11 | J20: E11.9 | K20: 99213 | O20: 1 | P20: 197.34 | Q20: 146.18 | R20: 116.94 | S20: 29.24 | T20: Y | X20: PLN-MKT-401 | Y20: Marketplace | Z20: PCP | AA20: =IFERROR(_xlfn.XLOOKUP($J20,avoidable_ed_reference!$A$2:$A$13,avoidable_ed_reference!$C$2:$C$13),"Not Classified") -> Not Classified | AB20: =IFERROR(_xlfn.XLOOKUP($B20,enrollment!$A$2:$A$801,enrollment!$I$2:$I$801),"") -> TN | AC20: =IFERROR(_xlfn.XLOOKUP($B20,enrollment!$A$2:$A$801,enrollment!$L$2:$L$801),"") -> 71 | AD20: {=_xlfn.IFS(AC20="","Unknown",AC20<18,"0-17",AC20<35,"18-34",AC20<50,"35-49",AC20<65,"50-64",TRUE,"65+")} -> 65+ | AE20: =IFERROR(_xlfn.XLOOKUP($B20,enrollment!$A$2:$A$801,enrollment!$O$2:$O$801),"") -> 5678901234 | AF20: =IFERROR(_xlfn.XLOOKUP($AE20,providers!$B$2:$B$11,providers!$Q$2:$Q$11),"") -> 3.8 | AG20: =EOMONTH(E20,-1)+1 -> 45474
A21: CLM-000020 | B21: M-000004 | C21: 5678901234 | D21: 5678901234 | E21: 45448 | F21: 45448 | G21: 45469 | H21: Professional | I21: 11 | J21: E11.9 | K21: 99213 | O21: 1 | P21: 185.57 | Q21: 137.46 | R21: 109.97 | S21: 27.49 | T21: Y | X21: PLN-MKT-401 | Y21: Marketplace | Z21: PCP | AA21: =IFERROR(_xlfn.XLOOKUP($J21,avoidable_ed_reference!$A$2:$A$13,avoidable_ed_reference!$C$2:$C$13),"Not Classified") -> Not Classified | AB21: =IFERROR(_xlfn.XLOOKUP($B21,enrollment!$A$2:$A$801,enrollment!$I$2:$I$801),"") -> TN | AC21: =IFERROR(_xlfn.XLOOKUP($B21,enrollment!$A$2:$A$801,enrollment!$L$2:$L$801),"") -> 71 | AD21: {=_xlfn.IFS(AC21="","Unknown",AC21<18,"0-17",AC21<35,"18-34",AC21<50,"35-49",AC21<65,"50-64",TRUE,"65+")} -> 65+ | AE21: =IFERROR(_xlfn.XLOOKUP($B21,enrollment!$A$2:$A$801,enrollment!$O$2:$O$801),"") -> 5678901234 | AF21: =IFERROR(_xlfn.XLOOKUP($AE21,providers!$B$2:$B$11,providers!$Q$2:$Q$11),"") -> 3.8 | AG21: =EOMONTH(E21,-1)+1 -> 45444
A22: CLM-000021 | B22: M-000004 | C22: 7890123456 | D22: 7890123456 | E22: 45336 | F22: 45336 | G22: 45361 | H22: Professional | I22: 23 | J22: M54.5 | K22: 99284 | O22: 1 | P22: 1706.15 | Q22: 947.86 | R22: 758.29 | S22: 189.57 | T22: Y | X22: PLN-MKT-401 | Y22: Marketplace | Z22: ED | AA22: =IFERROR(_xlfn.XLOOKUP($J22,avoidable_ed_reference!$A$2:$A$13,avoidable_ed_reference!$C$2:$C$13),"Not Classified") -> Avoidable | AB22: =IFERROR(_xlfn.XLOOKUP($B22,enrollment!$A$2:$A$801,enrollment!$I$2:$I$801),"") -> TN | AC22: =IFERROR(_xlfn.XLOOKUP($B22,enrollment!$A$2:$A$801,enrollment!$L$2:$L$801),"") -> 71 | AD22: {=_xlfn.IFS(AC22="","Unknown",AC22<18,"0-17",AC22<35,"18-34",AC22<50,"35-49",AC22<65,"50-64",TRUE,"65+")} -> 65+ | AE22: =IFERROR(_xlfn.XLOOKUP($B22,enrollment!$A$2:$A$801,enrollment!$O$2:$O$801),"") -> 5678901234 | AF22: =IFERROR(_xlfn.XLOOKUP($AE22,providers!$B$2:$B$11,providers!$Q$2:$Q$11),"") -> 3.8 | AG22: =EOMONTH(E22,-1)+1 -> 45323
A23: CLM-000022 | B23: M-000004 | C23: 9012345678 | D23: 9012345678 | E23: 45319 | F23: 45319 | G23: 45352 | H23: Professional | I23: 22 | J23: F32.9 | K23: 90837 | O23: 1 | P23: 248.41 | Q23: 184.01 | R23: 147.21 | S23: 36.8 | T23: Y | X23: PLN-MKT-401 | Y23: Marketplace | Z23: Behavioral Health | AA23: =IFERROR(_xlfn.XLOOKUP($J23,avoidable_ed_reference!$A$2:$A$13,avoidable_ed_reference!$C$2:$C$13),"Not Classified") -> Potentially Avoidable | AB23: =IFERROR(_xlfn.XLOOKUP($B23,enrollment!$A$2:$A$801,enrollment!$I$2:$I$801),"") -> TN | AC23: =IFERROR(_xlfn.XLOOKUP($B23,enrollment!$A$2:$A$801,enrollment!$L$2:$L$801),"") -> 71 | AD23: {=_xlfn.IFS(AC23="","Unknown",AC23<18,"0-17",AC23<35,"18-34",AC23<50,"35-49",AC23<65,"50-64",TRUE,"65+")} -> 65+ | AE23: =IFERROR(_xlfn.XLOOKUP($B23,enrollment!$A$2:$A$801,enrollment!$O$2:$O$801),"") -> 5678901234 | AF23: =IFERROR(_xlfn.XLOOKUP($AE23,providers!$B$2:$B$11,providers!$Q$2:$Q$11),"") -> 3.8 | AG23: =EOMONTH(E23,-1)+1 -> 45292
A24: CLM-000023 | B24: M-000004 | C24: 2233445566 | D24: 2233445566 | E24: 45443 | F24: 45443 | G24: 45457 | H24: Professional | I24: 23 | J24: J18.9 | K24: 99284 | O24: 1 | P24: 1893.62 | Q24: 1052.01 | R24: 841.61 | S24: 210.4 | T24: Y | X24: PLN-MKT-401 | Y24: Marketplace | Z24: ED | AA24: =IFERROR(_xlfn.XLOOKUP($J24,avoidable_ed_reference!$A$2:$A$13,avoidable_ed_reference!$C$2:$C$13),"Not Classified") -> Non-Avoidable | AB24: =IFERROR(_xlfn.XLOOKUP($B24,enrollment!$A$2:$A$801,enrollment!$I$2:$I$801),"") -> TN | AC24: =IFERROR(_xlfn.XLOOKUP($B24,enrollment!$A$2:$A$801,enrollment!$L$2:$L$801),"") -> 71 | AD24: {=_xlfn.IFS(AC24="","Unknown",AC24<18,"0-17",AC24<35,"18-34",AC24<50,"35-49",AC24<65,"50-64",TRUE,"65+")} -> 65+ | AE24: =IFERROR(_xlfn.XLOOKUP($B24,enrollment!$A$2:$A$801,enrollment!$O$2:$O$801),"") -> 5678901234 | AF24: =IFERROR(_xlfn.XLOOKUP($AE24,providers!$B$2:$B$11,providers!$Q$2:$Q$11),"") -> 3.8 | AG24: =EOMONTH(E24,-1)+1 -> 45413
A25: CLM-000024 | B25: M-000004 | C25: 9012345678 | D25: 9012345678 | E25: 45313 | F25: 45313 | G25: 45346 | H25: Pharmacy | J25: E11.9 | L25: 00378180510 | M25: Insulin Glargine | N25: Diabetes | O25: 1 | P25: 793.67 | Q25: 721.52 | R25: 577.22 | S25: 144.3 | T25: Y | X25: PLN-MKT-401 | Y25: Marketplace | Z25: Specialty Rx | AA25: =IFERROR(_xlfn.XLOOKUP($J25,avoidable_ed_reference!$A$2:$A$13,avoidable_ed_reference!$C$2:$C$13),"Not Classified") -> Not Classified | AB25: =IFERROR(_xlfn.XLOOKUP($B25,enrollment!$A$2:$A$801,enrollment!$I$2:$I$801),"") -> TN | AC25: =IFERROR(_xlfn.XLOOKUP($B25,enrollment!$A$2:$A$801,enrollment!$L$2:$L$801),"") -> 71 | AD25: {=_xlfn.IFS(AC25="","Unknown",AC25<18,"0-17",AC25<35,"18-34",AC25<50,"35-49",AC25<65,"50-64",TRUE,"65+")} -> 65+ | AE25: =IFERROR(_xlfn.XLOOKUP($B25,enrollment!$A$2:$A$801,enrollment!$O$2:$O$801),"") -> 5678901234 | AF25: =IFERROR(_xlfn.XLOOKUP($AE25,providers!$B$2:$B$11,providers!$Q$2:$Q$11),"") -> 3.8 | AG25: =EOMONTH(E25,-1)+1 -> 45292
A26: CLM-000025 | B26: M-000004 | C26: 3456789012 | D26: 3456789012 | E26: 45440 | F26: 45440 | G26: 45469 | H26: Institutional | I26: 21 | J26: J18.9 | K26: 99223 | O26: 1 | P26: 22010.43 | Q26: 14200.28 | R26: 11360.22 | S26: 2840.06 | T26: Y | V26: 1 | W26: 01 | X26: PLN-MKT-401 | Y26: Marketplace | Z26: Inpatient | AA26: =IFERROR(_xlfn.XLOOKUP($J26,avoidable_ed_reference!$A$2:$A$13,avoidable_ed_reference!$C$2:$C$13),"Not Classified") -> Non-Avoidable | AB26: =IFERROR(_xlfn.XLOOKUP($B26,enrollment!$A$2:$A$801,enrollment!$I$2:$I$801),"") -> TN | AC26: =IFERROR(_xlfn.XLOOKUP($B26,enrollment!$A$2:$A$801,enrollment!$L$2:$L$801),"") -> 71 | AD26: {=_xlfn.IFS(AC26="","Unknown",AC26<18,"0-17",AC26<35,"18-34",AC26<50,"35-49",AC26<65,"50-64",TRUE,"65+")} -> 65+ | AE26: =IFERROR(_xlfn.XLOOKUP($B26,enrollment!$A$2:$A$801,enrollment!$O$2:$O$801),"") -> 5678901234 | AF26: =IFERROR(_xlfn.XLOOKUP($AE26,providers!$B$2:$B$11,providers!$Q$2:$Q$11),"") -> 3.8 | AG26: =EOMONTH(E26,-1)+1 -> 45413
A27: CLM-000026 | B27: M-000005 | C27: 9012345678 | D27: 9012345678 | E27: 45319 | F27: 45319 | G27: 45339 | H27: Professional | I27: 11 | J27: E11.9 | K27: 99213 | O27: 1 | P27: 200.88 | Q27: 148.8 | R27: 119.04 | S27: 29.76 | T27: Y | X27: PLN-MKT-401 | Y27: Marketplace | Z27: PCP | AA27: =IFERROR(_xlfn.XLOOKUP($J27,avoidable_ed_reference!$A$2:$A$13,avoidable_ed_reference!$C$2:$C$13),"Not Classified") -> Not Classified | AB27: =IFERROR(_xlfn.XLOOKUP($B27,enrollment!$A$2:$A$801,enrollment!$I$2:$I$801),"") -> TN | AC27: =IFERROR(_xlfn.XLOOKUP($B27,enrollment!$A$2:$A$801,enrollment!$L$2:$L$801),"") -> 53 | AD27: {=_xlfn.IFS(AC27="","Unknown",AC27<18,"0-17",AC27<35,"18-34",AC27<50,"35-49",AC27<65,"50-64",TRUE,"65+")} -> 50-64 | AE27: =IFERROR(_xlfn.XLOOKUP($B27,enrollment!$A$2:$A$801,enrollment!$O$2:$O$801),"") -> 0 | AF27: =IFERROR(_xlfn.XLOOKUP($AE27,providers!$B$2:$B$11,providers!$Q$2:$Q$11),"") | AG27: =EOMONTH(E27,-1)+1 -> 45292
A28: CLM-000027 | B28: M-000005 | C28: 5678901234 | D28: 5678901234 | E28: 45358 | F28: 45358 | G28: 45386 | H28: Professional | I28: 20 | J28: J06.9 | K28: 99213 | O28: 1 | P28: 157.08 | Q28: 120.83 | R28: 96.66 | S28: 24.17 | T28: Y | X28: PLN-MKT-401 | Y28: Marketplace | Z28: Urgent Care | AA28: =IFERROR(_xlfn.XLOOKUP($J28,avoidable_ed_reference!$A$2:$A$13,avoidable_ed_reference!$C$2:$C$13),"Not Classified") -> Avoidable | AB28: =IFERROR(_xlfn.XLOOKUP($B28,enrollment!$A$2:$A$801,enrollment!$I$2:$I$801),"") -> TN | AC28: =IFERROR(_xlfn.XLOOKUP($B28,enrollment!$A$2:$A$801,enrollment!$L$2:$L$801),"") -> 53 | AD28: {=_xlfn.IFS(AC28="","Unknown",AC28<18,"0-17",AC28<35,"18-34",AC28<50,"35-49",AC28<65,"50-64",TRUE,"65+")} -> 50-64 | AE28: =IFERROR(_xlfn.XLOOKUP($B28,enrollment!$A$2:$A$801,enrollment!$O$2:$O$801),"") -> 0 | AF28: =IFERROR(_xlfn.XLOOKUP($AE28,providers!$B$2:$B$11,providers!$Q$2:$Q$11),"") | AG28: =EOMONTH(E28,-1)+1 -> 45352
A29: CLM-000028 | B29: M-000005 | C29: 7890123456 | D29: 7890123456 | E29: 45397 | F29: 45397 | G29: 45419 | H29: Professional | I29: 22 | J29: F32.9 | K29: 90837 | O29: 1 | P29: 278.76 | Q29: 206.49 | R29: 165.19 | S29: 41.3 | T29: Y | X29: PLN-MKT-401 | Y29: Marketplace | Z29: Behavioral Health | AA29: =IFERROR(_xlfn.XLOOKUP($J29,avoidable_ed_reference!$A$2:$A$13,avoidable_ed_reference!$C$2:$C$13),"Not Classified") -> Potentially Avoidable | AB29: =IFERROR(_xlfn.XLOOKUP($B29,enrollment!$A$2:$A$801,enrollment!$I$2:$I$801),"") -> TN | AC29: =IFERROR(_xlfn.XLOOKUP($B29,enrollment!$A$2:$A$801,enrollment!$L$2:$L$801),"") -> 53 | AD29: {=_xlfn.IFS(AC29="","Unknown",AC29<18,"0-17",AC29<35,"18-34",AC29<50,"35-49",AC29<65,"50-64",TRUE,"65+")} -> 50-64 | AE29: =IFERROR(_xlfn.XLOOKUP($B29,enrollment!$A$2:$A$801,enrollment!$O$2:$O$801),"") -> 0 | AF29: =IFERROR(_xlfn.XLOOKUP($AE29,providers!$B$2:$B$11,providers!$Q$2:$Q$11),"") | AG29: =EOMONTH(E29,-1)+1 -> 45383
A30: CLM-000029 | B30: M-000005 | C30: 2233445566 | D30: 2233445566 | E30: 45307 | F30: 45307 | G30: 45340 | H30: Professional | I30: 23 | J30: H66.90 | K30: 99284 | O30: 1 | P30: 2104.67 | Q30: 1169.26 | R30: 935.41 | S30: 233.85 | T30: Y | X30: PLN-MKT-401 | Y30: Marketplace | Z30: ED | AA30: =IFERROR(_xlfn.XLOOKUP($J30,avoidable_ed_reference!$A$2:$A$13,avoidable_ed_reference!$C$2:$C$13),"Not Classified") -> Avoidable | AB30: =IFERROR(_xlfn.XLOOKUP($B30,enrollment!$A$2:$A$801,enrollment!$I$2:$I$801),"") -> TN | AC30: =IFERROR(_xlfn.XLOOKUP($B30,enrollment!$A$2:$A$801,enrollment!$L$2:$L$801),"") -> 53 | AD30: {=_xlfn.IFS(AC30="","Unknown",AC30<18,"0-17",AC30<35,"18-34",AC30<50,"35-49",AC30<65,"50-64",TRUE,"65+")} -> 50-64 | AE30: =IFERROR(_xlfn.XLOOKUP($B30,enrollment!$A$2:$A$801,enrollment!$O$2:$O$801),"") -> 0 | AF30: =IFERROR(_xlfn.XLOOKUP($AE30,providers!$B$2:$B$11,providers!$Q$2:$Q$11),"") | AG30: =EOMONTH(E30,-1)+1 -> 45292
A31: CLM-000030 | B31: M-000005 | C31: 6789012345 | D31: 6789012345 | E31: 45329 | F31: 45329 | G31: 45352 | H31: Professional | I31: 23 | J31: K21.9 | K31: 99284 | O31: 1 | P31: 2519.62 | Q31: 1399.79 | R31: 1119.83 | S31: 279.96 | T31: Y | X31: PLN-MKT-401 | Y31: Marketplace | Z31: ED | AA31: =IFERROR(_xlfn.XLOOKUP($J31,avoidable_ed_reference!$A$2:$A$13,avoidable_ed_reference!$C$2:$C$13),"Not Classified") -> Avoidable | AB31: =IFERROR(_xlfn.XLOOKUP($B31,enrollment!$A$2:$A$801,enrollment!$I$2:$I$801),"") -> TN | AC31: =IFERROR(_xlfn.XLOOKUP($B31,enrollment!$A$2:$A$801,enrollment!$L$2:$L$801),"") -> 53 | AD31: {=_xlfn.IFS(AC31="","Unknown",AC31<18,"0-17",AC31<35,"18-34",AC31<50,"35-49",AC31<65,"50-64",TRUE,"65+")} -> 50-64 | AE31: =IFERROR(_xlfn.XLOOKUP($B31,enrollment!$A$2:$A$801,enrollment!$O$2:$O$801),"") -> 0 | AF31: =IFERROR(_xlfn.XLOOKUP($AE31,providers!$B$2:$B$11,providers!$Q$2:$Q$11),"") | AG31: =EOMONTH(E31,-1)+1 -> 45323
A32: CLM-000031 | B32: M-000005 | C32: 6789012345 | D32: 6789012345 | E32: 45410 | F32: 45410 | G32: 45436 | H32: Professional | I32: 11 | J32: I10 | K32: 99213 | O32: 1 | P32: 239.42 | Q32: 177.35 | R32: 141.88 | S32: 35.47 | T32: Y | X32: PLN-MKT-401 | Y32: Marketplace | Z32: PCP | AA32: =IFERROR(_xlfn.XLOOKUP($J32,avoidable_ed_reference!$A$2:$A$13,avoidable_ed_reference!$C$2:$C$13),"Not Classified") -> Not Classified | AB32: =IFERROR(_xlfn.XLOOKUP($B32,enrollment!$A$2:$A$801,enrollment!$I$2:$I$801),"") -> TN | AC32: =IFERROR(_xlfn.XLOOKUP($B32,enrollment!$A$2:$A$801,enrollment!$L$2:$L$801),"") -> 53 | AD32: {=_xlfn.IFS(AC32="","Unknown",AC32<18,"0-17",AC32<35,"18-34",AC32<50,"35-49",AC32<65,"50-64",TRUE,"65+")} -> 50-64 | AE32: =IFERROR(_xlfn.XLOOKUP($B32,enrollment!$A$2:$A$801,enrollment!$O$2:$O$801),"") -> 0 | AF32: =IFERROR(_xlfn.XLOOKUP($AE32,providers!$B$2:$B$11,providers!$Q$2:$Q$11),"") | AG32: =EOMONTH(E32,-1)+1 -> 45383
A33: CLM-000032 | B33: M-000005 | C33: 8901234567 | D33: 8901234567 | E33: 45566 | F33: 45566 | G33: 45591 | H33: Professional | I33: 11 | J33: J06.9 | K33: 99213 | O33: 1 | P33: 181.47 | Q33: 134.42 | R33: 107.54 | S33: 26.88 | T33: Y | X33: PLN-MKT-401 | Y33: Marketplace | Z33: PCP | AA33: =IFERROR(_xlfn.XLOOKUP($J33,avoidable_ed_reference!$A$2:$A$13,avoidable_ed_reference!$C$2:$C$13),"Not Classified") -> Avoidable | AB33: =IFERROR(_xlfn.XLOOKUP($B33,enrollment!$A$2:$A$801,enrollment!$I$2:$I$801),"") -> TN | AC33: =IFERROR(_xlfn.XLOOKUP($B33,enrollment!$A$2:$A$801,enrollment!$L$2:$L$801),"") -> 53 | AD33: {=_xlfn.IFS(AC33="","Unknown",AC33<18,"0-17",AC33<35,"18-34",AC33<50,"35-49",AC33<65,"50-64",TRUE,"65+")} -> 50-64 | AE33: =IFERROR(_xlfn.XLOOKUP($B33,enrollment!$A$2:$A$801,enrollment!$O$2:$O$801),"") -> 0 | AF33: =IFERROR(_xlfn.XLOOKUP($AE33,providers!$B$2:$B$11,providers!$Q$2:$Q$11),"") | AG33: =EOMONTH(E33,-1)+1 -> 45566
A34: CLM-000033 | B34: M-000006 | C34: 9012345678 | D34: 9012345678 | E34: 45656 | F34: 45656 | G34: 45677 | H34: Professional | I34: 11 | J34: E11.9 | K34: 99213 | O34: 1 | P34: 189.63 | Q34: 140.47 | R34: 112.38 | S34: 28.09 | T34: Y | X34: PLN-COM-250 | Y34: Commercial | Z34: PCP | AA34: =IFERROR(_xlfn.XLOOKUP($J34,avoidable_ed_reference!$A$2:$A$13,avoidable_ed_reference!$C$2:$C$13),"Not Classified") -> Not Classified | AB34: =IFERROR(_xlfn.XLOOKUP($B34,enrollment!$A$2:$A$801,enrollment!$I$2:$I$801),"") -> KY | AC34: =IFERROR(_xlfn.XLOOKUP($B34,enrollment!$A$2:$A$801,enrollment!$L$2:$L$801),"") -> 54 | AD34: {=_xlfn.IFS(AC34="","Unknown",AC34<18,"0-17",AC34<35,"18-34",AC34<50,"35-49",AC34<65,"50-64",TRUE,"65+")} -> 50-64 | AE34: =IFERROR(_xlfn.XLOOKUP($B34,enrollment!$A$2:$A$801,enrollment!$O$2:$O$801),"") -> 9012345678 | AF34: =IFERROR(_xlfn.XLOOKUP($AE34,providers!$B$2:$B$11,providers!$Q$2:$Q$11),"") -> 4.3 | AG34: =EOMONTH(E34,-1)+1 -> 45627
A35: CLM-000034 | B35: M-000006 | C35: 3456789012 | D35: 3456789012 | E35: 45352 | F35: 45352 | G35: 45367 | H35: Institutional | I35: 21 | J35: C34.90 | K35: 99223 | O35: 1 | P35: 32010.51 | Q35: 20651.94 | R35: 16521.55 | S35: 4130.39 | T35: Y | V35: 1 | W35: 01 | X35: PLN-COM-250 | Y35: Commercial | Z35: Inpatient | AA35: =IFERROR(_xlfn.XLOOKUP($J35,avoidable_ed_reference!$A$2:$A$13,avoidable_ed_reference!$C$2:$C$13),"Not Classified") -> Not Classified | AB35: =IFERROR(_xlfn.XLOOKUP($B35,enrollment!$A$2:$A$801,enrollment!$I$2:$I$801),"") -> KY | AC35: =IFERROR(_xlfn.XLOOKUP($B35,enrollment!$A$2:$A$801,enrollment!$L$2:$L$801),"") -> 54 | AD35: {=_xlfn.IFS(AC35="","Unknown",AC35<18,"0-17",AC35<35,"18-34",AC35<50,"35-49",AC35<65,"50-64",TRUE,"65+")} -> 50-64 | AE35: =IFERROR(_xlfn.XLOOKUP($B35,enrollment!$A$2:$A$801,enrollment!$O$2:$O$801),"") -> 9012345678 | AF35: =IFERROR(_xlfn.XLOOKUP($AE35,providers!$B$2:$B$11,providers!$Q$2:$Q$11),"") -> 4.3 | AG35: =EOMONTH(E35,-1)+1 -> 45352
A36: CLM-000035 | B36: M-000006 | C36: 9012345678 | D36: 9012345678 | E36: 45490 | F36: 45490 | G36: 45514 | H36: Professional | I36: 11 | J36: I10 | K36: 99213 | O36: 1 | P36: 165.5 | Q36: 122.59 | R36: 98.07 | S36: 24.52 | T36: Y | X36: PLN-COM-250 | Y36: Commercial | Z36: PCP | AA36: =IFERROR(_xlfn.XLOOKUP($J36,avoidable_ed_reference!$A$2:$A$13,avoidable_ed_reference!$C$2:$C$13),"Not Classified") -> Not Classified | AB36: =IFERROR(_xlfn.XLOOKUP($B36,enrollment!$A$2:$A$801,enrollment!$I$2:$I$801),"") -> KY | AC36: =IFERROR(_xlfn.XLOOKUP($B36,enrollment!$A$2:$A$801,enrollment!$L$2:$L$801),"") -> 54 | AD36: {=_xlfn.IFS(AC36="","Unknown",AC36<18,"0-17",AC36<35,"18-34",AC36<50,"35-49",AC36<65,"50-64",TRUE,"65+")} -> 50-64 | AE36: =IFERROR(_xlfn.XLOOKUP($B36,enrollment!$A$2:$A$801,enrollment!$O$2:$O$801),"") -> 9012345678 | AF36: =IFERROR(_xlfn.XLOOKUP($AE36,providers!$B$2:$B$11,providers!$Q$2:$Q$11),"") -> 4.3 | AG36: =EOMONTH(E36,-1)+1 -> 45474
A37: CLM-000036 | B37: M-000006 | C37: 9012345678 | D37: 9012345678 | E37: 45318 | F37: 45318 | G37: 45350 | H37: Professional | I37: 11 | J37: I10 | K37: 99213 | O37: 1 | P37: 240.11 | Q37: 177.86 | R37: 142.29 | S37: 35.57 | T37: Y | X37: PLN-COM-250 | Y37: Commercial | Z37: PCP | AA37: =IFERROR(_xlfn.XLOOKUP($J37,avoidable_ed_reference!$A$2:$A$13,avoidable_ed_reference!$C$2:$C$13),"Not Classified") -> Not Classified | AB37: =IFERROR(_xlfn.XLOOKUP($B37,enrollment!$A$2:$A$801,enrollment!$I$2:$I$801),"") -> KY | AC37: =IFERROR(_xlfn.XLOOKUP($B37,enrollment!$A$2:$A$801,enrollment!$L$2:$L$801),"") -> 54 | AD37: {=_xlfn.IFS(AC37="","Unknown",AC37<18,"0-17",AC37<35,"18-34",AC37<50,"35-49",AC37<65,"50-64",TRUE,"65+")} -> 50-64 | AE37: =IFERROR(_xlfn.XLOOKUP($B37,enrollment!$A$2:$A$801,enrollment!$O$2:$O$801),"") -> 9012345678 | AF37: =IFERROR(_xlfn.XLOOKUP($AE37,providers!$B$2:$B$11,providers!$Q$2:$Q$11),"") -> 4.3 | AG37: =EOMONTH(E37,-1)+1 -> 45292
A38: CLM-000037 | B38: M-000007 | C38: 5678901234 | D38: 5678901234 | E38: 45585 | F38: 45585 | G38: 45605 | H38: Professional | I38: 11 | J38: J06.9 | K38: 99213 | O38: 1 | P38: 228.6 | Q38: 169.33 | R38: 135.46 | S38: 33.87 | T38: Y | X38: PLN-COM-250 | Y38: Commercial | Z38: PCP | AA38: =IFERROR(_xlfn.XLOOKUP($J38,avoidable_ed_reference!$A$2:$A$13,avoidable_ed_reference!$C$2:$C$13),"Not Classified") -> Avoidable | AB38: =IFERROR(_xlfn.XLOOKUP($B38,enrollment!$A$2:$A$801,enrollment!$I$2:$I$801),"") -> TN | AC38: =IFERROR(_xlfn.XLOOKUP($B38,enrollment!$A$2:$A$801,enrollment!$L$2:$L$801),"") -> 69 | AD38: {=_xlfn.IFS(AC38="","Unknown",AC38<18,"0-17",AC38<35,"18-34",AC38<50,"35-49",AC38<65,"50-64",TRUE,"65+")} -> 65+ | AE38: =IFERROR(_xlfn.XLOOKUP($B38,enrollment!$A$2:$A$801,enrollment!$O$2:$O$801),"") -> 5678901234 | AF38: =IFERROR(_xlfn.XLOOKUP($AE38,providers!$B$2:$B$11,providers!$Q$2:$Q$11),"") -> 3.8 | AG38: =EOMONTH(E38,-1)+1 -> 45566
A39: CLM-000038 | B39: M-000007 | C39: 5678901234 | D39: 5678901234 | E39: 45635 | F39: 45635 | G39: 45656 | H39: Professional | I39: 11 | J39: I10 | K39: 99213 | O39: 1 | P39: 168.28 | Q39: 124.65 | R39: 99.72 | S39: 24.93 | T39: Y | X39: PLN-COM-250 | Y39: Commercial | Z39: PCP | AA39: =IFERROR(_xlfn.XLOOKUP($J39,avoidable_ed_reference!$A$2:$A$13,avoidable_ed_reference!$C$2:$C$13),"Not Classified") -> Not Classified | AB39: =IFERROR(_xlfn.XLOOKUP($B39,enrollment!$A$2:$A$801,enrollment!$I$2:$I$801),"") -> TN | AC39: =IFERROR(_xlfn.XLOOKUP($B39,enrollment!$A$2:$A$801,enrollment!$L$2:$L$801),"") -> 69 | AD39: {=_xlfn.IFS(AC39="","Unknown",AC39<18,"0-17",AC39<35,"18-34",AC39<50,"35-49",AC39<65,"50-64",TRUE,"65+")} -> 65+ | AE39: =IFERROR(_xlfn.XLOOKUP($B39,enrollment!$A$2:$A$801,enrollment!$O$2:$O$801),"") -> 5678901234 | AF39: =IFERROR(_xlfn.XLOOKUP($AE39,providers!$B$2:$B$11,providers!$Q$2:$Q$11),"") -> 3.8 | AG39: =EOMONTH(E39,-1)+1 -> 45627
A40: CLM-000039 | B40: M-000007 | C40: 2345678901 | D40: 2345678901 | E40: 45418 | F40: 45418 | G40: 45433 | H40: Pharmacy | J40: E11.9 | L40: 00074433902 | M40: Adalimumab | N40: Autoimmune Biologic | O40: 1 | P40: 902.6 | Q40: 820.55 | R40: 656.44 | S40: 164.11 | T40: Y | X40: PLN-COM-250 | Y40: Commercial | Z40: Specialty Rx | AA40: =IFERROR(_xlfn.XLOOKUP($J40,avoidable_ed_reference!$A$2:$A$13,avoidable_ed_reference!$C$2:$C$13),"Not Classified") -> Not Classified | AB40: =IFERROR(_xlfn.XLOOKUP($B40,enrollment!$A$2:$A$801,enrollment!$I$2:$I$801),"") -> TN | AC40: =IFERROR(_xlfn.XLOOKUP($B40,enrollment!$A$2:$A$801,enrollment!$L$2:$L$801),"") -> 69 | AD40: {=_xlfn.IFS(AC40="","Unknown",AC40<18,"0-17",AC40<35,"18-34",AC40<50,"35-49",AC40<65,"50-64",TRUE,"65+")} -> 65+ | AE40: =IFERROR(_xlfn.XLOOKUP($B40,enrollment!$A$2:$A$801,enrollment!$O$2:$O$801),"") -> 5678901234 | AF40: =IFERROR(_xlfn.XLOOKUP($AE40,providers!$B$2:$B$11,providers!$Q$2:$Q$11),"") -> 3.8 | AG40: =EOMONTH(E40,-1)+1 -> 45413
A41: CLM-000040 | B41: M-000007 | C41: 6789012345 | D41: 6789012345 | E41: 45385 | F41: 45385 | G41: 45403 | H41: Professional | I41: 23 | J41: J18.9 | K41: 99284 | O41: 1 | P41: 2136.46 | Q41: 1186.92 | R41: 949.54 | S41: 237.38 | T41: Y | X41: PLN-COM-250 | Y41: Commercial | Z41: ED | AA41: =IFERROR(_xlfn.XLOOKUP($J41,avoidable_ed_reference!$A$2:$A$13,avoidable_ed_reference!$C$2:$C$13),"Not Classified") -> Non-Avoidable | AB41: =IFERROR(_xlfn.XLOOKUP($B41,enrollment!$A$2:$A$801,enrollment!$I$2:$I$801),"") -> TN | AC41: =IFERROR(_xlfn.XLOOKUP($B41,enrollment!$A$2:$A$801,enrollment!$L$2:$L$801),"") -> 69 | AD41: {=_xlfn.IFS(AC41="","Unknown",AC41<18,"0-17",AC41<35,"18-34",AC41<50,"35-49",AC41<65,"50-64",TRUE,"65+")} -> 65+ | AE41: =IFERROR(_xlfn.XLOOKUP($B41,enrollment!$A$2:$A$801,enrollment!$O$2:$O$801),"") -> 5678901234 | AF41: =IFERROR(_xlfn.XLOOKUP($AE41,providers!$B$2:$B$11,providers!$Q$2:$Q$11),"") -> 3.8 | AG41: =EOMONTH(E41,-1)+1 -> 45383
A42: CLM-000041 | B42: M-000007 | C42: 5678901234 | D42: 5678901234 | E42: 45442 | F42: 45442 | G42: 45463 | H42: Professional | I42: 11 | J42: J06.9 | K42: 99213 | O42: 1 | P42: 215.41 | Q42: 159.56 | R42: 127.65 | S42: 31.91 | T42: Y | X42: PLN-COM-250 | Y42: Commercial | Z42: PCP | AA42: =IFERROR(_xlfn.XLOOKUP($J42,avoidable_ed_reference!$A$2:$A$13,avoidable_ed_reference!$C$2:$C$13),"Not Classified") -> Avoidable | AB42: =IFERROR(_xlfn.XLOOKUP($B42,enrollment!$A$2:$A$801,enrollment!$I$2:$I$801),"") -> TN | AC42: =IFERROR(_xlfn.XLOOKUP($B42,enrollment!$A$2:$A$801,enrollment!$L$2:$L$801),"") -> 69 | AD42: {=_xlfn.IFS(AC42="","Unknown",AC42<18,"0-17",AC42<35,"18-34",AC42<50,"35-49",AC42<65,"50-64",TRUE,"65+")} -> 65+ | AE42: =IFERROR(_xlfn.XLOOKUP($B42,enrollment!$A$2:$A$801,enrollment!$O$2:$O$801),"") -> 5678901234 | AF42: =IFERROR(_xlfn.XLOOKUP($AE42,providers!$B$2:$B$11,providers!$Q$2:$Q$11),"") -> 3.8 | AG42: =EOMONTH(E42,-1)+1 -> 45413
A43: CLM-000042 | B43: M-000008 | C43: 6789012345 | D43: 6789012345 | E43: 45546 | F43: 45546 | G43: 45575 | H43: Professional | I43: 11 | J43: E11.9 | K43: 99213 | O43: 1 | P43: 195.52 | Q43: 144.83 | R43: 115.86 | S43: 28.97 | T43: Y | X43: PLN-MKT-401 | Y43: Marketplace | Z43: PCP | AA43: =IFERROR(_xlfn.XLOOKUP($J43,avoidable_ed_reference!$A$2:$A$13,avoidable_ed_reference!$C$2:$C$13),"Not Classified") -> Not Classified | AB43: =IFERROR(_xlfn.XLOOKUP($B43,enrollment!$A$2:$A$801,enrollment!$I$2:$I$801),"") -> OH | AC43: =IFERROR(_xlfn.XLOOKUP($B43,enrollment!$A$2:$A$801,enrollment!$L$2:$L$801),"") -> 30 | AD43: {=_xlfn.IFS(AC43="","Unknown",AC43<18,"0-17",AC43<35,"18-34",AC43<50,"35-49",AC43<65,"50-64",TRUE,"65+")} -> 18-34 | AE43: =IFERROR(_xlfn.XLOOKUP($B43,enrollment!$A$2:$A$801,enrollment!$O$2:$O$801),"") -> 6789012345 | AF43: =IFERROR(_xlfn.XLOOKUP($AE43,providers!$B$2:$B$11,providers!$Q$2:$Q$11),"") -> 4.1 | AG43: =EOMONTH(E43,-1)+1 -> 45536
A44: CLM-000043 | B44: M-000008 | C44: 6789012345 | D44: 6789012345 | E44: 45390 | F44: 45390 | G44: 45423 | H44: Professional | I44: 11 | J44: E11.9 | K44: 99213 | O44: 1 | P44: 203.63 | Q44: 150.84 | R44: 120.67 | S44: 30.17 | T44: Y | X44: PLN-MKT-401 | Y44: Marketplace | Z44: PCP | AA44: =IFERROR(_xlfn.XLOOKUP($J44,avoidable_ed_reference!$A$2:$A$13,avoidable_ed_reference!$C$2:$C$13),"Not Classified") -> Not Classified | AB44: =IFERROR(_xlfn.XLOOKUP($B44,enrollment!$A$2:$A$801,enrollment!$I$2:$I$801),"") -> OH | AC44: =IFERROR(_xlfn.XLOOKUP($B44,enrollment!$A$2:$A$801,enrollment!$L$2:$L$801),"") -> 30 | AD44: {=_xlfn.IFS(AC44="","Unknown",AC44<18,"0-17",AC44<35,"18-34",AC44<50,"35-49",AC44<65,"50-64",TRUE,"65+")} -> 18-34 | AE44: =IFERROR(_xlfn.XLOOKUP($B44,enrollment!$A$2:$A$801,enrollment!$O$2:$O$801),"") -> 6789012345 | AF44: =IFERROR(_xlfn.XLOOKUP($AE44,providers!$B$2:$B$11,providers!$Q$2:$Q$11),"") -> 4.1 | AG44: =EOMONTH(E44,-1)+1 -> 45383
A45: CLM-000044 | B45: M-000008 | C45: 5678901234 | D45: 5678901234 | E45: 45643 | F45: 45643 | G45: 45674 | H45: Professional | I45: 20 | J45: J06.9 | K45: 99213 | O45: 1 | P45: 153.87 | Q45: 118.36 | R45: 94.69 | S45: 23.67 | T45: Y | X45: PLN-MKT-401 | Y45: Marketplace | Z45: Urgent Care | AA45: =IFERROR(_xlfn.XLOOKUP($J45,avoidable_ed_reference!$A$2:$A$13,avoidable_ed_reference!$C$2:$C$13),"Not Classified") -> Avoidable | AB45: =IFERROR(_xlfn.XLOOKUP($B45,enrollment!$A$2:$A$801,enrollment!$I$2:$I$801),"") -> OH | AC45: =IFERROR(_xlfn.XLOOKUP($B45,enrollment!$A$2:$A$801,enrollment!$L$2:$L$801),"") -> 30 | AD45: {=_xlfn.IFS(AC45="","Unknown",AC45<18,"0-17",AC45<35,"18-34",AC45<50,"35-49",AC45<65,"50-64",TRUE,"65+")} -> 18-34 | AE45: =IFERROR(_xlfn.XLOOKUP($B45,enrollment!$A$2:$A$801,enrollment!$O$2:$O$801),"") -> 6789012345 | AF45: =IFERROR(_xlfn.XLOOKUP($AE45,providers!$B$2:$B$11,providers!$Q$2:$Q$11),"") -> 4.1 | AG45: =EOMONTH(E45,-1)+1 -> 45627
A46: CLM-000045 | B46: M-000008 | C46: 6789012345 | D46: 6789012345 | E46: 45551 | F46: 45551 | G46: 45586 | H46: Professional | I46: 11 | J46: E11.9 | K46: 99213 | O46: 1 | P46: 228.54 | Q46: 169.29 | R46: 135.43 | S46: 33.86 | T46: Y | X46: PLN-MKT-401 | Y46: Marketplace | Z46: PCP | AA46: =IFERROR(_xlfn.XLOOKUP($J46,avoidable_ed_reference!$A$2:$A$13,avoidable_ed_reference!$C$2:$C$13),"Not Classified") -> Not Classified | AB46: =IFERROR(_xlfn.XLOOKUP($B46,enrollment!$A$2:$A$801,enrollment!$I$2:$I$801),"") -> OH | AC46: =IFERROR(_xlfn.XLOOKUP($B46,enrollment!$A$2:$A$801,enrollment!$L$2:$L$801),"") -> 30 | AD46: {=_xlfn.IFS(AC46="","Unknown",AC46<18,"0-17",AC46<35,"18-34",AC46<50,"35-49",AC46<65,"50-64",TRUE,"65+")} -> 18-34 | AE46: =IFERROR(_xlfn.XLOOKUP($B46,enrollment!$A$2:$A$801,enrollment!$O$2:$O$801),"") -> 6789012345 | AF46: =IFERROR(_xlfn.XLOOKUP($AE46,providers!$B$2:$B$11,providers!$Q$2:$Q$11),"") -> 4.1 | AG46: =EOMONTH(E46,-1)+1 -> 45536
A47: CLM-000046 | B47: M-000008 | C47: 6789012345 | D47: 6789012345 | E47: 45345 | F47: 45345 | G47: 45370 | H47: Professional | I47: 11 | J47: E11.9 | K47: 99213 | O47: 1 | P47: 239.94 | Q47: 177.73 | R47: 142.18 | S47: 35.55 | T47: Y | X47: PLN-MKT-401 | Y47: Marketplace | Z47: PCP | AA47: =IFERROR(_xlfn.XLOOKUP($J47,avoidable_ed_reference!$A$2:$A$13,avoidable_ed_reference!$C$2:$C$13),"Not Classified") -> Not Classified | AB47: =IFERROR(_xlfn.XLOOKUP($B47,enrollment!$A$2:$A$801,enrollment!$I$2:$I$801),"") -> OH | AC47: =IFERROR(_xlfn.XLOOKUP($B47,enrollment!$A$2:$A$801,enrollment!$L$2:$L$801),"") -> 30 | AD47: {=_xlfn.IFS(AC47="","Unknown",AC47<18,"0-17",AC47<35,"18-34",AC47<50,"35-49",AC47<65,"50-64",TRUE,"65+")} -> 18-34 | AE47: =IFERROR(_xlfn.XLOOKUP($B47,enrollment!$A$2:$A$801,enrollment!$O$2:$O$801),"") -> 6789012345 | AF47: =IFERROR(_xlfn.XLOOKUP($AE47,providers!$B$2:$B$11,providers!$Q$2:$Q$11),"") -> 4.1 | AG47: =EOMONTH(E47,-1)+1 -> 45323
A48: CLM-000047 | B48: M-000009 | C48: 8901234567 | D48: 8901234567 | E48: 45653 | F48: 45653 | G48: 45681 | H48: Professional | I48: 11 | J48: I10 | K48: 99213 | O48: 1 | P48: 209.2 | Q48: 154.96 | R48: 123.97 | S48: 30.99 | T48: Y | X48: PLN-MKT-401 | Y48: Marketplace | Z48: PCP | AA48: =IFERROR(_xlfn.XLOOKUP($J48,avoidable_ed_reference!$A$2:$A$13,avoidable_ed_reference!$C$2:$C$13),"Not Classified") -> Not Classified | AB48: =IFERROR(_xlfn.XLOOKUP($B48,enrollment!$A$2:$A$801,enrollment!$I$2:$I$801),"") -> GA | AC48: =IFERROR(_xlfn.XLOOKUP($B48,enrollment!$A$2:$A$801,enrollment!$L$2:$L$801),"") -> 35 | AD48: {=_xlfn.IFS(AC48="","Unknown",AC48<18,"0-17",AC48<35,"18-34",AC48<50,"35-49",AC48<65,"50-64",TRUE,"65+")} -> 35-49 | AE48: =IFERROR(_xlfn.XLOOKUP($B48,enrollment!$A$2:$A$801,enrollment!$O$2:$O$801),"") -> 8901234567 | AF48: =IFERROR(_xlfn.XLOOKUP($AE48,providers!$B$2:$B$11,providers!$Q$2:$Q$11),"") -> 3.7 | AG48: =EOMONTH(E48,-1)+1 -> 45627
A49: CLM-000048 | B49: M-000009 | C49: 8901234567 | D49: 8901234567 | E49: 45511 | F49: 45511 | G49: 45533 | H49: Professional | I49: 11 | J49: J06.9 | K49: 99213 | O49: 1 | P49: 230.78 | Q49: 170.95 | R49: 136.76 | S49: 34.19 | T49: Y | X49: PLN-MKT-401 | Y49: Marketplace | Z49: PCP | AA49: =IFERROR(_xlfn.XLOOKUP($J49,avoidable_ed_reference!$A$2:$A$13,avoidable_ed_reference!$C$2:$C$13),"Not Classified") -> Avoidable | AB49: =IFERROR(_xlfn.XLOOKUP($B49,enrollment!$A$2:$A$801,enrollment!$I$2:$I$801),"") -> GA | AC49: =IFERROR(_xlfn.XLOOKUP($B49,enrollment!$A$2:$A$801,enrollment!$L$2:$L$801),"") -> 35 | AD49: {=_xlfn.IFS(AC49="","Unknown",AC49<18,"0-17",AC49<35,"18-34",AC49<50,"35-49",AC49<65,"50-64",TRUE,"65+")} -> 35-49 | AE49: =IFERROR(_xlfn.XLOOKUP($B49,enrollment!$A$2:$A$801,enrollment!$O$2:$O$801),"") -> 8901234567 | AF49: =IFERROR(_xlfn.XLOOKUP($AE49,providers!$B$2:$B$11,providers!$Q$2:$Q$11),"") -> 3.7 | AG49: =EOMONTH(E49,-1)+1 -> 45505
A50: CLM-000049 | B50: M-000009 | C50: 7890123456 | D50: 7890123456 | E50: 45408 | F50: 45408 | G50: 45443 | H50: Pharmacy | J50: Z79.4 | L50: 00074433902 | M50: Adalimumab | N50: Autoimmune Biologic | O50: 1 | P50: 1197.53 | Q50: 1088.66 | R50: 870.93 | S50: 217.73 | T50: Y | X50: PLN-MKT-401 | Y50: Marketplace | Z50: Specialty Rx | AA50: =IFERROR(_xlfn.XLOOKUP($J50,avoidable_ed_reference!$A$2:$A$13,avoidable_ed_reference!$C$2:$C$13),"Not Classified") -> Not Classified | AB50: =IFERROR(_xlfn.XLOOKUP($B50,enrollment!$A$2:$A$801,enrollment!$I$2:$I$801),"") -> GA | AC50: =IFERROR(_xlfn.XLOOKUP($B50,enrollment!$A$2:$A$801,enrollment!$L$2:$L$801),"") -> 35 | AD50: {=_xlfn.IFS(AC50="","Unknown",AC50<18,"0-17",AC50<35,"18-34",AC50<50,"35-49",AC50<65,"50-64",TRUE,"65+")} -> 35-49 | AE50: =IFERROR(_xlfn.XLOOKUP($B50,enrollment!$A$2:$A$801,enrollment!$O$2:$O$801),"") -> 8901234567 | AF50: =IFERROR(_xlfn.XLOOKUP($AE50,providers!$B$2:$B$11,providers!$Q$2:$Q$11),"") -> 3.7 | AG50: =EOMONTH(E50,-1)+1 -> 45383
A51: CLM-000050 | B51: M-000009 | C51: 8901234567 | D51: 8901234567 | E51: 45346 | F51: 45346 | G51: 45363 | H51: Professional | I51: 11 | J51: E11.9 | K51: 99213 | O51: 1 | P51: 223.71 | Q51: 165.71 | R51: 132.57 | S51: 33.14 | T51: Y | X51: PLN-MKT-401 | Y51: Marketplace | Z51: PCP | AA51: =IFERROR(_xlfn.XLOOKUP($J51,avoidable_ed_reference!$A$2:$A$13,avoidable_ed_reference!$C$2:$C$13),"Not Classified") -> Not Classified | AB51: =IFERROR(_xlfn.XLOOKUP($B51,enrollment!$A$2:$A$801,enrollment!$I$2:$I$801),"") -> GA | AC51: =IFERROR(_xlfn.XLOOKUP($B51,enrollment!$A$2:$A$801,enrollment!$L$2:$L$801),"") -> 35 | AD51: {=_xlfn.IFS(AC51="","Unknown",AC51<18,"0-17",AC51<35,"18-34",AC51<50,"35-49",AC51<65,"50-64",TRUE,"65+")} -> 35-49 | AE51: =IFERROR(_xlfn.XLOOKUP($B51,enrollment!$A$2:$A$801,enrollment!$O$2:$O$801),"") -> 8901234567 | AF51: =IFERROR(_xlfn.XLOOKUP($AE51,providers!$B$2:$B$11,providers!$Q$2:$Q$11),"") -> 3.7 | AG51: =EOMONTH(E51,-1)+1 -> 45323
A52: CLM-000051 | B52: M-000009 | C52: 8901234567 | D52: 8901234567 | E52: 45588 | F52: 45588 | G52: 45617 | H52: Professional | I52: 23 | J52: J06.9 | K52: 99284 | O52: 1 | P52: 2387.54 | Q52: 1326.41 | R52: 1061.13 | S52: 265.28 | T52: Y | X52: PLN-MKT-401 | Y52: Marketplace | Z52: ED | AA52: =IFERROR(_xlfn.XLOOKUP($J52,avoidable_ed_reference!$A$2:$A$13,avoidable_ed_reference!$C$2:$C$13),"Not Classified") -> Avoidable | AB52: =IFERROR(_xlfn.XLOOKUP($B52,enrollment!$A$2:$A$801,enrollment!$I$2:$I$801),"") -> GA | AC52: =IFERROR(_xlfn.XLOOKUP($B52,enrollment!$A$2:$A$801,enrollment!$L$2:$L$801),"") -> 35 | AD52: {=_xlfn.IFS(AC52="","Unknown",AC52<18,"0-17",AC52<35,"18-34",AC52<50,"35-49",AC52<65,"50-64",TRUE,"65+")} -> 35-49 | AE52: =IFERROR(_xlfn.XLOOKUP($B52,enrollment!$A$2:$A$801,enrollment!$O$2:$O$801),"") -> 8901234567 | AF52: =IFERROR(_xlfn.XLOOKUP($AE52,providers!$B$2:$B$11,providers!$Q$2:$Q$11),"") -> 3.7 | AG52: =EOMONTH(E52,-1)+1 -> 45566
A53: CLM-000052 | B53: M-000009 | C53: 8901234567 | D53: 8901234567 | E53: 45360 | F53: 45360 | G53: 45374 | H53: Professional | I53: 11 | J53: I10 | K53: 99213 | O53: 1 | P53: 166.74 | Q53: 123.51 | R53: 98.81 | S53: 24.7 | T53: Y | X53: PLN-MKT-401 | Y53: Marketplace | Z53: PCP | AA53: =IFERROR(_xlfn.XLOOKUP($J53,avoidable_ed_reference!$A$2:$A$13,avoidable_ed_reference!$C$2:$C$13),"Not Classified") -> Not Classified | AB53: =IFERROR(_xlfn.XLOOKUP($B53,enrollment!$A$2:$A$801,enrollment!$I$2:$I$801),"") -> GA | AC53: =IFERROR(_xlfn.XLOOKUP($B53,enrollment!$A$2:$A$801,enrollment!$L$2:$L$801),"") -> 35 | AD53: {=_xlfn.IFS(AC53="","Unknown",AC53<18,"0-17",AC53<35,"18-34",AC53<50,"35-49",AC53<65,"50-64",TRUE,"65+")} -> 35-49 | AE53: =IFERROR(_xlfn.XLOOKUP($B53,enrollment!$A$2:$A$801,enrollment!$O$2:$O$801),"") -> 8901234567 | AF53: =IFERROR(_xlfn.XLOOKUP($AE53,providers!$B$2:$B$11,providers!$Q$2:$Q$11),"") -> 3.7 | AG53: =EOMONTH(E53,-1)+1 -> 45352
A54: CLM-000053 | B54: M-000010 | C54: 2233445566 | D54: 2233445566 | E54: 45320 | F54: 45320 | G54: 45348 | H54: Professional | I54: 23 | J54: I50.9 | K54: 99284 | O54: 1 | P54: 1801.82 | Q54: 1001.01 | R54: 800.81 | S54: 200.2 | T54: Y | X54: PLN-COM-250 | Y54: Commercial | Z54: ED | AA54: =IFERROR(_xlfn.XLOOKUP($J54,avoidable_ed_reference!$A$2:$A$13,avoidable_ed_reference!$C$2:$C$13),"Not Classified") -> Non-Avoidable | AB54: =IFERROR(_xlfn.XLOOKUP($B54,enrollment!$A$2:$A$801,enrollment!$I$2:$I$801),"") -> TN | AC54: =IFERROR(_xlfn.XLOOKUP($B54,enrollment!$A$2:$A$801,enrollment!$L$2:$L$801),"") -> 50 | AD54: {=_xlfn.IFS(AC54="","Unknown",AC54<18,"0-17",AC54<35,"18-34",AC54<50,"35-49",AC54<65,"50-64",TRUE,"65+")} -> 50-64 | AE54: =IFERROR(_xlfn.XLOOKUP($B54,enrollment!$A$2:$A$801,enrollment!$O$2:$O$801),"") -> 2233445566 | AF54: =IFERROR(_xlfn.XLOOKUP($AE54,providers!$B$2:$B$11,providers!$Q$2:$Q$11),"") -> 3.5 | AG54: =EOMONTH(E54,-1)+1 -> 45292
A55: CLM-000054 | B55: M-000010 | C55: 6789012345 | D55: 6789012345 | E55: 45523 | F55: 45523 | G55: 45538 | H55: Professional | I55: 23 | J55: N39.0 | K55: 99284 | O55: 1 | P55: 1935.65 | Q55: 1075.36 | R55: 860.29 | S55: 215.07 | T55: Y | X55: PLN-COM-250 | Y55: Commercial | Z55: ED | AA55: =IFERROR(_xlfn.XLOOKUP($J55,avoidable_ed_reference!$A$2:$A$13,avoidable_ed_reference!$C$2:$C$13),"Not Classified") -> Avoidable | AB55: =IFERROR(_xlfn.XLOOKUP($B55,enrollment!$A$2:$A$801,enrollment!$I$2:$I$801),"") -> TN | AC55: =IFERROR(_xlfn.XLOOKUP($B55,enrollment!$A$2:$A$801,enrollment!$L$2:$L$801),"") -> 50 | AD55: {=_xlfn.IFS(AC55="","Unknown",AC55<18,"0-17",AC55<35,"18-34",AC55<50,"35-49",AC55<65,"50-64",TRUE,"65+")} -> 50-64 | AE55: =IFERROR(_xlfn.XLOOKUP($B55,enrollment!$A$2:$A$801,enrollment!$O$2:$O$801),"") -> 2233445566 | AF55: =IFERROR(_xlfn.XLOOKUP($AE55,providers!$B$2:$B$11,providers!$Q$2:$Q$11),"") -> 3.5 | AG55: =EOMONTH(E55,-1)+1 -> 45505
A56: CLM-000055 | B56: M-000010 | C56: 3456789012 | D56: 3456789012 | E56: 45389 | F56: 45389 | G56: 45415 | H56: Professional | I56: 23 | J56: R51.9 | K56: 99284 | O56: 1 | P56: 1929.98 | Q56: 1072.21 | R56: 857.77 | S56: 214.44 | T56: Y | X56: PLN-COM-250 | Y56: Commercial | Z56: ED | AA56: =IFERROR(_xlfn.XLOOKUP($J56,avoidable_ed_reference!$A$2:$A$13,avoidable_ed_reference!$C$2:$C$13),"Not Classified") -> Potentially Avoidable | AB56: =IFERROR(_xlfn.XLOOKUP($B56,enrollment!$A$2:$A$801,enrollment!$I$2:$I$801),"") -> TN | AC56: =IFERROR(_xlfn.XLOOKUP($B56,enrollment!$A$2:$A$801,enrollment!$L$2:$L$801),"") -> 50 | AD56: {=_xlfn.IFS(AC56="","Unknown",AC56<18,"0-17",AC56<35,"18-34",AC56<50,"35-49",AC56<65,"50-64",TRUE,"65+")} -> 50-64 | AE56: =IFERROR(_xlfn.XLOOKUP($B56,enrollment!$A$2:$A$801,enrollment!$O$2:$O$801),"") -> 2233445566 | AF56: =IFERROR(_xlfn.XLOOKUP($AE56,providers!$B$2:$B$11,providers!$Q$2:$Q$11),"") -> 3.5 | AG56: =EOMONTH(E56,-1)+1 -> 45383
A57: CLM-000056 | B57: M-000010 | C57: 7890123456 | D57: 7890123456 | E57: 45323 | F57: 45323 | G57: 45358 | H57: Professional | I57: 23 | J57: J18.9 | K57: 99284 | O57: 1 | P57: 1896.41 | Q57: 1053.56 | R57: 842.85 | S57: 210.71 | T57: Y | X57: PLN-COM-250 | Y57: Commercial | Z57: ED | AA57: =IFERROR(_xlfn.XLOOKUP($J57,avoidable_ed_reference!$A$2:$A$13,avoidable_ed_reference!$C$2:$C$13),"Not Classified") -> Non-Avoidable | AB57: =IFERROR(_xlfn.XLOOKUP($B57,enrollment!$A$2:$A$801,enrollment!$I$2:$I$801),"") -> TN | AC57: =IFERROR(_xlfn.XLOOKUP($B57,enrollment!$A$2:$A$801,enrollment!$L$2:$L$801),"") -> 50 | AD57: {=_xlfn.IFS(AC57="","Unknown",AC57<18,"0-17",AC57<35,"18-34",AC57<50,"35-49",AC57<65,"50-64",TRUE,"65+")} -> 50-64 | AE57: =IFERROR(_xlfn.XLOOKUP($B57,enrollment!$A$2:$A$801,enrollment!$O$2:$O$801),"") -> 2233445566 | AF57: =IFERROR(_xlfn.XLOOKUP($AE57,providers!$B$2:$B$11,providers!$Q$2:$Q$11),"") -> 3.5 | AG57: =EOMONTH(E57,-1)+1 -> 45323
A58: CLM-000057 | B58: M-000010 | C58: 2233445566 | D58: 2233445566 | E58: 45560 | F58: 45560 | G58: 45579 | H58: Professional | I58: 11 | J58: J06.9 | K58: 99213 | O58: 1 | P58: 207.16 | Q58: 153.45 | R58: 122.76 | S58: 30.69 | T58: Y | X58: PLN-COM-250 | Y58: Commercial | Z58: PCP | AA58: =IFERROR(_xlfn.XLOOKUP($J58,avoidable_ed_reference!$A$2:$A$13,avoidable_ed_reference!$C$2:$C$13),"Not Classified") -> Avoidable | AB58: =IFERROR(_xlfn.XLOOKUP($B58,enrollment!$A$2:$A$801,enrollment!$I$2:$I$801),"") -> TN | AC58: =IFERROR(_xlfn.XLOOKUP($B58,enrollment!$A$2:$A$801,enrollment!$L$2:$L$801),"") -> 50 | AD58: {=_xlfn.IFS(AC58="","Unknown",AC58<18,"0-17",AC58<35,"18-34",AC58<50,"35-49",AC58<65,"50-64",TRUE,"65+")} -> 50-64 | AE58: =IFERROR(_xlfn.XLOOKUP($B58,enrollment!$A$2:$A$801,enrollment!$O$2:$O$801),"") -> 2233445566 | AF58: =IFERROR(_xlfn.XLOOKUP($AE58,providers!$B$2:$B$11,providers!$Q$2:$Q$11),"") -> 3.5 | AG58: =EOMONTH(E58,-1)+1 -> 45536
A59: CLM-000058 | B59: M-000010 | C59: 2233445566 | D59: 2233445566 | E59: 45387 | F59: 45387 | G59: 45416 | H59: Professional | I59: 11 | J59: J06.9 | K59: 99213 | O59: 1 | P59: 220.28 | Q59: 163.17 | R59: 130.54 | S59: 32.63 | T59: Y | X59: PLN-COM-250 | Y59: Commercial | Z59: PCP | AA59: =IFERROR(_xlfn.XLOOKUP($J59,avoidable_ed_reference!$A$2:$A$13,avoidable_ed_reference!$C$2:$C$13),"Not Classified") -> Avoidable | AB59: =IFERROR(_xlfn.XLOOKUP($B59,enrollment!$A$2:$A$801,enrollment!$I$2:$I$801),"") -> TN | AC59: =IFERROR(_xlfn.XLOOKUP($B59,enrollment!$A$2:$A$801,enrollment!$L$2:$L$801),"") -> 50 | AD59: {=_xlfn.IFS(AC59="","Unknown",AC59<18,"0-17",AC59<35,"18-34",AC59<50,"35-49",AC59<65,"50-64",TRUE,"65+")} -> 50-64 | AE59: =IFERROR(_xlfn.XLOOKUP($B59,enrollment!$A$2:$A$801,enrollment!$O$2:$O$801),"") -> 2233445566 | AF59: =IFERROR(_xlfn.XLOOKUP($AE59,providers!$B$2:$B$11,providers!$Q$2:$Q$11),"") -> 3.5 | AG59: =EOMONTH(E59,-1)+1 -> 45383
A60: CLM-000059 | B60: M-000010 | C60: 9012345678 | D60: 9012345678 | E60: 45641 | F60: 45641 | G60: 45673 | H60: Professional | I60: 23 | J60: R51.9 | K60: 99284 | O60: 1 | P60: 1656.94 | Q60: 920.52 | R60: 736.42 | S60: 184.1 | T60: Y | X60: PLN-COM-250 | Y60: Commercial | Z60: ED | AA60: =IFERROR(_xlfn.XLOOKUP($J60,avoidable_ed_reference!$A$2:$A$13,avoidable_ed_reference!$C$2:$C$13),"Not Classified") -> Potentially Avoidable | AB60: =IFERROR(_xlfn.XLOOKUP($B60,enrollment!$A$2:$A$801,enrollment!$I$2:$I$801),"") -> TN | AC60: =IFERROR(_xlfn.XLOOKUP($B60,enrollment!$A$2:$A$801,enrollment!$L$2:$L$801),"") -> 50 | AD60: {=_xlfn.IFS(AC60="","Unknown",AC60<18,"0-17",AC60<35,"18-34",AC60<50,"35-49",AC60<65,"50-64",TRUE,"65+")} -> 50-64 | AE60: =IFERROR(_xlfn.XLOOKUP($B60,enrollment!$A$2:$A$801,enrollment!$O$2:$O$801),"") -> 2233445566 | AF60: =IFERROR(_xlfn.XLOOKUP($AE60,providers!$B$2:$B$11,providers!$Q$2:$Q$11),"") -> 3.5 | AG60: =EOMONTH(E60,-1)+1 -> 45627
A61: CLM-000060 | B61: M-000010 | C61: 8901234567 | D61: 8901234567 | E61: 45435 | F61: 45435 | G61: 45460 | H61: Professional | I61: 23 | J61: I50.9 | K61: 99284 | O61: 1 | P61: 2123.15 | Q61: 1179.53 | R61: 943.62 | S61: 235.91 | T61: Y | X61: PLN-COM-250 | Y61: Commercial | Z61: ED | AA61: =IFERROR(_xlfn.XLOOKUP($J61,avoidable_ed_reference!$A$2:$A$13,avoidable_ed_reference!$C$2:$C$13),"Not Classified") -> Non-Avoidable | AB61: =IFERROR(_xlfn.XLOOKUP($B61,enrollment!$A$2:$A$801,enrollment!$I$2:$I$801),"") -> TN | AC61: =IFERROR(_xlfn.XLOOKUP($B61,enrollment!$A$2:$A$801,enrollment!$L$2:$L$801),"") -> 50 | AD61: {=_xlfn.IFS(AC61="","Unknown",AC61<18,"0-17",AC61<35,"18-34",AC61<50,"35-49",AC61<65,"50-64",TRUE,"65+")} -> 50-64 | AE61: =IFERROR(_xlfn.XLOOKUP($B61,enrollment!$A$2:$A$801,enrollment!$O$2:$O$801),"") -> 2233445566 | AF61: =IFERROR(_xlfn.XLOOKUP($AE61,providers!$B$2:$B$11,providers!$Q$2:$Q$11),"") -> 3.5 | AG61: =EOMONTH(E61,-1)+1 -> 45413
A62: CLM-000061 | B62: M-000010 | C62: 7890123456 | D62: 7890123456 | E62: 45299 | F62: 45299 | G62: 45319 | H62: Professional | I62: 23 | J62: M54.5 | K62: 99284 | O62: 1 | P62: 2446.33 | Q62: 1359.07 | R62: 1087.26 | S62: 271.81 | T62: Y | X62: PLN-COM-250 | Y62: Commercial | Z62: ED | AA62: =IFERROR(_xlfn.XLOOKUP($J62,avoidable_ed_reference!$A$2:$A$13,avoidable_ed_reference!$C$2:$C$13),"Not Classified") -> Avoidable | AB62: =IFERROR(_xlfn.XLOOKUP($B62,enrollment!$A$2:$A$801,enrollment!$I$2:$I$801),"") -> TN | AC62: =IFERROR(_xlfn.XLOOKUP($B62,enrollment!$A$2:$A$801,enrollment!$L$2:$L$801),"") -> 50 | AD62: {=_xlfn.IFS(AC62="","Unknown",AC62<18,"0-17",AC62<35,"18-34",AC62<50,"35-49",AC62<65,"50-64",TRUE,"65+")} -> 50-64 | AE62: =IFERROR(_xlfn.XLOOKUP($B62,enrollment!$A$2:$A$801,enrollment!$O$2:$O$801),"") -> 2233445566 | AF62: =IFERROR(_xlfn.XLOOKUP($AE62,providers!$B$2:$B$11,providers!$Q$2:$Q$11),"") -> 3.5 | AG62: =EOMONTH(E62,-1)+1 -> 45292
... A72: CLM-000071 | B72: M-000012 | C72: 5678901234 | D72: 5678901234 | E72: 45544 | F72: 45544 | G72: 45571 | H72: Professional | I72: 20 | J72: J06.9 | K72: 99213 | O72: 1 | P72: 143.29 | Q72: 110.22 | R72: 88.18 | S72: 22.04 | T72: Y | X72: PLN-MA-100 | Y72: Medicare Advantage | Z72: Urgent Care | AA72: =IFERROR(_xlfn.XLOOKUP($J72,avoidable_ed_reference!$A$2:$A$13,avoidable_ed_reference!$C$2:$C$13),"Not Classified") -> Avoidable | AB72: =IFERROR(_xlfn.XLOOKUP($B72,enrollment!$A$2:$A$801,enrollment!$I$2:$I$801),"") -> KY | AC72: =IFERROR(_xlfn.XLOOKUP($B72,enrollment!$A$2:$A$801,enrollment!$L$2:$L$801),"") -> 74 | AD72: {=_xlfn.IFS(AC72="","Unknown",AC72<18,"0-17",AC72<35,"18-34",AC72<50,"35-49",AC72<65,"50-64",TRUE,"65+")} -> 65+ | AE72: =IFERROR(_xlfn.XLOOKUP($B72,enrollment!$A$2:$A$801,enrollment!$O$2:$O$801),"") -> 3456789012 | AF72: =IFERROR(_xlfn.XLOOKUP($AE72,providers!$B$2:$B$11,providers!$Q$2:$Q$11),"") -> 4 | AG72: =EOMONTH(E72,-1)+1 -> 45536
A73: CLM-000072 | B73: M-000012 | C73: 3456789012 | D73: 3456789012 | E73: 45567 | F73: 45567 | G73: 45593 | H73: Pharmacy | J73: C34.90 | L73: 00169430730 | M73: Semaglutide | N73: GLP-1 Agonist | O73: 1 | P73: 1215.39 | Q73: 1104.9 | R73: 883.92 | S73: 220.98 | T73: Y | X73: PLN-MA-100 | Y73: Medicare Advantage | Z73: Specialty Rx | AA73: =IFERROR(_xlfn.XLOOKUP($J73,avoidable_ed_reference!$A$2:$A$13,avoidable_ed_reference!$C$2:$C$13),"Not Classified") -> Not Classified | AB73: =IFERROR(_xlfn.XLOOKUP($B73,enrollment!$A$2:$A$801,enrollment!$I$2:$I$801),"") -> KY | AC73: =IFERROR(_xlfn.XLOOKUP($B73,enrollment!$A$2:$A$801,enrollment!$L$2:$L$801),"") -> 74 | AD73: {=_xlfn.IFS(AC73="","Unknown",AC73<18,"0-17",AC73<35,"18-34",AC73<50,"35-49",AC73<65,"50-64",TRUE,"65+")} -> 65+ | AE73: =IFERROR(_xlfn.XLOOKUP($B73,enrollment!$A$2:$A$801,enrollment!$O$2:$O$801),"") -> 3456789012 | AF73: =IFERROR(_xlfn.XLOOKUP($AE73,providers!$B$2:$B$11,providers!$Q$2:$Q$11),"") -> 4 | AG73: =EOMONTH(E73,-1)+1 -> 45566
A74: CLM-000073 | B74: M-000012 | C74: 3456789012 | D74: 3456789012 | E74: 45652 | F74: 45652 | G74: 45673 | H74: Professional | I74: 11 | J74: I10 | K74: 99213 | O74: 1 | P74: 217.22 | Q74: 160.9 | R74: 128.72 | S74: 32.18 | T74: Y | X74: PLN-MA-100 | Y74: Medicare Advantage | Z74: PCP | AA74: =IFERROR(_xlfn.XLOOKUP($J74,avoidable_ed_reference!$A$2:$A$13,avoidable_ed_reference!$C$2:$C$13),"Not Classified") -> Not Classified | AB74: =IFERROR(_xlfn.XLOOKUP($B74,enrollment!$A$2:$A$801,enrollment!$I$2:$I$801),"") -> KY | AC74: =IFERROR(_xlfn.XLOOKUP($B74,enrollment!$A$2:$A$801,enrollment!$L$2:$L$801),"") -> 74 | AD74: {=_xlfn.IFS(AC74="","Unknown",AC74<18,"0-17",AC74<35,"18-34",AC74<50,"35-49",AC74<65,"50-64",TRUE,"65+")} -> 65+ | AE74: =IFERROR(_xlfn.XLOOKUP($B74,enrollment!$A$2:$A$801,enrollment!$O$2:$O$801),"") -> 3456789012 | AF74: =IFERROR(_xlfn.XLOOKUP($AE74,providers!$B$2:$B$11,providers!$Q$2:$Q$11),"") -> 4 | AG74: =EOMONTH(E74,-1)+1 -> 45627
A75: CLM-000074 | B75: M-000012 | C75: 7890123456 | D75: 7890123456 | E75: 45577 | F75: 45577 | G75: 45607 | H75: Professional | I75: 23 | J75: N39.0 | K75: 99284 | O75: 1 | P75: 1946.63 | Q75: 1081.46 | R75: 865.17 | S75: 216.29 | T75: Y | X75: PLN-MA-100 | Y75: Medicare Advantage | Z75: ED | AA75: =IFERROR(_xlfn.XLOOKUP($J75,avoidable_ed_reference!$A$2:$A$13,avoidable_ed_reference!$C$2:$C$13),"Not Classified") -> Avoidable | AB75: =IFERROR(_xlfn.XLOOKUP($B75,enrollment!$A$2:$A$801,enrollment!$I$2:$I$801),"") -> KY | AC75: =IFERROR(_xlfn.XLOOKUP($B75,enrollment!$A$2:$A$801,enrollment!$L$2:$L$801),"") -> 74 | AD75: {=_xlfn.IFS(AC75="","Unknown",AC75<18,"0-17",AC75<35,"18-34",AC75<50,"35-49",AC75<65,"50-64",TRUE,"65+")} -> 65+ | AE75: =IFERROR(_xlfn.XLOOKUP($B75,enrollment!$A$2:$A$801,enrollment!$O$2:$O$801),"") -> 3456789012 | AF75: =IFERROR(_xlfn.XLOOKUP($AE75,providers!$B$2:$B$11,providers!$Q$2:$Q$11),"") -> 4 | AG75: =EOMONTH(E75,-1)+1 -> 45566
A76: CLM-000075 | B76: M-000012 | C76: 3456789012 | D76: 3456789012 | E76: 45572 | F76: 45572 | G76: 45602 | H76: Institutional | I76: 21 | J76: J18.9 | K76: 99223 | O76: 1 | P76: 32908.39 | Q76: 21231.22 | R76: 16984.98 | S76: 4246.24 | T76: Y | V76: 1 | W76: 01 | X76: PLN-MA-100 | Y76: Medicare Advantage | Z76: Inpatient | AA76: =IFERROR(_xlfn.XLOOKUP($J76,avoidable_ed_reference!$A$2:$A$13,avoidable_ed_reference!$C$2:$C$13),"Not Classified") -> Non-Avoidable | AB76: =IFERROR(_xlfn.XLOOKUP($B76,enrollment!$A$2:$A$801,enrollment!$I$2:$I$801),"") -> KY | AC76: =IFERROR(_xlfn.XLOOKUP($B76,enrollment!$A$2:$A$801,enrollment!$L$2:$L$801),"") -> 74 | AD76: {=_xlfn.IFS(AC76="","Unknown",AC76<18,"0-17",AC76<35,"18-34",AC76<50,"35-49",AC76<65,"50-64",TRUE,"65+")} -> 65+ | AE76: =IFERROR(_xlfn.XLOOKUP($B76,enrollment!$A$2:$A$801,enrollment!$O$2:$O$801),"") -> 3456789012 | AF76: =IFERROR(_xlfn.XLOOKUP($AE76,providers!$B$2:$B$11,providers!$Q$2:$Q$11),"") -> 4 | AG76: =EOMONTH(E76,-1)+1 -> 45566
A77: CLM-000076 | B77: M-000013 | C77: 7890123456 | D77: 7890123456 | E77: 45437 | F77: 45437 | G77: 45455 | H77: Professional | I77: 11 | J77: J06.9 | K77: 99213 | O77: 1 | P77: 166.04 | Q77: 122.99 | R77: 98.39 | S77: 24.6 | T77: Y | X77: PLN-MKT-401 | Y77: Marketplace | Z77: PCP | AA77: =IFERROR(_xlfn.XLOOKUP($J77,avoidable_ed_reference!$A$2:$A$13,avoidable_ed_reference!$C$2:$C$13),"Not Classified") -> Avoidable | AB77: =IFERROR(_xlfn.XLOOKUP($B77,enrollment!$A$2:$A$801,enrollment!$I$2:$I$801),"") -> TN | AC77: =IFERROR(_xlfn.XLOOKUP($B77,enrollment!$A$2:$A$801,enrollment!$L$2:$L$801),"") -> 54 | AD77: {=_xlfn.IFS(AC77="","Unknown",AC77<18,"0-17",AC77<35,"18-34",AC77<50,"35-49",AC77<65,"50-64",TRUE,"65+")} -> 50-64 | AE77: =IFERROR(_xlfn.XLOOKUP($B77,enrollment!$A$2:$A$801,enrollment!$O$2:$O$801),"") -> 7890123456 | AF77: =IFERROR(_xlfn.XLOOKUP($AE77,providers!$B$2:$B$11,providers!$Q$2:$Q$11),"") -> 3.9 | AG77: =EOMONTH(E77,-1)+1 -> 45413
A78: CLM-000077 | B78: M-000013 | C78: 3456789012 | D78: 3456789012 | E78: 45603 | F78: 45603 | G78: 45620 | H78: Pharmacy | J78: C34.90 | L78: 00169430730 | M78: Semaglutide | N78: GLP-1 Agonist | O78: 1 | P78: 967.76 | Q78: 879.78 | R78: 703.82 | S78: 175.96 | T78: Y | X78: PLN-MKT-401 | Y78: Marketplace | Z78: Specialty Rx | AA78: =IFERROR(_xlfn.XLOOKUP($J78,avoidable_ed_reference!$A$2:$A$13,avoidable_ed_reference!$C$2:$C$13),"Not Classified") -> Not Classified | AB78: =IFERROR(_xlfn.XLOOKUP($B78,enrollment!$A$2:$A$801,enrollment!$I$2:$I$801),"") -> TN | AC78: =IFERROR(_xlfn.XLOOKUP($B78,enrollment!$A$2:$A$801,enrollment!$L$2:$L$801),"") -> 54 | AD78: {=_xlfn.IFS(AC78="","Unknown",AC78<18,"0-17",AC78<35,"18-34",AC78<50,"35-49",AC78<65,"50-64",TRUE,"65+")} -> 50-64 | AE78: =IFERROR(_xlfn.XLOOKUP($B78,enrollment!$A$2:$A$801,enrollment!$O$2:$O$801),"") -> 7890123456 | AF78: =IFERROR(_xlfn.XLOOKUP($AE78,providers!$B$2:$B$11,providers!$Q$2:$Q$11),"") -> 3.9 | AG78: =EOMONTH(E78,-1)+1 -> 45597
A79: CLM-000078 | B79: M-000013 | C79: 9012345678 | D79: 9012345678 | E79: 45578 | F79: 45578 | G79: 45607 | H79: Professional | I79: 22 | J79: F32.9 | K79: 90837 | O79: 1 | P79: 204.5 | Q79: 151.48 | R79: 121.18 | S79: 30.3 | T79: Y | X79: PLN-MKT-401 | Y79: Marketplace | Z79: Behavioral Health | AA79: =IFERROR(_xlfn.XLOOKUP($J79,avoidable_ed_reference!$A$2:$A$13,avoidable_ed_reference!$C$2:$C$13),"Not Classified") -> Potentially Avoidable | AB79: =IFERROR(_xlfn.XLOOKUP($B79,enrollment!$A$2:$A$801,enrollment!$I$2:$I$801),"") -> TN | AC79: =IFERROR(_xlfn.XLOOKUP($B79,enrollment!$A$2:$A$801,enrollment!$L$2:$L$801),"") -> 54 | AD79: {=_xlfn.IFS(AC79="","Unknown",AC79<18,"0-17",AC79<35,"18-34",AC79<50,"35-49",AC79<65,"50-64",TRUE,"65+")} -> 50-64 | AE79: =IFERROR(_xlfn.XLOOKUP($B79,enrollment!$A$2:$A$801,enrollment!$O$2:$O$801),"") -> 7890123456 | AF79: =IFERROR(_xlfn.XLOOKUP($AE79,providers!$B$2:$B$11,providers!$Q$2:$Q$11),"") -> 3.9 | AG79: =EOMONTH(E79,-1)+1 -> 45566
A80: CLM-000079 | B80: M-000013 | C80: 8901234567 | D80: 8901234567 | E80: 45384 | F80: 45384 | G80: 45410 | H80: Pharmacy | J80: Z79.4 | L80: 00378180510 | M80: Insulin Glargine | N80: Diabetes | O80: 1 | P80: 949.28 | Q80: 862.98 | R80: 690.38 | S80: 172.6 | T80: Y | X80: PLN-MKT-401 | Y80: Marketplace | Z80: Specialty Rx | AA80: =IFERROR(_xlfn.XLOOKUP($J80,avoidable_ed_reference!$A$2:$A$13,avoidable_ed_reference!$C$2:$C$13),"Not Classified") -> Not Classified | AB80: =IFERROR(_xlfn.XLOOKUP($B80,enrollment!$A$2:$A$801,enrollment!$I$2:$I$801),"") -> TN | AC80: =IFERROR(_xlfn.XLOOKUP($B80,enrollment!$A$2:$A$801,enrollment!$L$2:$L$801),"") -> 54 | AD80: {=_xlfn.IFS(AC80="","Unknown",AC80<18,"0-17",AC80<35,"18-34",AC80<50,"35-49",AC80<65,"50-64",TRUE,"65+")} -> 50-64 | AE80: =IFERROR(_xlfn.XLOOKUP($B80,enrollment!$A$2:$A$801,enrollment!$O$2:$O$801),"") -> 7890123456 | AF80: =IFERROR(_xlfn.XLOOKUP($AE80,providers!$B$2:$B$11,providers!$Q$2:$Q$11),"") -> 3.9 | AG80: =EOMONTH(E80,-1)+1 -> 45383
A81: CLM-000080 | B81: M-000013 | C81: 7890123456 | D81: 7890123456 | E81: 45513 | F81: 45513 | G81: 45529 | H81: Professional | I81: 11 | J81: J06.9 | K81: 99213 | O81: 1 | P81: 229.85 | Q81: 170.26 | R81: 136.21 | S81: 34.05 | T81: Y | X81: PLN-MKT-401 | Y81: Marketplace | Z81: PCP | AA81: =IFERROR(_xlfn.XLOOKUP($J81,avoidable_ed_reference!$A$2:$A$13,avoidable_ed_reference!$C$2:$C$13),"Not Classified") -> Avoidable | AB81: =IFERROR(_xlfn.XLOOKUP($B81,enrollment!$A$2:$A$801,enrollment!$I$2:$I$801),"") -> TN | AC81: =IFERROR(_xlfn.XLOOKUP($B81,enrollment!$A$2:$A$801,enrollment!$L$2:$L$801),"") -> 54 | AD81: {=_xlfn.IFS(AC81="","Unknown",AC81<18,"0-17",AC81<35,"18-34",AC81<50,"35-49",AC81<65,"50-64",TRUE,"65+")} -> 50-64 | AE81: =IFERROR(_xlfn.XLOOKUP($B81,enrollment!$A$2:$A$801,enrollment!$O$2:$O$801),"") -> 7890123456 | AF81: =IFERROR(_xlfn.XLOOKUP($AE81,providers!$B$2:$B$11,providers!$Q$2:$Q$11),"") -> 3.9 | AG81: =EOMONTH(E81,-1)+1 -> 45505
A82: CLM-000081 | B82: M-000013 | C82: 2233445566 | D82: 2233445566 | E82: 45656 | F82: 45656 | G82: 45679 | H82: Professional | I82: 23 | J82: K21.9 | K82: 99284 | O82: 1 | P82: 2294.08 | Q82: 1274.49 | R82: 1019.59 | S82: 254.9 | T82: Y | X82: PLN-MKT-401 | Y82: Marketplace | Z82: ED | AA82: =IFERROR(_xlfn.XLOOKUP($J82,avoidable_ed_reference!$A$2:$A$13,avoidable_ed_reference!$C$2:$C$13),"Not Classified") -> Avoidable | AB82: =IFERROR(_xlfn.XLOOKUP($B82,enrollment!$A$2:$A$801,enrollment!$I$2:$I$801),"") -> TN | AC82: =IFERROR(_xlfn.XLOOKUP($B82,enrollment!$A$2:$A$801,enrollment!$L$2:$L$801),"") -> 54 | AD82: {=_xlfn.IFS(AC82="","Unknown",AC82<18,"0-17",AC82<35,"18-34",AC82<50,"35-49",AC82<65,"50-64",TRUE,"65+")} -> 50-64 | AE82: =IFERROR(_xlfn.XLOOKUP($B82,enrollment!$A$2:$A$801,enrollment!$O$2:$O$801),"") -> 7890123456 | AF82: =IFERROR(_xlfn.XLOOKUP($AE82,providers!$B$2:$B$11,providers!$Q$2:$Q$11),"") -> 3.9 | AG82: =EOMONTH(E82,-1)+1 -> 45627
A83: CLM-000082 | B83: M-000014 | C83: 3456789012 | D83: 3456789012 | E83: 45458 | F83: 45458 | G83: 45484 | H83: Institutional | I83: 21 | J83: C34.90 | K83: 99223 | O83: 1 | P83: 30518.24 | Q83: 19689.19 | R83: 15751.35 | S83: 3937.84 | T83: Y | V83: 1 | W83: 01 | X83: PLN-COM-250 | Y83: Commercial | Z83: Inpatient | AA83: =IFERROR(_xlfn.XLOOKUP($J83,avoidable_ed_reference!$A$2:$A$13,avoidable_ed_reference!$C$2:$C$13),"Not Classified") -> Not Classified | AB83: =IFERROR(_xlfn.XLOOKUP($B83,enrollment!$A$2:$A$801,enrollment!$I$2:$I$801),"") -> KY | AC83: =IFERROR(_xlfn.XLOOKUP($B83,enrollment!$A$2:$A$801,enrollment!$L$2:$L$801),"") -> 75 | AD83: {=_xlfn.IFS(AC83="","Unknown",AC83<18,"0-17",AC83<35,"18-34",AC83<50,"35-49",AC83<65,"50-64",TRUE,"65+")} -> 65+ | AE83: =IFERROR(_xlfn.XLOOKUP($B83,enrollment!$A$2:$A$801,enrollment!$O$2:$O$801),"") -> 3456789012 | AF83: =IFERROR(_xlfn.XLOOKUP($AE83,providers!$B$2:$B$11,providers!$Q$2:$Q$11),"") -> 4 | AG83: =EOMONTH(E83,-1)+1 -> 45444
A84: CLM-000083 | B84: M-000014 | C84: 3456789012 | D84: 3456789012 | E84: 45491 | F84: 45491 | G84: 45519 | H84: Professional | I84: 11 | J84: I10 | K84: 99213 | O84: 1 | P84: 172.81 | Q84: 128.01 | R84: 102.41 | S84: 25.6 | T84: Y | X84: PLN-COM-250 | Y84: Commercial | Z84: PCP | AA84: =IFERROR(_xlfn.XLOOKUP($J84,avoidable_ed_reference!$A$2:$A$13,avoidable_ed_reference!$C$2:$C$13),"Not Classified") -> Not Classified | AB84: =IFERROR(_xlfn.XLOOKUP($B84,enrollment!$A$2:$A$801,enrollment!$I$2:$I$801),"") -> KY | AC84: =IFERROR(_xlfn.XLOOKUP($B84,enrollment!$A$2:$A$801,enrollment!$L$2:$L$801),"") -> 75 | AD84: {=_xlfn.IFS(AC84="","Unknown",AC84<18,"0-17",AC84<35,"18-34",AC84<50,"35-49",AC84<65,"50-64",TRUE,"65+")} -> 65+ | AE84: =IFERROR(_xlfn.XLOOKUP($B84,enrollment!$A$2:$A$801,enrollment!$O$2:$O$801),"") -> 3456789012 | AF84: =IFERROR(_xlfn.XLOOKUP($AE84,providers!$B$2:$B$11,providers!$Q$2:$Q$11),"") -> 4 | AG84: =EOMONTH(E84,-1)+1 -> 45474
A85: CLM-000084 | B85: M-000014 | C85: 9012345678 | D85: 9012345678 | E85: 45299 | F85: 45299 | G85: 45314 | H85: Institutional | I85: 21 | J85: C34.90 | K85: 99223 | O85: 1 | P85: 34016.05 | Q85: 21945.84 | R85: 17556.67 | S85: 4389.17 | T85: Y | V85: 1 | W85: 01 | X85: PLN-COM-250 | Y85: Commercial | Z85: Inpatient | AA85: =IFERROR(_xlfn.XLOOKUP($J85,avoidable_ed_reference!$A$2:$A$13,avoidable_ed_reference!$C$2:$C$13),"Not Classified") -> Not Classified | AB85: =IFERROR(_xlfn.XLOOKUP($B85,enrollment!$A$2:$A$801,enrollment!$I$2:$I$801),"") -> KY | AC85: =IFERROR(_xlfn.XLOOKUP($B85,enrollment!$A$2:$A$801,enrollment!$L$2:$L$801),"") -> 75 | AD85: {=_xlfn.IFS(AC85="","Unknown",AC85<18,"0-17",AC85<35,"18-34",AC85<50,"35-49",AC85<65,"50-64",TRUE,"65+")} -> 65+ | AE85: =IFERROR(_xlfn.XLOOKUP($B85,enrollment!$A$2:$A$801,enrollment!$O$2:$O$801),"") -> 3456789012 | AF85: =IFERROR(_xlfn.XLOOKUP($AE85,providers!$B$2:$B$11,providers!$Q$2:$Q$11),"") -> 4 | AG85: =EOMONTH(E85,-1)+1 -> 45292
A86: CLM-000085 | B86: M-000014 | C86: 9012345678 | D86: 9012345678 | E86: 45379 | F86: 45379 | G86: 45402 | H86: Pharmacy | J86: E11.9 | L86: 00078063941 | M86: Pembrolizumab | N86: Oncology Biologic | O86: 1 | P86: 822.37 | Q86: 747.61 | R86: 598.09 | S86: 149.52 | T86: Y | X86: PLN-COM-250 | Y86: Commercial | Z86: Specialty Rx | AA86: =IFERROR(_xlfn.XLOOKUP($J86,avoidable_ed_reference!$A$2:$A$13,avoidable_ed_reference!$C$2:$C$13),"Not Classified") -> Not Classified | AB86: =IFERROR(_xlfn.XLOOKUP($B86,enrollment!$A$2:$A$801,enrollment!$I$2:$I$801),"") -> KY | AC86: =IFERROR(_xlfn.XLOOKUP($B86,enrollment!$A$2:$A$801,enrollment!$L$2:$L$801),"") -> 75 | AD86: {=_xlfn.IFS(AC86="","Unknown",AC86<18,"0-17",AC86<35,"18-34",AC86<50,"35-49",AC86<65,"50-64",TRUE,"65+")} -> 65+ | AE86: =IFERROR(_xlfn.XLOOKUP($B86,enrollment!$A$2:$A$801,enrollment!$O$2:$O$801),"") -> 3456789012 | AF86: =IFERROR(_xlfn.XLOOKUP($AE86,providers!$B$2:$B$11,providers!$Q$2:$Q$11),"") -> 4 | AG86: =EOMONTH(E86,-1)+1 -> 45352
A87: CLM-000086 | B87: M-000015 | C87: 5678901234 | D87: 5678901234 | E87: 45311 | F87: 45311 | G87: 45345 | H87: Professional | I87: 20 | J87: J06.9 | K87: 99213 | O87: 1 | P87: 158.38 | Q87: 121.83 | R87: 97.46 | S87: 24.37 | T87: Y | X87: PLN-MKT-400 | Y87: Marketplace | Z87: Urgent Care | AA87: =IFERROR(_xlfn.XLOOKUP($J87,avoidable_ed_reference!$A$2:$A$13,avoidable_ed_reference!$C$2:$C$13),"Not Classified") -> Avoidable | AB87: =IFERROR(_xlfn.XLOOKUP($B87,enrollment!$A$2:$A$801,enrollment!$I$2:$I$801),"") -> TN | AC87: =IFERROR(_xlfn.XLOOKUP($B87,enrollment!$A$2:$A$801,enrollment!$L$2:$L$801),"") -> 42 | AD87: {=_xlfn.IFS(AC87="","Unknown",AC87<18,"0-17",AC87<35,"18-34",AC87<50,"35-49",AC87<65,"50-64",TRUE,"65+")} -> 35-49 | AE87: =IFERROR(_xlfn.XLOOKUP($B87,enrollment!$A$2:$A$801,enrollment!$O$2:$O$801),"") -> 5678901234 | AF87: =IFERROR(_xlfn.XLOOKUP($AE87,providers!$B$2:$B$11,providers!$Q$2:$Q$11),"") -> 3.8 | AG87: =EOMONTH(E87,-1)+1 -> 45292
A88: CLM-000087 | B88: M-000015 | C88: 5678901234 | D88: 5678901234 | E88: 45368 | F88: 45368 | G88: 45395 | H88: Professional | I88: 11 | J88: I10 | K88: 99213 | O88: 1 | P88: 186.89 | Q88: 138.44 | R88: 110.75 | S88: 27.69 | T88: Y | X88: PLN-MKT-400 | Y88: Marketplace | Z88: PCP | AA88: =IFERROR(_xlfn.XLOOKUP($J88,avoidable_ed_reference!$A$2:$A$13,avoidable_ed_reference!$C$2:$C$13),"Not Classified") -> Not Classified | AB88: =IFERROR(_xlfn.XLOOKUP($B88,enrollment!$A$2:$A$801,enrollment!$I$2:$I$801),"") -> TN | AC88: =IFERROR(_xlfn.XLOOKUP($B88,enrollment!$A$2:$A$801,enrollment!$L$2:$L$801),"") -> 42 | AD88: {=_xlfn.IFS(AC88="","Unknown",AC88<18,"0-17",AC88<35,"18-34",AC88<50,"35-49",AC88<65,"50-64",TRUE,"65+")} -> 35-49 | AE88: =IFERROR(_xlfn.XLOOKUP($B88,enrollment!$A$2:$A$801,enrollment!$O$2:$O$801),"") -> 5678901234 | AF88: =IFERROR(_xlfn.XLOOKUP($AE88,providers!$B$2:$B$11,providers!$Q$2:$Q$11),"") -> 3.8 | AG88: =EOMONTH(E88,-1)+1 -> 45352
A89: CLM-000088 | B89: M-000015 | C89: 6789012345 | D89: 6789012345 | E89: 45550 | F89: 45550 | G89: 45580 | H89: Professional | I89: 22 | J89: F32.9 | K89: 90837 | O89: 1 | P89: 236.05 | Q89: 174.85 | R89: 139.88 | S89: 34.97 | T89: Y | X89: PLN-MKT-400 | Y89: Marketplace | Z89: Behavioral Health | AA89: =IFERROR(_xlfn.XLOOKUP($J89,avoidable_ed_reference!$A$2:$A$13,avoidable_ed_reference!$C$2:$C$13),"Not Classified") -> Potentially Avoidable | AB89: =IFERROR(_xlfn.XLOOKUP($B89,enrollment!$A$2:$A$801,enrollment!$I$2:$I$801),"") -> TN | AC89: =IFERROR(_xlfn.XLOOKUP($B89,enrollment!$A$2:$A$801,enrollment!$L$2:$L$801),"") -> 42 | AD89: {=_xlfn.IFS(AC89="","Unknown",AC89<18,"0-17",AC89<35,"18-34",AC89<50,"35-49",AC89<65,"50-64",TRUE,"65+")} -> 35-49 | AE89: =IFERROR(_xlfn.XLOOKUP($B89,enrollment!$A$2:$A$801,enrollment!$O$2:$O$801),"") -> 5678901234 | AF89: =IFERROR(_xlfn.XLOOKUP($AE89,providers!$B$2:$B$11,providers!$Q$2:$Q$11),"") -> 3.8 | AG89: =EOMONTH(E89,-1)+1 -> 45536
A90: CLM-000089 | B90: M-000015 | C90: 7890123456 | D90: 7890123456 | E90: 45317 | F90: 45317 | G90: 45342 | H90: Pharmacy | J90: Z79.4 | L90: 00378180510 | M90: Insulin Glargine | N90: Diabetes | O90: 1 | P90: 1000.76 | Q90: 909.78 | R90: 727.82 | S90: 181.96 | T90: Y | X90: PLN-MKT-400 | Y90: Marketplace | Z90: Specialty Rx | AA90: =IFERROR(_xlfn.XLOOKUP($J90,avoidable_ed_reference!$A$2:$A$13,avoidable_ed_reference!$C$2:$C$13),"Not Classified") -> Not Classified | AB90: =IFERROR(_xlfn.XLOOKUP($B90,enrollment!$A$2:$A$801,enrollment!$I$2:$I$801),"") -> TN | AC90: =IFERROR(_xlfn.XLOOKUP($B90,enrollment!$A$2:$A$801,enrollment!$L$2:$L$801),"") -> 42 | AD90: {=_xlfn.IFS(AC90="","Unknown",AC90<18,"0-17",AC90<35,"18-34",AC90<50,"35-49",AC90<65,"50-64",TRUE,"65+")} -> 35-49 | AE90: =IFERROR(_xlfn.XLOOKUP($B90,enrollment!$A$2:$A$801,enrollment!$O$2:$O$801),"") -> 5678901234 | AF90: =IFERROR(_xlfn.XLOOKUP($AE90,providers!$B$2:$B$11,providers!$Q$2:$Q$11),"") -> 3.8 | AG90: =EOMONTH(E90,-1)+1 -> 45292
A91: CLM-000090 | B91: M-000015 | C91: 5678901234 | D91: 5678901234 | E91: 45614 | F91: 45614 | G91: 45646 | H91: Professional | I91: 11 | J91: I10 | K91: 99213 | O91: 1 | P91: 203.35 | Q91: 150.63 | R91: 120.5 | S91: 30.13 | T91: Y | X91: PLN-MKT-400 | Y91: Marketplace | Z91: PCP | AA91: =IFERROR(_xlfn.XLOOKUP($J91,avoidable_ed_reference!$A$2:$A$13,avoidable_ed_reference!$C$2:$C$13),"Not Classified") -> Not Classified | AB91: =IFERROR(_xlfn.XLOOKUP($B91,enrollment!$A$2:$A$801,enrollment!$I$2:$I$801),"") -> TN | AC91: =IFERROR(_xlfn.XLOOKUP($B91,enrollment!$A$2:$A$801,enrollment!$L$2:$L$801),"") -> 42 | AD91: {=_xlfn.IFS(AC91="","Unknown",AC91<18,"0-17",AC91<35,"18-34",AC91<50,"35-49",AC91<65,"50-64",TRUE,"65+")} -> 35-49 | AE91: =IFERROR(_xlfn.XLOOKUP($B91,enrollment!$A$2:$A$801,enrollment!$O$2:$O$801),"") -> 5678901234 | AF91: =IFERROR(_xlfn.XLOOKUP($AE91,providers!$B$2:$B$11,providers!$Q$2:$Q$11),"") -> 3.8 | AG91: =EOMONTH(E91,-1)+1 -> 45597
A92: CLM-000091 | B92: M-000015 | C92: 3456789012 | D92: 3456789012 | E92: 45548 | F92: 45548 | G92: 45572 | H92: Institutional | I92: 21 | J92: J18.9 | K92: 99223 | O92: 1 | P92: 21788.69 | Q92: 14057.22 | R92: 11245.78 | S92: 2811.44 | T92: Y | V92: 1 | W92: 01 | X92: PLN-MKT-400 | Y92: Marketplace | Z92: Inpatient | AA92: =IFERROR(_xlfn.XLOOKUP($J92,avoidable_ed_reference!$A$2:$A$13,avoidable_ed_reference!$C$2:$C$13),"Not Classified") -> Non-Avoidable | AB92: =IFERROR(_xlfn.XLOOKUP($B92,enrollment!$A$2:$A$801,enrollment!$I$2:$I$801),"") -> TN | AC92: =IFERROR(_xlfn.XLOOKUP($B92,enrollment!$A$2:$A$801,enrollment!$L$2:$L$801),"") -> 42 | AD92: {=_xlfn.IFS(AC92="","Unknown",AC92<18,"0-17",AC92<35,"18-34",AC92<50,"35-49",AC92<65,"50-64",TRUE,"65+")} -> 35-49 | AE92: =IFERROR(_xlfn.XLOOKUP($B92,enrollment!$A$2:$A$801,enrollment!$O$2:$O$801),"") -> 5678901234 | AF92: =IFERROR(_xlfn.XLOOKUP($AE92,providers!$B$2:$B$11,providers!$Q$2:$Q$11),"") -> 3.8 | AG92: =EOMONTH(E92,-1)+1 -> 45536
A93: CLM-000092 | B93: M-000015 | C93: 2233445566 | D93: 2233445566 | E93: 45578 | F93: 45578 | G93: 45594 | H93: Professional | I93: 23 | J93: M54.5 | K93: 99284 | O93: 1 | P93: 1836.79 | Q93: 1020.44 | R93: 816.35 | S93: 204.09 | T93: Y | X93: PLN-MKT-400 | Y93: Marketplace | Z93: ED | AA93: =IFERROR(_xlfn.XLOOKUP($J93,avoidable_ed_reference!$A$2:$A$13,avoidable_ed_reference!$C$2:$C$13),"Not Classified") -> Avoidable | AB93: =IFERROR(_xlfn.XLOOKUP($B93,enrollment!$A$2:$A$801,enrollment!$I$2:$I$801),"") -> TN | AC93: =IFERROR(_xlfn.XLOOKUP($B93,enrollment!$A$2:$A$801,enrollment!$L$2:$L$801),"") -> 42 | AD93: {=_xlfn.IFS(AC93="","Unknown",AC93<18,"0-17",AC93<35,"18-34",AC93<50,"35-49",AC93<65,"50-64",TRUE,"65+")} -> 35-49 | AE93: =IFERROR(_xlfn.XLOOKUP($B93,enrollment!$A$2:$A$801,enrollment!$O$2:$O$801),"") -> 5678901234 | AF93: =IFERROR(_xlfn.XLOOKUP($AE93,providers!$B$2:$B$11,providers!$Q$2:$Q$11),"") -> 3.8 | AG93: =EOMONTH(E93,-1)+1 -> 45566
A94: CLM-000093 | B94: M-000015 | C94: 8901234567 | D94: 8901234567 | E94: 45317 | F94: 45317 | G94: 45338 | H94: Professional | I94: 22 | J94: F32.9 | K94: 90837 | O94: 1 | P94: 256.45 | Q94: 189.96 | R94: 151.97 | S94: 37.99 | T94: Y | X94: PLN-MKT-400 | Y94: Marketplace | Z94: Behavioral Health | AA94: =IFERROR(_xlfn.XLOOKUP($J94,avoidable_ed_reference!$A$2:$A$13,avoidable_ed_reference!$C$2:$C$13),"Not Classified") -> Potentially Avoidable | AB94: =IFERROR(_xlfn.XLOOKUP($B94,enrollment!$A$2:$A$801,enrollment!$I$2:$I$801),"") -> TN | AC94: =IFERROR(_xlfn.XLOOKUP($B94,enrollment!$A$2:$A$801,enrollment!$L$2:$L$801),"") -> 42 | AD94: {=_xlfn.IFS(AC94="","Unknown",AC94<18,"0-17",AC94<35,"18-34",AC94<50,"35-49",AC94<65,"50-64",TRUE,"65+")} -> 35-49 | AE94: =IFERROR(_xlfn.XLOOKUP($B94,enrollment!$A$2:$A$801,enrollment!$O$2:$O$801),"") -> 5678901234 | AF94: =IFERROR(_xlfn.XLOOKUP($AE94,providers!$B$2:$B$11,providers!$Q$2:$Q$11),"") -> 3.8 | AG94: =EOMONTH(E94,-1)+1 -> 45292
A95: CLM-000094 | B95: M-000015 | C95: 5678901234 | D95: 5678901234 | E95: 45304 | F95: 45304 | G95: 45328 | H95: Professional | I95: 11 | J95: E11.9 | K95: 99213 | O95: 1 | P95: 208.48 | Q95: 154.43 | R95: 123.54 | S95: 30.89 | T95: Y | X95: PLN-MKT-400 | Y95: Marketplace | Z95: PCP | AA95: =IFERROR(_xlfn.XLOOKUP($J95,avoidable_ed_reference!$A$2:$A$13,avoidable_ed_reference!$C$2:$C$13),"Not Classified") -> Not Classified | AB95: =IFERROR(_xlfn.XLOOKUP($B95,enrollment!$A$2:$A$801,enrollment!$I$2:$I$801),"") -> TN | AC95: =IFERROR(_xlfn.XLOOKUP($B95,enrollment!$A$2:$A$801,enrollment!$L$2:$L$801),"") -> 42 | AD95: {=_xlfn.IFS(AC95="","Unknown",AC95<18,"0-17",AC95<35,"18-34",AC95<50,"35-49",AC95<65,"50-64",TRUE,"65+")} -> 35-49 | AE95: =IFERROR(_xlfn.XLOOKUP($B95,enrollment!$A$2:$A$801,enrollment!$O$2:$O$801),"") -> 5678901234 | AF95: =IFERROR(_xlfn.XLOOKUP($AE95,providers!$B$2:$B$11,providers!$Q$2:$Q$11),"") -> 3.8 | AG95: =EOMONTH(E95,-1)+1 -> 45292
A96: CLM-000095 | B96: M-000015 | C96: 5678901234 | D96: 5678901234 | E96: 45569 | F96: 45569 | G96: 45604 | H96: Professional | I96: 11 | J96: I10 | K96: 99213 | O96: 1 | P96: 217.63 | Q96: 161.21 | R96: 128.97 | S96: 32.24 | T96: Y | X96: PLN-MKT-400 | Y96: Marketplace | Z96: PCP | AA96: =IFERROR(_xlfn.XLOOKUP($J96,avoidable_ed_reference!$A$2:$A$13,avoidable_ed_reference!$C$2:$C$13),"Not Classified") -> Not Classified | AB96: =IFERROR(_xlfn.XLOOKUP($B96,enrollment!$A$2:$A$801,enrollment!$I$2:$I$801),"") -> TN | AC96: =IFERROR(_xlfn.XLOOKUP($B96,enrollment!$A$2:$A$801,enrollment!$L$2:$L$801),"") -> 42 | AD96: {=_xlfn.IFS(AC96="","Unknown",AC96<18,"0-17",AC96<35,"18-34",AC96<50,"35-49",AC96<65,"50-64",TRUE,"65+")} -> 35-49 | AE96: =IFERROR(_xlfn.XLOOKUP($B96,enrollment!$A$2:$A$801,enrollment!$O$2:$O$801),"") -> 5678901234 | AF96: =IFERROR(_xlfn.XLOOKUP($AE96,providers!$B$2:$B$11,providers!$Q$2:$Q$11),"") -> 3.8 | AG96: =EOMONTH(E96,-1)+1 -> 45566
A97: CLM-000096 | B97: M-000016 | C97: 5678901234 | D97: 5678901234 | E97: 45295 | F97: 45295 | G97: 45317 | H97: Professional | I97: 11 | J97: I10 | K97: 99213 | O97: 1 | P97: 173.81 | Q97: 128.75 | R97: 103 | S97: 25.75 | T97: Y | X97: PLN-MKT-400 | Y97: Marketplace | Z97: PCP | AA97: =IFERROR(_xlfn.XLOOKUP($J97,avoidable_ed_reference!$A$2:$A$13,avoidable_ed_reference!$C$2:$C$13),"Not Classified") -> Not Classified | AB97: =IFERROR(_xlfn.XLOOKUP($B97,enrollment!$A$2:$A$801,enrollment!$I$2:$I$801),"") -> TN | AC97: =IFERROR(_xlfn.XLOOKUP($B97,enrollment!$A$2:$A$801,enrollment!$L$2:$L$801),"") -> 82 | AD97: {=_xlfn.IFS(AC97="","Unknown",AC97<18,"0-17",AC97<35,"18-34",AC97<50,"35-49",AC97<65,"50-64",TRUE,"65+")} -> 65+ | AE97: =IFERROR(_xlfn.XLOOKUP($B97,enrollment!$A$2:$A$801,enrollment!$O$2:$O$801),"") -> 5678901234 | AF97: =IFERROR(_xlfn.XLOOKUP($AE97,providers!$B$2:$B$11,providers!$Q$2:$Q$11),"") -> 3.8 | AG97: =EOMONTH(E97,-1)+1 -> 45292
A98: CLM-000097 | B98: M-000016 | C98: 5678901234 | D98: 5678901234 | E98: 45421 | F98: 45421 | G98: 45454 | H98: Professional | I98: 20 | J98: J06.9 | K98: 99213 | O98: 1 | P98: 147.71 | Q98: 113.62 | R98: 90.9 | S98: 22.72 | T98: Y | X98: PLN-MKT-400 | Y98: Marketplace | Z98: Urgent Care | AA98: =IFERROR(_xlfn.XLOOKUP($J98,avoidable_ed_reference!$A$2:$A$13,avoidable_ed_reference!$C$2:$C$13),"Not Classified") -> Avoidable | AB98: =IFERROR(_xlfn.XLOOKUP($B98,enrollment!$A$2:$A$801,enrollment!$I$2:$I$801),"") -> TN | AC98: =IFERROR(_xlfn.XLOOKUP($B98,enrollment!$A$2:$A$801,enrollment!$L$2:$L$801),"") -> 82 | AD98: {=_xlfn.IFS(AC98="","Unknown",AC98<18,"0-17",AC98<35,"18-34",AC98<50,"35-49",AC98<65,"50-64",TRUE,"65+")} -> 65+ | AE98: =IFERROR(_xlfn.XLOOKUP($B98,enrollment!$A$2:$A$801,enrollment!$O$2:$O$801),"") -> 5678901234 | AF98: =IFERROR(_xlfn.XLOOKUP($AE98,providers!$B$2:$B$11,providers!$Q$2:$Q$11),"") -> 3.8 | AG98: =EOMONTH(E98,-1)+1 -> 45413
A99: CLM-000098 | B99: M-000016 | C99: 8901234567 | D99: 8901234567 | E99: 45361 | F99: 45361 | G99: 45375 | H99: Professional | I99: 23 | J99: R07.9 | K99: 99284 | O99: 1 | P99: 1587.96 | Q99: 882.2 | R99: 705.76 | S99: 176.44 | T99: Y | X99: PLN-MKT-400 | Y99: Marketplace | Z99: ED | AA99: =IFERROR(_xlfn.XLOOKUP($J99,avoidable_ed_reference!$A$2:$A$13,avoidable_ed_reference!$C$2:$C$13),"Not Classified") -> Non-Avoidable | AB99: =IFERROR(_xlfn.XLOOKUP($B99,enrollment!$A$2:$A$801,enrollment!$I$2:$I$801),"") -> TN | AC99: =IFERROR(_xlfn.XLOOKUP($B99,enrollment!$A$2:$A$801,enrollment!$L$2:$L$801),"") -> 82 | AD99: {=_xlfn.IFS(AC99="","Unknown",AC99<18,"0-17",AC99<35,"18-34",AC99<50,"35-49",AC99<65,"50-64",TRUE,"65+")} -> 65+ | AE99: =IFERROR(_xlfn.XLOOKUP($B99,enrollment!$A$2:$A$801,enrollment!$O$2:$O$801),"") -> 5678901234 | AF99: =IFERROR(_xlfn.XLOOKUP($AE99,providers!$B$2:$B$11,providers!$Q$2:$Q$11),"") -> 3.8 | AG99: =EOMONTH(E99,-1)+1 -> 45352
A100: CLM-000099 | B100: M-000016 | C100: 6789012345 | D100: 6789012345 | E100: 45358 | F100: 45358 | G100: 45391 | H100: Professional | I100: 23 | J100: N39.0 | K100: 99284 | O100: 1 | P100: 2224.42 | Q100: 1235.79 | R100: 988.63 | S100: 247.16 | T100: Y | X100: PLN-MKT-400 | Y100: Marketplace | Z100: ED | AA100: =IFERROR(_xlfn.XLOOKUP($J100,avoidable_ed_reference!$A$2:$A$13,avoidable_ed_reference!$C$2:$C$13),"Not Classified") -> Avoidable | AB100: =IFERROR(_xlfn.XLOOKUP($B100,enrollment!$A$2:$A$801,enrollment!$I$2:$I$801),"") -> TN | AC100: =IFERROR(_xlfn.XLOOKUP($B100,enrollment!$A$2:$A$801,enrollment!$L$2:$L$801),"") -> 82 | AD100: {=_xlfn.IFS(AC100="","Unknown",AC100<18,"0-17",AC100<35,"18-34",AC100<50,"35-49",AC100<65,"50-64",TRUE,"65+")} -> 65+ | AE100: =IFERROR(_xlfn.XLOOKUP($B100,enrollment!$A$2:$A$801,enrollment!$O$2:$O$801),"") -> 5678901234 | AF100: =IFERROR(_xlfn.XLOOKUP($AE100,providers!$B$2:$B$11,providers!$Q$2:$Q$11),"") -> 3.8 | AG100: =EOMONTH(E100,-1)+1 -> 45352
A101: CLM-000100 | B101: M-000016 | C101: 2233445566 | D101: 2233445566 | E101: 45364 | F101: 45364 | G101: 45384 | H101: Professional | I101: 23 | J101: R07.9 | K101: 99284 | O101: 1 | P101: 2451.37 | Q101: 1361.87 | R101: 1089.5 | S101: 272.37 | T101: Y | X101: PLN-MKT-400 | Y101: Marketplace | Z101: ED | AA101: =IFERROR(_xlfn.XLOOKUP($J101,avoidable_ed_reference!$A$2:$A$13,avoidable_ed_reference!$C$2:$C$13),"Not Classified") -> Non-Avoidable | AB101: =IFERROR(_xlfn.XLOOKUP($B101,enrollment!$A$2:$A$801,enrollment!$I$2:$I$801),"") -> TN | AC101: =IFERROR(_xlfn.XLOOKUP($B101,enrollment!$A$2:$A$801,enrollment!$L$2:$L$801),"") -> 82 | AD101: {=_xlfn.IFS(AC101="","Unknown",AC101<18,"0-17",AC101<35,"18-34",AC101<50,"35-49",AC101<65,"50-64",TRUE,"65+")} -> 65+ | AE101: =IFERROR(_xlfn.XLOOKUP($B101,enrollment!$A$2:$A$801,enrollment!$O$2:$O$801),"") -> 5678901234 | AF101: =IFERROR(_xlfn.XLOOKUP($AE101,providers!$B$2:$B$11,providers!$Q$2:$Q$11),"") -> 3.8 | AG101: =EOMONTH(E101,-1)+1 -> 45352
A102: CLM-000101 | B102: M-000016 | C102: 5678901234 | D102: 5678901234 | E102: 45366 | F102: 45366 | G102: 45393 | H102: Professional | I102: 11 | J102: I10 | K102: 99213 | O102: 1 | P102: 182.1 | Q102: 134.89 | R102: 107.91 | S102: 26.98 | T102: Y | X102: PLN-MKT-400 | Y102: Marketplace | Z102: PCP | AA102: =IFERROR(_xlfn.XLOOKUP($J102,avoidable_ed_reference!$A$2:$A$13,avoidable_ed_reference!$C$2:$C$13),"Not Classified") -> Not Classified | AB102: =IFERROR(_xlfn.XLOOKUP($B102,enrollment!$A$2:$A$801,enrollment!$I$2:$I$801),"") -> TN | AC102: =IFERROR(_xlfn.XLOOKUP($B102,enrollment!$A$2:$A$801,enrollment!$L$2:$L$801),"") -> 82 | AD102: {=_xlfn.IFS(AC102="","Unknown",AC102<18,"0-17",AC102<35,"18-34",AC102<50,"35-49",AC102<65,"50-64",TRUE,"65+")} -> 65+ | AE102: =IFERROR(_xlfn.XLOOKUP($B102,enrollment!$A$2:$A$801,enrollment!$O$2:$O$801),"") -> 5678901234 | AF102: =IFERROR(_xlfn.XLOOKUP($AE102,providers!$B$2:$B$11,providers!$Q$2:$Q$11),"") -> 3.8 | AG102: =EOMONTH(E102,-1)+1 -> 45352
A103: CLM-000102 | B103: M-000016 | C103: 5678901234 | D103: 5678901234 | E103: 45482 | F103: 45482 | G103: 45508 | H103: Professional | I103: 11 | J103: E11.9 | K103: 99213 | O103: 1 | P103: 207.72 | Q103: 153.87 | R103: 123.1 | S103: 30.77 | T103: Y | X103: PLN-MKT-400 | Y103: Marketplace | Z103: PCP | AA103: =IFERROR(_xlfn.XLOOKUP($J103,avoidable_ed_reference!$A$2:$A$13,avoidable_ed_reference!$C$2:$C$13),"Not Classified") -> Not Classified | AB103: =IFERROR(_xlfn.XLOOKUP($B103,enrollment!$A$2:$A$801,enrollment!$I$2:$I$801),"") -> TN | AC103: =IFERROR(_xlfn.XLOOKUP($B103,enrollment!$A$2:$A$801,enrollment!$L$2:$L$801),"") -> 82 | AD103: {=_xlfn.IFS(AC103="","Unknown",AC103<18,"0-17",AC103<35,"18-34",AC103<50,"35-49",AC103<65,"50-64",TRUE,"65+")} -> 65+ | AE103: =IFERROR(_xlfn.XLOOKUP($B103,enrollment!$A$2:$A$801,enrollment!$O$2:$O$801),"") -> 5678901234 | AF103: =IFERROR(_xlfn.XLOOKUP($AE103,providers!$B$2:$B$11,providers!$Q$2:$Q$11),"") -> 3.8 | AG103: =EOMONTH(E103,-1)+1 -> 45474
A104: CLM-000103 | B104: M-000017 | C104: 2345678901 | D104: 2345678901 | E104: 45544 | F104: 45544 | G104: 45576 | H104: Professional | I104: 22 | J104: F32.9 | K104: 90837 | O104: 1 | P104: 241.18 | Q104: 178.65 | R104: 142.92 | S104: 35.73 | T104: Y | X104: PLN-MA-100 | Y104: Medicare Advantage | Z104: Behavioral Health | AA104: =IFERROR(_xlfn.XLOOKUP($J104,avoidable_ed_reference!$A$2:$A$13,avoidable_ed_reference!$C$2:$C$13),"Not Classified") -> Potentially Avoidable | AB104: =IFERROR(_xlfn.XLOOKUP($B104,enrollment!$A$2:$A$801,enrollment!$I$2:$I$801),"") -> GA | AC104: =IFERROR(_xlfn.XLOOKUP($B104,enrollment!$A$2:$A$801,enrollment!$L$2:$L$801),"") -> 65 | AD104: {=_xlfn.IFS(AC104="","Unknown",AC104<18,"0-17",AC104<35,"18-34",AC104<50,"35-49",AC104<65,"50-64",TRUE,"65+")} -> 65+ | AE104: =IFERROR(_xlfn.XLOOKUP($B104,enrollment!$A$2:$A$801,enrollment!$O$2:$O$801),"") -> 8901234567 | AF104: =IFERROR(_xlfn.XLOOKUP($AE104,providers!$B$2:$B$11,providers!$Q$2:$Q$11),"") -> 3.7 | AG104: =EOMONTH(E104,-1)+1 -> 45536
... A108: CLM-000107 | B108: M-000018 | C108: 5678901234 | D108: 5678901234 | E108: 45463 | F108: 45463 | G108: 45491 | H108: Professional | I108: 11 | J108: E11.9 | K108: 99213 | O108: 1 | P108: 234.4 | Q108: 173.63 | R108: 138.9 | S108: 34.73 | T108: Y | X108: PLN-COM-250 | Y108: Commercial | Z108: PCP | AA108: =IFERROR(_xlfn.XLOOKUP($J108,avoidable_ed_reference!$A$2:$A$13,avoidable_ed_reference!$C$2:$C$13),"Not Classified") -> Not Classified | AB108: =IFERROR(_xlfn.XLOOKUP($B108,enrollment!$A$2:$A$801,enrollment!$I$2:$I$801),"") -> TN | AC108: =IFERROR(_xlfn.XLOOKUP($B108,enrollment!$A$2:$A$801,enrollment!$L$2:$L$801),"") -> 35 | AD108: {=_xlfn.IFS(AC108="","Unknown",AC108<18,"0-17",AC108<35,"18-34",AC108<50,"35-49",AC108<65,"50-64",TRUE,"65+")} -> 35-49 | AE108: =IFERROR(_xlfn.XLOOKUP($B108,enrollment!$A$2:$A$801,enrollment!$O$2:$O$801),"") -> 5678901234 | AF108: =IFERROR(_xlfn.XLOOKUP($AE108,providers!$B$2:$B$11,providers!$Q$2:$Q$11),"") -> 3.8 | AG108: =EOMONTH(E108,-1)+1 -> 45444
A109: CLM-000108 | B109: M-000018 | C109: 6789012345 | D109: 6789012345 | E109: 45636 | F109: 45636 | G109: 45663 | H109: Pharmacy | J109: C34.90 | L109: 00169430730 | M109: Semaglutide | N109: GLP-1 Agonist | O109: 1 | P109: 979.62 | Q109: 890.56 | R109: 712.45 | S109: 178.11 | T109: Y | X109: PLN-COM-250 | Y109: Commercial | Z109: Specialty Rx | AA109: =IFERROR(_xlfn.XLOOKUP($J109,avoidable_ed_reference!$A$2:$A$13,avoidable_ed_reference!$C$2:$C$13),"Not Classified") -> Not Classified | AB109: =IFERROR(_xlfn.XLOOKUP($B109,enrollment!$A$2:$A$801,enrollment!$I$2:$I$801),"") -> TN | AC109: =IFERROR(_xlfn.XLOOKUP($B109,enrollment!$A$2:$A$801,enrollment!$L$2:$L$801),"") -> 35 | AD109: {=_xlfn.IFS(AC109="","Unknown",AC109<18,"0-17",AC109<35,"18-34",AC109<50,"35-49",AC109<65,"50-64",TRUE,"65+")} -> 35-49 | AE109: =IFERROR(_xlfn.XLOOKUP($B109,enrollment!$A$2:$A$801,enrollment!$O$2:$O$801),"") -> 5678901234 | AF109: =IFERROR(_xlfn.XLOOKUP($AE109,providers!$B$2:$B$11,providers!$Q$2:$Q$11),"") -> 3.8 | AG109: =EOMONTH(E109,-1)+1 -> 45627
A110: CLM-000109 | B110: M-000018 | C110: 8901234567 | D110: 8901234567 | E110: 45425 | F110: 45425 | G110: 45447 | H110: Pharmacy | J110: C34.90 | L110: 00169430730 | M110: Semaglutide | N110: GLP-1 Agonist | O110: 1 | P110: 967.67 | Q110: 879.7 | R110: 703.76 | S110: 175.94 | T110: Y | X110: PLN-COM-250 | Y110: Commercial | Z110: Specialty Rx | AA110: =IFERROR(_xlfn.XLOOKUP($J110,avoidable_ed_reference!$A$2:$A$13,avoidable_ed_reference!$C$2:$C$13),"Not Classified") -> Not Classified | AB110: =IFERROR(_xlfn.XLOOKUP($B110,enrollment!$A$2:$A$801,enrollment!$I$2:$I$801),"") -> TN | AC110: =IFERROR(_xlfn.XLOOKUP($B110,enrollment!$A$2:$A$801,enrollment!$L$2:$L$801),"") -> 35 | AD110: {=_xlfn.IFS(AC110="","Unknown",AC110<18,"0-17",AC110<35,"18-34",AC110<50,"35-49",AC110<65,"50-64",TRUE,"65+")} -> 35-49 | AE110: =IFERROR(_xlfn.XLOOKUP($B110,enrollment!$A$2:$A$801,enrollment!$O$2:$O$801),"") -> 5678901234 | AF110: =IFERROR(_xlfn.XLOOKUP($AE110,providers!$B$2:$B$11,providers!$Q$2:$Q$11),"") -> 3.8 | AG110: =EOMONTH(E110,-1)+1 -> 45413
A111: CLM-000110 | B111: M-000018 | C111: 5678901234 | D111: 5678901234 | E111: 45555 | F111: 45555 | G111: 45584 | H111: Professional | I111: 11 | J111: J06.9 | K111: 99213 | O111: 1 | P111: 224.07 | Q111: 165.98 | R111: 132.78 | S111: 33.2 | T111: Y | X111: PLN-COM-250 | Y111: Commercial | Z111: PCP | AA111: =IFERROR(_xlfn.XLOOKUP($J111,avoidable_ed_reference!$A$2:$A$13,avoidable_ed_reference!$C$2:$C$13),"Not Classified") -> Avoidable | AB111: =IFERROR(_xlfn.XLOOKUP($B111,enrollment!$A$2:$A$801,enrollment!$I$2:$I$801),"") -> TN | AC111: =IFERROR(_xlfn.XLOOKUP($B111,enrollment!$A$2:$A$801,enrollment!$L$2:$L$801),"") -> 35 | AD111: {=_xlfn.IFS(AC111="","Unknown",AC111<18,"0-17",AC111<35,"18-34",AC111<50,"35-49",AC111<65,"50-64",TRUE,"65+")} -> 35-49 | AE111: =IFERROR(_xlfn.XLOOKUP($B111,enrollment!$A$2:$A$801,enrollment!$O$2:$O$801),"") -> 5678901234 | AF111: =IFERROR(_xlfn.XLOOKUP($AE111,providers!$B$2:$B$11,providers!$Q$2:$Q$11),"") -> 3.8 | AG111: =EOMONTH(E111,-1)+1 -> 45536
A112: CLM-000111 | B112: M-000018 | C112: 5678901234 | D112: 5678901234 | E112: 45511 | F112: 45511 | G112: 45532 | H112: Professional | I112: 20 | J112: J06.9 | K112: 99213 | O112: 1 | P112: 179.3 | Q112: 137.92 | R112: 110.34 | S112: 27.58 | T112: Y | X112: PLN-COM-250 | Y112: Commercial | Z112: Urgent Care | AA112: =IFERROR(_xlfn.XLOOKUP($J112,avoidable_ed_reference!$A$2:$A$13,avoidable_ed_reference!$C$2:$C$13),"Not Classified") -> Avoidable | AB112: =IFERROR(_xlfn.XLOOKUP($B112,enrollment!$A$2:$A$801,enrollment!$I$2:$I$801),"") -> TN | AC112: =IFERROR(_xlfn.XLOOKUP($B112,enrollment!$A$2:$A$801,enrollment!$L$2:$L$801),"") -> 35 | AD112: {=_xlfn.IFS(AC112="","Unknown",AC112<18,"0-17",AC112<35,"18-34",AC112<50,"35-49",AC112<65,"50-64",TRUE,"65+")} -> 35-49 | AE112: =IFERROR(_xlfn.XLOOKUP($B112,enrollment!$A$2:$A$801,enrollment!$O$2:$O$801),"") -> 5678901234 | AF112: =IFERROR(_xlfn.XLOOKUP($AE112,providers!$B$2:$B$11,providers!$Q$2:$Q$11),"") -> 3.8 | AG112: =EOMONTH(E112,-1)+1 -> 45505
...

Sheet member_months
A1: member_id | B1: plan_id | C1: lob | D1: state | E1: calendar_month | F1: member_months
A2: M-000001 | B2: PLN-COM-250 | C2: Commercial | D2: KY | E2: 45323 | F2: 1
A3: M-000001 | B3: PLN-COM-250 | C3: Commercial | D3: KY | E3: 45352 | F3: 1
A4: M-000001 | B4: PLN-COM-250 | C4: Commercial | D4: KY | E4: 45383 | F4: 1
A5: M-000001 | B5: PLN-COM-250 | C5: Commercial | D5: KY | E5: 45413 | F5: 1
A6: M-000001 | B6: PLN-COM-250 | C6: Commercial | D6: KY | E6: 45444 | F6: 1
A7: M-000001 | B7: PLN-COM-250 | C7: Commercial | D7: KY | E7: 45474 | F7: 1
A8: M-000001 | B8: PLN-COM-250 | C8: Commercial | D8: KY | E8: 45505 | F8: 1
A9: M-000001 | B9: PLN-COM-250 | C9: Commercial | D9: KY | E9: 45536 | F9: 1
A10: M-000001 | B10: PLN-COM-250 | C10: Commercial | D10: KY | E10: 45566 | F10: 1
A11: M-000001 | B11: PLN-COM-250 | C11: Commercial | D11: KY | E11: 45597 | F11: 1
A12: M-000001 | B12: PLN-COM-250 | C12: Commercial | D12: KY | E12: 45627 | F12: 1
A13: M-000002 | B13: PLN-MKT-401 | C13: Marketplace | D13: KY | E13: 45352 | F13: 1
... A8463: M-000800 | B8463: PLN-MA-100 | C8463: Medicare Advantage | D8463: GA | E8463: 45627 | F8463: 1

Sheet enrollment
A1: member_id | B1: subscriber_id | C1: enrollment_start_date | D1: enrollment_end_date | E1: plan_id | F1: lob | G1: product_name | H1: group_id | I1: state | J1: county | K1: zip | L1: age | M1: gender | N1: risk_score | O1: attributed_pcp_npi | P1: disenrollment_reason
A2: M-000001 | B2: S-000001 | C2: 45341 | E2: PLN-COM-250 | F2: Commercial | G2: PPO Gold | H2: GRP-ACME-01 | I2: KY | J2: Jefferson | K2: 40202 | L2: 53 | M2: F | N2: 0.82 | O2: 9012345678
A3: M-000002 | B3: S-000002 | C3: 45379 | E3: PLN-MKT-401 | F3: Marketplace | G3: Bronze HMO | I3: KY | J3: Jefferson | K3: 40202 | L3: 36 | M3: M | N3: 0.88 | O3: 9012345678
A4: M-000003 | B4: S-000003 | C4: 45303 | D4: 45448 | E4: PLN-MKT-400 | F4: Marketplace | G4: Silver HMO | I4: GA | J4: Fulton | K4: 30303 | L4: 24 | M4: M | N4: 1.27 | O4: 8901234567 | P4: Premium Affordability
A5: M-000004 | B5: S-000004 | C5: 45317 | E5: PLN-MKT-401 | F5: Marketplace | G5: Bronze HMO | I5: TN | J5: Davidson | K5: 37203 | L5: 71 | M5: M | N5: 2.08 | O5: 5678901234
A6: M-000005 | B6: S-000005 | C6: 45342 | D6: 45474 | E6: PLN-MKT-401 | F6: Marketplace | G6: Bronze HMO | I6: TN | J6: Rural-Cannon | K6: 37087 | L6: 53 | M6: F | N6: 1.03 | P6: Network Adequacy
